Workbook
Name codmun: #REF!
Name lista_mun: OFFSET(INDIRECT(#REF!),,,#REF!)
Name niveles: #REF!
Name resultados_2019: '[1]5'!$B$1:$G$60
Name resultados_2020: '[1]6'!$B$1:$G$60
Name resultados_2021: '[1]7'!$B$1:$G$60

Sheet Estructura
A1: FACTOR 1 | B1: CONDICIONES HABILITANTES | D1: Periodo | E1: Último | F1: Pilar | G1: Subpilar | H1: Subpilar en el pilar | I1: Variable en el subpilar | J1: Variable en el pilar
A2: PILAR 1: INSTITUCIONES | C2: INVERSA | D2: Corte | E2: Año | F2: =1/13 -> 0.076923077
A3: INS-1 | B3: Desempeño administrativo | G3: =$F$2/4 -> 0.019230769 | H3: =G3/$F$2 -> 0.25 | L3: 2021 | M3: =COUNTIF(E:E,L3) -> 1 | N3: =M3/92 -> 0.010869565
A4: INS-1-1 | B4: Gestión de recursos | C4: No | D4: 2019-2023 | E4: =IFERROR(MID(D4,6,4),"") -> 2023 | I4: =1/COUNTBLANK($H$4:$H$5) -> 0.5 | J4: =I4*$H$3 -> 0.125 | L4: 2022 | M4: =COUNTIF(E:E,L4) -> 7 | N4: =M4/92 -> 0.076086957
A5: INS-1-2 | B5: Índice de Gobierno Digital para el Estado | C5: No | D5: 2022-2024 | E5: =IFERROR(MID(D5,6,4),"") -> 2024 | I5: =1/COUNTBLANK($H$4:$H$5) -> 0.5 | J5: =I5*$H$3 -> 0.125 | L5: 2023 | M5: =COUNTIF(E:E,L5) -> 23 | N5: =M5/92 -> 0.25
A6: INS-2 | B6: Gestión fiscal | E6: =IFERROR(MID(D6,6,4),"") | G6: =$F$2/4 -> 0.019230769 | H6: =G6/$F$2 -> 0.25 | L6: 2024 | M6: =COUNTIF(E:E,L6) -> 60 | N6: =M6/92 -> 0.65217391
A7: INS-2-1 | B7: Autonomía fiscal | C7: No | D7: 2018-2024 | E7: =IFERROR(MID(D7,6,4),"") -> 2024 | I7: =1/COUNTBLANK($H$7:$H$9) -> 0.33333333 | J7: =I7*$H$6 -> 0.083333333 | L7: 2025 | M7: =COUNTIF(E:E,L7) -> 1 | N7: =M7/92 -> 0.010869565
A8: INS-2-2 | B8: Capacidad local de recaudo | C8: No | D8: 2017-2023 | E8: =IFERROR(MID(D8,6,4),"") -> 2023 | I8: =1/COUNTBLANK($H$7:$H$9) -> 0.33333333 | J8: =I8*$H$6 -> 0.083333333
A9: INS-2-3 | B9: Capacidad de ahorro | C9: No | D9: 2017-2023 | E9: =IFERROR(MID(D9,6,4),"") -> 2023 | I9: =1/COUNTBLANK($H$7:$H$9) -> 0.33333333 | J9: =I9*$H$6 -> 0.083333333
A10: INS-3 | B10: Transparencia y contratación pública | E10: =IFERROR(MID(D10,6,4),"") | G10: =$F$2/4 -> 0.019230769 | H10: =G10/$F$2 -> 0.25
A11: INS-3-1 | B11: Índice de Gobierno Digital para la Sociedad | C11: No | D11: 2022-2024 | E11: =IFERROR(MID(D11,6,4),"") -> 2024 | I11: =1/COUNTBLANK($H$11:$H$12) -> 0.5 | J11: =I11*$H$10 -> 0.125
A12: INS-3-2 | B12: Procesos de contratación en SECOP II | C12: No | D12: 2020-2024 | E12: =IFERROR(MID(D12,6,4),"") -> 2024 | I12: =1/COUNTBLANK($H$11:$H$12) -> 0.5 | J12: =I12*$H$10 -> 0.125
A13: INS-4 | B13: Seguridad y justicia | E13: =IFERROR(MID(D13,6,4),"") | G13: =$F$2/4 -> 0.019230769 | H13: =G13/$F$2 -> 0.25
A14: INS-4-1 | B14: Tasa de homicidios | C14: Sí | D14: 2018-2024 | E14: =IFERROR(MID(D14,6,4),"") -> 2024 | I14: =1/COUNTBLANK($H$14:$H$19) -> 0.16666667 | J14: =I14*$H$13 -> 0.041666667
A15: INS-4-2 | B15: Tasa de hurtos | C15: Sí | D15: 2018-2024 | E15: =IFERROR(MID(D15,6,4),"") -> 2024 | I15: =1/COUNTBLANK($H$14:$H$19) -> 0.16666667 | J15: =I15*$H$13 -> 0.041666667
A16: INS-4-3 | B16: Tasa de extorsión | C16: Sí | D16: 2018-2024 | E16: =IFERROR(MID(D16,6,4),"") -> 2024 | I16: =1/COUNTBLANK($H$14:$H$19) -> 0.16666667 | J16: =I16*$H$13 -> 0.041666667
A17: INS-4-4 | B17: Eficiencia de la justicia | C17: No | D17: 2018-2024 | E17: =IFERROR(MID(D17,6,4),"") -> 2024 | I17: =1/COUNTBLANK($H$14:$H$19) -> 0.16666667 | J17: =I17*$H$13 -> 0.041666667
A18: INS-4-5 | B18: Productividad de jueces | C18: No | D18: 2017-2024 | E18: =IFERROR(MID(D18,6,4),"") -> 2024 | I18: =1/COUNTBLANK($H$14:$H$19) -> 0.16666667 | J18: =I18*$H$13 -> 0.041666667
A19: INS-4-6 | B19: Eficiencia de los métodos de resolución de conflictos | C19: No | D19: 2018-2024 | E19: =IFERROR(MID(D19,6,4),"") -> 2024 | I19: =1/COUNTBLANK($H$14:$H$19) -> 0.16666667 | J19: =I19*$H$13 -> 0.041666667
A20: PILAR 2: INFRAESTRUCTURA Y EQUIPAMIENTO | E20: =IFERROR(MID(D20,6,4),"") | F20: =F2 -> 0.076923077
A21: INF-1 | B21: Infraestructura de servicios | E21: =IFERROR(MID(D21,6,4),"") | G21: =$F$20/3 -> 0.025641026 | H21: =G21/$F$20 -> 0.33333333
A22: INF-1-1 | B22: Cobertura de acueducto | C22: No | D22: 2018-2022 | E22: =IFERROR(MID(D22,6,4),"") -> 2022 | I22: =1/COUNTBLANK($H$22:$H$26) -> 0.2 | J22: =I22*$H$21 -> 0.066666667
A23: INF-1-2 | B23: Cobertura efectiva de gas natural | C23: No | D23: 2018-2024 | E23: =IFERROR(MID(D23,6,4),"") -> 2024 | I23: =1/COUNTBLANK($H$22:$H$26) -> 0.2 | J23: =I23*$H$21 -> 0.066666667
A24: INF-1-3 | B24: Cobertura de la energía eléctrica | C24: No | D24: 2018-2023 | E24: =IFERROR(MID(D24,6,4),"") -> 2023 | I24: =1/COUNTBLANK($H$22:$H$26) -> 0.2 | J24: =I24*$H$21 -> 0.066666667
A25: INF-1-4 | B25: Costo de la energía eléctrica | C25: Sí | D25: 2018-2024 | E25: =IFERROR(MID(D25,6,4),"") -> 2024 | I25: =1/COUNTBLANK($H$22:$H$26) -> 0.2 | J25: =I25*$H$21 -> 0.066666667
A26: INF-1-5 | B26: Cobertura de alcantarillado | C26: No | D26: 2018-2022 | E26: =IFERROR(MID(D26,6,4),"") -> 2022 | I26: =1/COUNTBLANK($H$22:$H$26) -> 0.2 | J26: =I26*$H$21 -> 0.066666667
A27: INF-2 | B27: Conectividad | E27: =IFERROR(MID(D27,6,4),"") | G27: =G21 -> 0.025641026 | H27: =G27/$F$20 -> 0.33333333
A28: INF-2-1 | B28: Costo de transporte terrestre a mercado interno | C28: Sí | D28: 2018-2024 | E28: =IFERROR(MID(D28,6,4),"") -> 2024 | I28: =1/COUNTBLANK($H$28:$H$32) -> 0.2 | J28: =I28*$H$27 -> 0.066666667
A29: INF-2-2 | B29: Costo de transporte terrestre a aduanas | C29: Sí | D29: 2018-2024 | E29: =IFERROR(MID(D29,6,4),"") -> 2024 | I29: =1/COUNTBLANK($H$28:$H$32) -> 0.2 | J29: =I29*$H$27 -> 0.066666667
A30: INF-2-3 | B30: Pasajeros movilizados vía aérea | C30: No | D30: 2018-2024 | E30: =IFERROR(MID(D30,6,4),"") -> 2024 | I30: =1/COUNTBLANK($H$28:$H$32) -> 0.2 | J30: =I30*$H$27 -> 0.066666667
A31: INF-2-4 | B31: Índice de conectividad aérea | C31: No | D31: 2018-2024 | E31: =IFERROR(MID(D31,6,4),"") -> 2024 | I31: =1/COUNTBLANK($H$28:$H$32) -> 0.2 | J31: =I31*$H$27 -> 0.066666667
A32: INF-2-5 | B32: Pasajeros movilizados por transporte público | C32: No | D32: 2019-2025 | E32: =IFERROR(MID(D32,6,4),"") -> 2025 | I32: =1/COUNTBLANK($H$28:$H$32) -> 0.2 | J32: =I32*$H$27 -> 0.066666667
A33: INF-3 | B33: Oferta Cultural | E33: =IFERROR(MID(D33,6,4),"") | G33: =G21 -> 0.025641026 | H33: =G33/$F$20 -> 0.33333333
A34: INF-3-1 | B34: Ejemplares de biblioteca | C34: No | D34: 2018-2023 | E34: =IFERROR(MID(D34,6,4),"") -> 2023 | I34: =1/COUNTBLANK($H$34:$H$36) -> 0.33333333 | J34: =I34*$H$33 -> 0.11111111
A35: INF-3-2 | B35: Museos | C35: No | D35: 2019-2024 | E35: =IFERROR(MID(D35,6,4),"") -> 2024 | I35: =1/COUNTBLANK($H$34:$H$36) -> 0.33333333 | J35: =I35*$H$33 -> 0.11111111
A36: INF-3-3 | B36: Bienes de interés cultural | C36: No | D36: 2019-2024 | E36: =IFERROR(MID(D36,6,4),"") -> 2024 | I36: =1/COUNTBLANK($H$34:$H$36) -> 0.33333333 | J36: =I36*$H$33 -> 0.11111111
A37: PILAR 3: Adopción TIC | E37: =IFERROR(MID(D37,6,4),"") | F37: =F2 -> 0.076923077
A38: TIC-1 | B38: Infraestructura TIC | E38: =IFERROR(MID(D38,6,4),"") | G38: =F37/2 -> 0.038461538 | H38: =G38/$F$37 -> 0.5
A39: TIC-1-1 | B39: Penetración de internet banda ancha fijo | C39: No | D39: 2018-2023 | E39: =IFERROR(MID(D39,6,4),"") -> 2023 | I39: =1/COUNTBLANK($H$39:$H$42) -> 0.25 | J39: =I39*$H$38 -> 0.125
A40: TIC-1-2 | B40: Ancho de banda de internet | C40: No | D40: 2018-2023 | E40: =IFERROR(MID(D40,6,4),"") -> 2023 | I40: =1/COUNTBLANK($H$39:$H$42) -> 0.25 | J40: =I40*$H$38 -> 0.125
A41: TIC-1-3 | B41: Hogares con computador, portátil o tablet | C41: No | D41: 2020-2024 | E41: =IFERROR(MID(D41,6,4),"") -> 2024 | I41: =1/COUNTBLANK($H$39:$H$42) -> 0.25 | J41: =I41*$H$38 -> 0.125
A42: TIC-1-4 | B42: Uso de Internet | C42: No | D42: 2020-2024 | E42: =IFERROR(MID(D42,6,4),"") -> 2024 | I42: =1/COUNTBLANK($H$39:$H$42) -> 0.25 | J42: =I42*$H$38 -> 0.125
A43: TIC-2 | B43: Capacidades TIC | E43: =IFERROR(MID(D43,6,4),"") | G43: =G38 -> 0.038461538 | H43: =H38 -> 0.5
A44: TIC-2-1 | B44: Matriculados en programas TIC | C44: No | D44: 2018-2024 | E44: =IFERROR(MID(D44,6,4),"") -> 2024 | I44: =1/COUNTBLANK($H$44:$H$46) -> 0.33333333 | J44: =I44*$H$43 -> 0.16666667
A45: TIC-2-2 | B45: Graduados en programas TIC | C45: No | D45: 2018-2024 | E45: =IFERROR(MID(D45,6,4),"") -> 2024 | I45: =1/COUNTBLANK($H$44:$H$46) -> 0.33333333 | J45: =I45*$H$43 -> 0.16666667
A46: TIC-2-3 | B46: Programas TIC | C46: No | D46: 2018-2024 | E46: =IFERROR(MID(D46,6,4),"") -> 2024 | I46: =1/COUNTBLANK($H$44:$H$46) -> 0.33333333 | J46: =I46*$H$43 -> 0.16666667
A47: PILAR 4: SOSTENIBILIDAD AMBIENTAL | E47: =IFERROR(MID(D47,6,4),"") | F47: =F2 -> 0.076923077
A48: AMB-1 | B48: Activos naturales | E48: =IFERROR(MID(D48,6,4),"") | G48: =$F$47/2 -> 0.038461538 | H48: =G48/$F$47 -> 0.5
A49: AMB-1-1 | B49: Eficiencia energética | C49: Sí | D49: 2018-2023 | E49: =IFERROR(MID(D49,6,4),"") -> 2023 | I49: =1/COUNTBLANK($H$49:$H$50) -> 0.5 | J49: =I49*$H$48 -> 0.25
A50: AMB-1-2 | B50: Eficiencia en el uso del agua | C50: Sí | D50: 2018-2023 | E50: =IFERROR(MID(D50,6,4),"") -> 2023 | I50: =1/COUNTBLANK($H$49:$H$50) -> 0.5 | J50: =I50*$H$48 -> 0.25
A51: AMB-2 | B51: Crecimiento verde | E51: =IFERROR(MID(D51,6,4),"") | G51: =$F$47/2 -> 0.038461538 | H51: =G51/$F$47 -> 0.5
A52: AMB-2-1 | B52: Negocios verdes | C52: No | D52: 2018-2022 | E52: =IFERROR(MID(D52,6,4),"") -> 2022 | I52: =1/COUNTBLANK($H$52:$H$53) -> 0.5 | J52: =I52*$H$51 -> 0.25
A53: AMB-2-2 | B53: Empleos verdes | C53: No | D53: 2021-2024 | E53: =IFERROR(MID(D53,6,4),"") -> 2024 | I53: =1/COUNTBLANK($H$52:$H$53) -> 0.5 | J53: =I53*$H$51 -> 0.25
A54: FACTOR 2 | B54: CAPITAL HUMANO | E54: =IFERROR(MID(D54,6,4),"")
A55: PILAR 5: SALUD | E55: =IFERROR(MID(D55,6,4),"") | F55: =F2 -> 0.076923077
A56: SAL-1 | B56: Acceso a salud | E56: =IFERROR(MID(D56,6,4),"") | G56: =$F$55/3 -> 0.025641026 | H56: =G56/$F$55 -> 0.33333333
A57: SAL-1-1 | B57: Cobertura de vacunación triple viral | C57: No | D57: 2018-2024 | E57: =IFERROR(MID(D57,6,4),"") -> 2024 | I57: =1/COUNTBLANK($H$57:$H$59) -> 0.33333333 | J57: =I57*$H$56 -> 0.11111111
A58: SAL-1-2 | B58: Cobertura de vacunación pentavalente (DTP) | C58: No | D58: 2018-2024 | E58: =IFERROR(MID(D58,6,4),"") -> 2024 | I58: =1/COUNTBLANK($H$57:$H$59) -> 0.33333333 | J58: =I58*$H$56 -> 0.11111111
A59: SAL-1-3 | B59: Controles prenatales | C59: No | D59: 2017-2023 | E59: =IFERROR(MID(D59,6,4),"") -> 2023 | I59: =1/COUNTBLANK($H$57:$H$59) -> 0.33333333 | J59: =I59*$H$56 -> 0.11111111
A60: SAL-2 | B60: Resultados en salud | E60: =IFERROR(MID(D60,6,4),"") | G60: =$F$55/3 -> 0.025641026 | H60: =G60/$F$55 -> 0.33333333
A61: SAL-2-1 | B61: Mortalidad infantil | C61: Sí | D61: 2018-2023 | E61: =IFERROR(MID(D61,6,4),"") -> 2023 | I61: =1/COUNTBLANK($H$61:$H$62) -> 0.5 | J61: =I61*$H$60 -> 0.16666667
A62: SAL-2-2 | B62: Mortalidad materna | C62: Sí | D62: 2018-2024 | E62: =IFERROR(MID(D62,6,4),"") -> 2024 | I62: =1/COUNTBLANK($H$61:$H$62) -> 0.5 | J62: =I62*$H$60 -> 0.16666667
A63: SAL-3 | B63: Capacidades en salud | E63: =IFERROR(MID(D63,6,4),"") | G63: =$F$55/3 -> 0.025641026 | H63: =G63/$F$55 -> 0.33333333
A64: SAL-3-1 | B64: Comunidad de la salud | C64: No | D64: 2018-2024 | E64: =IFERROR(MID(D64,6,4),"") -> 2024 | I64: =1/COUNTBLANK($H$64:$H$67) -> 0.25 | J64: =I64*$H$63 -> 0.083333333
A65: SAL-3-2 | B65: Médicos generales | C65: No | D65: 2018-2024 | E65: =IFERROR(MID(D65,6,4),"") -> 2024 | I65: =1/COUNTBLANK($H$64:$H$67) -> 0.25 | J65: =I65*$H$63 -> 0.083333333
A66: SAL-3-3 | B66: Médicos especialistas | C66: No | D66: 2018-2024 | E66: =IFERROR(MID(D66,6,4),"") -> 2024 | I66: =1/COUNTBLANK($H$64:$H$67) -> 0.25 | J66: =I66*$H$63 -> 0.083333333
A67: SAL-3-4 | B67: Camas generales y especializadas | C67: No | D67: 2018-2024 | E67: =IFERROR(MID(D67,6,4),"") -> 2024 | I67: =1/COUNTBLANK($H$64:$H$67) -> 0.25 | J67: =I67*$H$63 -> 0.083333333
A68: PILAR 6: EDUCACIÓN BÁSICA Y MEDIA | E68: =IFERROR(MID(D68,6,4),"") | F68: =F2 -> 0.076923077
A69: EDU-1 | B69: Cobertura en educación | E69: =IFERROR(MID(D69,6,4),"") | G69: =$F$68/2 -> 0.038461538 | H69: =G69/$F$68 -> 0.5
A70: EDU-1-1 | B70: Cobertura neta en preescolar | C70: No | D70: 2018-2023 | E70: =IFERROR(MID(D70,6,4),"") -> 2023 | I70: =1/COUNTBLANK($H$70:$H$74) -> 0.2 | J70: =I70*$H$69 -> 0.1
A71: EDU-1-2 | B71: Cobertura neta en educación primaria | C71: No | D71: 2018-2023 | E71: =IFERROR(MID(D71,6,4),"") -> 2023 | I71: =1/COUNTBLANK($H$70:$H$74) -> 0.2 | J71: =I71*$H$69 -> 0.1
A72: EDU-1-3 | B72: Cobertura neta en educación secundaria | C72: No | D72: 2018-2023 | E72: =IFERROR(MID(D72,6,4),"") -> 2023 | I72: =1/COUNTBLANK($H$70:$H$74) -> 0.2 | J72: =I72*$H$69 -> 0.1
A73: EDU-1-4 | B73: Cobertura neta en educación media | C73: No | D73: 2018-2023 | E73: =IFERROR(MID(D73,6,4),"") -> 2023 | I73: =1/COUNTBLANK($H$70:$H$74) -> 0.2 | J73: =I73*$H$69 -> 0.1
A74: EDU-1-5 | B74: Deserción escolar en educación básica y media | C74: Sí | D74: 2018-2023 | E74: =IFERROR(MID(D74,6,4),"") -> 2023 | I74: =1/COUNTBLANK($H$70:$H$74) -> 0.2 | J74: =I74*$H$69 -> 0.1
A75: EDU-2 | B75: Calidad en educación | E75: =IFERROR(MID(D75,6,4),"") | G75: =$F$68/2 -> 0.038461538 | H75: =G75/$F$68 -> 0.5
A76: EDU-2-1 | B76: Puntaje pruebas Saber 11 | C76: No | D76: 2019-2024 | E76: =IFERROR(MID(D76,6,4),"") -> 2024 | I76: =1/COUNTBLANK($H$76:$H$79) -> 0.25 | J76: =I76*$H$75 -> 0.125
A77: EDU-2-2 | B77: Puntaje pruebas Saber 11 en colegios oficiales | C77: No | D77: 2019-2024 | E77: =IFERROR(MID(D77,6,4),"") -> 2024 | I77: =1/COUNTBLANK($H$76:$H$79) -> 0.25 | J77: =I77*$H$75 -> 0.125
A78: EDU-2-3 | B78: Docentes de colegios oficiales con posgrado | C78: No | D78: 2018-2022 | E78: =IFERROR(MID(D78,6,4),"") -> 2022 | I78: =1/COUNTBLANK($H$76:$H$79) -> 0.25 | J78: =I78*$H$75 -> 0.125
A79: EDU-2-4 | B79: Relación estudiantes-docentes | C79: Sí | D79: 2018-2022 | E79: =IFERROR(MID(D79,6,4),"") -> 2022 | I79: =1/COUNTBLANK($H$76:$H$79) -> 0.25 | J79: =I79*$H$75 -> 0.125
A80: PILAR 7: EDUCACIÓN SUPERIOR Y FORMACIÓN PARA EL TRABAJO | E80: =IFERROR(MID(D80,6,4),"") | F80: =F2 -> 0.076923077
A81: EDS-1 | B81: Cobertura en educación superior | E81: =IFERROR(MID(D81,6,4),"") | G81: =$F$80/3 -> 0.025641026 | H81: =G81/$F$80 -> 0.33333333
A82: EDS-1-1 | B82: Cobertura bruta en formación universitaria | C82: No | D82: 2018-2024 | E82: =IFERROR(MID(D82,6,4),"") -> 2024 | I82: =1/COUNTBLANK($H$82:$H$84) -> 0.33333333 | J82: =I82*$H$81 -> 0.11111111
A83: EDS-1-2 | B83: Graduados en posgrado | C83: No | D83: 2018-2024 | E83: =IFERROR(MID(D83,6,4),"") -> 2024 | I83: =1/COUNTBLANK($H$82:$H$84) -> 0.33333333 | J83: =I83*$H$81 -> 0.11111111
A84: EDS-1-3 | B84: Cobertura bruta en formación técnica y tecnológica | C84: No | D84: 2018-2024 | E84: =IFERROR(MID(D84,6,4),"") -> 2024 | I84: =1/COUNTBLANK($H$82:$H$84) -> 0.33333333 | J84: =I84*$H$81 -> 0.11111111
A85: EDS-2 | B85: Calidad en educación superior | E85: =IFERROR(MID(D85,6,4),"") | G85: =$F$80/3 -> 0.025641026 | H85: =G85/$F$80 -> 0.33333333
A86: EDS-2-1 | B86: Puntaje pruebas Saber Pro | C86: No | D86: 2018-2023 | E86: =IFERROR(MID(D86,6,4),"") -> 2023 | I86: =1/COUNTBLANK($H$86:$H$89) -> 0.25 | J86: =I86*$H$85 -> 0.083333333
A87: EDS-2-2 | B87: Calidad de docentes de educación superior | C87: No | D87: 2018-2024 | E87: =IFERROR(MID(D87,6,4),"") -> 2024 | I87: =1/COUNTBLANK($H$86:$H$89) -> 0.25 | J87: =I87*$H$85 -> 0.083333333
A88: EDS-2-3 | B88: Cobertura instituciones de educación superior con acreditación de alta calidad | C88: No | D88: 2018-2024 | E88: =IFERROR(MID(D88,6,4),"") -> 2024 | I88: =1/COUNTBLANK($H$86:$H$89) -> 0.25 | J88: =I88*$H$85 -> 0.083333333
A89: EDS-2-4 | B89: Dominio de inglés | C89: No | D89: 2018-2023 | E89: =IFERROR(MID(D89,6,4),"") -> 2023 | I89: =1/COUNTBLANK($H$86:$H$89) -> 0.25 | J89: =I89*$H$85 -> 0.083333333
A90: EDS-3 | B90: Educación para el trabajo y el desarrollo humano | E90: =IFERROR(MID(D90,6,4),"") | G90: =$F$80/3 -> 0.025641026 | H90: =G90/$F$80 -> 0.33333333
A91: EDS-3-1 | B91: Proporción de estudiantes en IETDH matriculados en instituciones certificadas | C91: No | D91: 2018-2023 | E91: =IFERROR(MID(D91,6,4),"") -> 2023 | I91: =1/COUNTBLANK($H$91:$H$92) -> 0.5 | J91: =I91*$H$90 -> 0.16666667
A92: EDS-3-2 | B92: Egresados del SENA vinculados al mercado laboral | C92: No | D92: 2019-2024 | E92: =IFERROR(MID(D92,6,4),"") -> 2024 | I92: =1/COUNTBLANK($H$91:$H$92) -> 0.5 | J92: =I92*$H$90 -> 0.16666667
A93: FACTOR 3 | B93: EFICIENCIA DE LOS MERCADOS | E93: =IFERROR(MID(D93,6,4),"")
A94: PILAR 8: ENTORNO PARA LOS NEGOCIOS | E94: =IFERROR(MID(D94,6,4),"") | F94: =F2 -> 0.076923077
A95: NEG-1 | B95: Trámites y especialización empresarial | E95: =IFERROR(MID(D95,6,4),"") | G95: =$F$94/2 -> 0.038461538 | H95: =G95/$F$80 -> 0.5
A96: NEG-1-1 | B96: Facilitación de trámites | C96: No | D96: 2019-2024 | E96: =IFERROR(MID(D96,6,4),"") -> 2024 | I96: =1/COUNTBLANK($H$96:$H$98) -> 0.33333333 | J96: =I96*$F$94 -> 0.025641026
A97: NEG-1-2 | B97: Concentración en el sector secundario | C97: Sí | D97: 2019-2024 | E97: =IFERROR(MID(D97,6,4),"") -> 2024 | I97: =1/COUNTBLANK($H$96:$H$98) -> 0.33333333 | J97: =I97*$F$94 -> 0.025641026
A98: NEG-1-3 | B98: Concentración en el sector terciario | C98: Sí | D98: 2019-2024 | E98: =IFERROR(MID(D98,6,4),"") -> 2024 | I98: =1/COUNTBLANK($H$96:$H$98) -> 0.33333333 | J98: =I98*$F$94 -> 0.025641026
A99: NEG-2 | B99: Dinámica empresarial | E99: =IFERROR(MID(D99,6,4),"") | G99: =$F$94/2 -> 0.038461538 | H99: =G99/$F$80 -> 0.5
A100: NEG-2-1 | B100: Tasa de registro empresarial | C100: No | D100: 2018-2024 | E100: =IFERROR(MID(D100,6,4),"") -> 2024 | I100: =1/COUNTBLANK($H$100:$H$102) -> 0.33333333 | J100: =I100*$F$94 -> 0.025641026
...

Sheet Valor_original (winzo-imp)
A1: Ciudad o AM | B1: Año edición | C1: INS-1-1 | D1: INS-1-2 | E1: INS-2-1 | F1: INS-2-2 | G1: INS-2-3 | H1: INS-3-1 | I1: INS-3-2 | J1: INS-4-1 | K1: INS-4-2 | L1: INS-4-3 | M1: INS-4-4 | N1: INS-4-5 | O1: INS-4-6 | P1: INF-1-1 | Q1: INF-1-2 | R1: INF-1-3 | S1: INF-1-4 | T1: INF-1-5 | U1: INF-2-1 | V1: INF-2-2 | W1: INF-2-3 | X1: INF-2-4 | Y1: INF-2-5 | Z1: INF-3-1 | AA1: INF-3-2 | AB1: INF-3-3 | AC1: TIC-1-1 | AD1: TIC-1-2 | AE1: TIC-1-3 | AF1: TIC-1-4 | AG1: TIC-2-1 | AH1: TIC-2-2 | AI1: TIC-2-3 | AJ1: AMB-1-1 | AK1: AMB-1-2 | AL1: AMB-2-1 | AM1: AMB-2-2 | AN1: SAL-1-1 | AO1: SAL-1-2 | AP1: SAL-1-3 | AQ1: SAL-2-1 | AR1: SAL-2-2 | AS1: SAL-3-1 | AT1: SAL-3-2 | AU1: SAL-3-3 | AV1: SAL-3-4 | AW1: EDU-1-1 | AX1: EDU-1-2 | AY1: EDU-1-3 | AZ1: EDU-1-4 | BA1: EDU-1-5 | BB1: EDU-2-1 | BC1: EDU-2-2 | BD1: EDU-2-3 | BE1: EDU-2-4 | BF1: EDS-1-1 | BG1: EDS-1-2 | BH1: EDS-1-3 | BI1: EDS-2-1 | BJ1: EDS-2-2 | BK1: EDS-2-3 | BL1: EDS-2-4 | BM1: EDS-3-1 | BN1: EDS-3-2 | BO1: NEG-1-1 | BP1: NEG-1-2 | BQ1: NEG-1-3 | BR1: NEG-2-1 | BS1: NEG-2-2 | BT1: NEG-2-3 | BU1: LAB-1-1 | BV1: LAB-1-2 | BW1: LAB-1-3 | BX1: LAB-1-4 | BY1: LAB-1-5 | BZ1: FIN-1-1 | CA1: FIN-1-2 | CB1: FIN-1-3 | CC1: FIN-1-4 | CD1: TAM-1-1 | CE1: TAM-2-1 | CF1: TAM-2-2 | CG1: SOF-1-1 | CH1: SOF-1-2 | CI1: INN-1-1 | CJ1: INN-1-2 | CK1: INN-1-3 | CL1: INN-1-4 | CM1: INN-2-1 | CN1: INN-2-2 | CO1: INN-2-3 | CP1: INN-2-4
A2: Arauca | B2: 2019 | C2: 121.14002 | D2: 21.032857 | E2: 0.18219489 | F2: 0.015013936 | G2: 48.123994 | H2: 37.82 | I2: 0.072591526 | J2: 32.716013 | K2: 848.27949 | L2: 63.095169 | M2: 0.43671706 | N2: 288.78261 | O2: 0.58181818 | P2: 47.322365 | Q2: n/a | R2: 95.114412 | S2: 441.02028 | T2: 47.37097 | U2: 180.34663 | V2: 179.64446 | W2: 114012 | X2: 0.1088 | Y2: N/A | Z2: 2102.7049 | AA2: 0 | AB2: 0 | AC2: 7.99 | AD2: 5.5890582 | AE2: 22.427528 | AF2: 68.294633 | AG2: 1312.722 | AH2: 368.053 | AI2: 0.5 | AJ2: 36953.685 | AK2: 41.551358 | AL2: 0 | AM2: 28.831922 | AN2: 1 | AO2: 0.9282 | AP2: 81.320225 | AQ2: 10.848756 | AR2: 61.99628 | AS2: 51.225522 | AT2: 11.709781 | AU2: 5.5688207 | AV2: 269.90711 | AW2: 0.568 | AX2: 0.9594 | AY2: 0.7578 | AZ2: 0.394 | BA2: 0.0296 | BB2: 255 | BC2: 250.66424 | BD2: 0.54151329 | BE2: 26.641309 | BF2: 20.608 | BG2: 19.554 | BH2: 12.428 | BI2: 138.37842 | BJ2: 45.454545 | BK2: 1.3497879 | BL2: 5.5374593 | BM2: 0 | BN2: 0.40883978 | BO2: 0.083916084 | BP2: 0.1386173 | BQ2: 0.064505 | BR2: 6.4263598 | BS2: 6.7418356 | BT2: 0.03812825 | BU2: 61.895839 | BV2: 24.88527 | BW2: 40.146241 | BX2: 10.697331 | BY2: 53.325791 | BZ2: 45.210462 | CA2: 72.968994 | CB2: 0.0039138006 | CC2: 0.16464855 | CD2: 28.240705 | CE2: 26.908411 | CF2: 26.414047 | CG2: 0.305 | CH2: 0.99756022 | CI2: 0 | CJ2: 11.68429 | CK2: 0 | CL2: 0 | CM2: 0 | CN2: 0 | CO2: 0 | CP2: 93.474324
A3: Armenia | B3: 2019 | C3: 202.81292 | D3: 53.9325 | E3: 0.33521994 | F3: 0.029881744 | G3: 52.739413 | H3: 42.44 | I3: 0.39631976 | J3: 29.80949 | K3: 785.54782 | L3: 12.533536 | M3: 0.61884494 | N3: 494.38983 | O3: 0.20596511 | P3: 100 | Q3: 0.8182131 | R3: 99.079541 | S3: 413.186 | T3: 99.998082 | U3: 272.05812 | V3: 235.82489 | W3: 387616 | X3: 0.2414 | Y3: 18.509876 | Z3: 251.2127 | AA3: 9.9935375 | AB3: 13.324717 | AC3: 24.6 | AD3: 8.7742677 | AE3: 41.797892 | AF3: 74.634168 | AG3: 10558.9 | AH3: 1157.081 | AI3: 1.2105 | AJ3: 62669.815 | AK3: 51.516226 | AL3: 1.4519056 | AM3: 31.269909 | AN3: 0.97801545 | AO3: 0.91192768 | AP3: 94.538723 | AQ3: 9.9710518 | AR3: 64.040986 | AS3: 144.446 | AT3: 19.855382 | AU3: 9.7980382 | AV3: 435.62505 | AW3: 0.7119 | AX3: 0.9458 | AY3: 0.9022 | AZ3: 0.5701 | BA3: 0.0428 | BB3: 269 | BC3: 262.25743 | BD3: 0.6025641 | BE3: 24.217338 | BF3: 64.025 | BG3: 97.361 | BH3: 44.424 | BI3: 148.82155 | BJ3: 6.3015312 | BK3: 46.497811 | BL3: 26.928747 | BM3: 59.871383 | BN3: 0.53039514 | BO3: 0.019480519 | BP3: 0.0544573 | BQ3: 0.0782741 | BR3: 11.957671 | BS3: 7.8825777 | BT3: 0.06231199 | BU3: 60.715577 | BV3: 17.088902 | BW3: 47.471812 | BX3: 10.82113 | BY3: 50.017474 | BZ3: 29.360615 | CA3: 109.7289 | CB3: 0.037271891 | CC3: 0.48542031 | CD3: 28.99568 | CE3: 26.713389 | CF3: 13.733634 | CG3: 0.218 | CH3: 0.90263872 | CI3: 2.3712095 | CJ3: 430.20514 | CK3: 1.61 | CL3: 25 | CM3: 20.324652 | CN3: 13.549768 | CO3: 16.93721 | CP3: 752.01214
A4: Barranquilla AM | B4: 2019 | C4: 182.44751 | D4: 71.188127 | E4: 0.38587138 | F4: 0.03571593 | G4: 65.230595 | H4: 49.067451 | I4: 0.28163933 | J4: 26.238484 | K4: 786.82309 | L4: 7.2915366 | M4: 0.46595014 | N4: 338.11 | O4: 0.45842789 | P4: 94.206461 | Q4: 0.89286444 | R4: 99.638348 | S4: 374.13522 | T4: 86.178068 | U4: 169.21186 | V4: 161.11148 | W4: 2482372 | X4: 0.3158 | Y4: 21.942994 | Z4: 581.5829 | AA4: 5.8475771 | AB4: 10.631958 | AC4: 13.838173 | AD4: 11.521319 | AE4: 44.982809 | AF4: 77.643446 | AG4: 7585.936 | AH4: 907.957 | AI4: 2.2895 | AJ4: 99990.406 | AK4: 55.333194 | AL4: 3.4482759 | AM4: 28.368488 | AN4: 0.98546667 | AO4: 0.9770368 | AP4: 91.146548 | AQ4: 12.86013 | AR4: 74.128984 | AS4: 62.196388 | AT4: 27.477631 | AU4: 11.851626 | AV4: 402.91264 | AW4: 0.63985197 | AX4: 0.91119901 | AY4: 0.79399019 | AZ4: 0.51740022 | BA4: 0.0098874718 | BB4: 255.24775 | BC4: 251.02746 | BD4: 0.46319164 | BE4: 29.547495 | BF4: 55.07 | BG4: 429.009 | BH4: 26.464 | BI4: 146.51808 | BJ4: 13.395079 | BK4: 51.227864 | BL4: 30.858676 | BM4: 42.440221 | BN4: 0.4785753 | BO4: 0.11333333 | BP4: 0.0287095 | BQ4: 0.0736313 | BR4: 21.454794 | BS4: 14.442214 | BT4: 0.060929432 | BU4: 64.167768 | BV4: 8.7404648 | BW4: 39.403991 | BX4: 12.407808 | BY4: 48.765305 | BZ4: 45.960873 | CA4: 79.232532 | CB4: 0.041266947 | CC4: 0.76216195 | CD4: 31.041911 | CE4: 28.808833 | CF4: 30.824488 | CG4: 0.099 | CH4: 0.032605743 | CI4: 5.5238914 | CJ4: 475.60705 | CK4: 1.63 | CL4: 21.6 | CM4: 11.047783 | CN4: 3.866724 | CO4: 3.3143348 | CP4: 1083.7875
A5: Bogotá D.C. | B5: 2019 | C5: 194.38686 | D5: 91.9025 | E5: 0.61918234 | F5: 0.038101415 | G5: 62.916318 | H5: 48.215 | I5: 0.65729288 | J5: 14.542872 | K5: 1667.8975 | L5: 10.25286 | M5: 0.54659668 | N5: 597.55 | O5: 0.36015982 | P5: 98.101949 | Q5: 0.96346458 | R5: 99.894262 | S5: 377.72407 | T5: 98.056066 | U5: 243.34343 | V5: 189.77317 | W5: 12843372 | X5: 0.60508 | Y5: 32.036673 | Z5: 691.65253 | AA5: 8.9557692 | AB5: 20.545588 | AC5: 25.31 | AD5: 12.107394 | AE5: 63.897082 | AF5: 87.173928 | AG5: 10166.292 | AH5: 1601.455 | AI5: 2.7656 | AJ5: 40850.186 | AK5: 39.10817 | AL5: 3.0852995 | AM5: 33.456585 | AN5: 0.92496506 | AO5: 0.88670345 | AP5: 88.39084 | AQ5: 8.9094019 | AR5: 56.198461 | AS5: 123.00059 | AT5: 43.938901 | AU5: 27.786599 | AV5: 240.33513 | AW5: 0.7065 | AX5: 0.9781 | AY5: 0.8597 | AZ5: 0.5601 | BA5: 0.0165 | BB5: 274.57283 | BC5: 257.90472 | BD5: 0.37160875 | BE5: 24.15716 | BF5: 79.512 | BG5: 571.929 | BH5: 30.591 | BI5: 155.68934 | BJ5: 8.2291743 | BK5: 33.857732 | BL5: 37.870485 | BM5: 39.621085 | BN5: 0.67928233 | BO5: 0.35774947 | BP5: 0.0052617 | BQ5: 0.0066994 | BR5: 32.586556 | BS5: 25.635927 | BT5: 0.071978866 | BU5: 71.170849 | BV5: 10.60834 | BW5: 56.496643 | BX5: 8.1421844 | BY5: 31.781272 | BZ5: 70.923984 | CA5: 119.03735 | CB5: 0.071459118 | CC5: 0.83183552 | CD5: 32.98897 | CE5: 29.618654 | CF5: 34.266254 | CG5: 0.159 | CH5: 0.020942613 | CI5: 6.043791 | CJ5: 588.46019 | CK5: 2.14 | CL5: 18.8 | CM5: 29.544425 | CN5: 18.347223 | CO5: 38.448224 | CP5: 3325.0294
A6: Bucaramanga AM | B6: 2019 | C6: 202.21521 | D6: 77.063775 | E6: 0.39485024 | F6: 0.025989014 | G6: 60.9875 | H6: 64.75984 | I6: 0.19091127 | J6: 12.54056 | K6: 835.64974 | L6: 10.049058 | M6: 0.51027988 | N6: 482.21081 | O6: 0.45364536 | P6: 69.843314 | Q6: 0.95770278 | R6: 99.520925 | S6: 388.77476 | T6: 64.615611 | U6: 208.33529 | V6: 169.53913 | W6: 1595907 | X6: 0.2756 | Y6: 16.436687 | Z6: 930.22715 | AA6: 7.25342 | AB6: 5.6415489 | AC6: 21.283309 | AD6: 9.425301 | AE6: 50.178464 | AF6: 80.175522 | AG6: 9643.108 | AH6: 1428.933 | AI6: 2.6667 | AJ6: 57402.322 | AK6: 52.176762 | AL6: 3.8112523 | AM6: 28.578598 | AN6: 0.9042601 | AO6: 0.89458273 | AP6: 94.103078 | AQ6: 7.0036541 | AR6: 48.561369 | AS6: 61.977164 | AT6: 22.322031 | AU6: 12.495211 | AV6: 319.57664 | AW6: 0.71440529 | AX6: 0.96476289 | AY6: 0.845617 | AZ6: 0.50737472 | BA6: 0.037678077 | BB6: 287.38174 | BC6: 277.20161 | BD6: 0.71239728 | BE6: 28.227045 | BF6: 56.403 | BG6: 1167.727 | BH6: 30.269 | BI6: 152.18063 | BJ6: 8.2297052 | BK6: 42.674383 | BL6: 31.48729 | BM6: 48.673594 | BN6: 0.55356619 | BO6: 0.073908175 | BP6: 0.0163077 | BQ6: 0.0052737 | BR6: 11.319724 | BS6: 11.891108 | BT6: 0.06153094 | BU6: 63.655162 | BV6: 9.7161008 | BW6: 46.868272 | BX6: 6.8990549 | BY6: 46.862681 | BZ6: 49.039077 | CA6: 92.750939 | CB6: 0.057415759 | CC6: 0.70259627 | CD6: 30.801355 | CE6: 27.709858 | CF6: 8.3574307 | CG6: 0.102 | CH6: 0.40225216 | CI6: 5.0660539 | CJ6: 522.3849 | CK6: 1.36 | CL6: 22.6 | CM6: 14.118511 | CN6: 6.6440051 | CO6: 14.949011 | CP6: 1073.0068
A7: Cali AM | B7: 2019 | C7: 165.31472 | D7: 76.953977 | E7: 0.47258926 | F7: 0.029833391 | G7: 64.417971 | H7: 65.233563 | I7: 0.42674671 | J7: 53.876357 | K7: 991.7875 | L7: 13.490503 | M7: 0.51559143 | N7: 450.46154 | O7: 0.45357238 | P7: 81.743899 | Q7: 0.99742801 | R7: 99.272399 | S7: 366.86036 | T7: 81.363658 | U7: 241.44244 | V7: 196.91324 | W7: 4647659 | X7: 0.373 | Y7: 33.766696 | Z7: 1751.9195 | AA7: 8.9347254 | AB7: 8.5092623 | AC7: 21.094539 | AD7: 10.080154 | AE7: 50.949048 | AF7: 82.960341 | AG7: 6283.943 | AH7: 953.934 | AI7: 1.8246 | AJ7: 77366.662 | AK7: 51.305689 | AL7: 1.9963702 | AM7: 30.038185 | AN7: 0.98227167 | AO7: 0.97858494 | AP7: 93.019595 | AQ7: 9.1225358 | AR7: 30.797659 | AS7: 61.022555 | AT7: 24.634229 | AU7: 12.524895 | AV7: 316.14886 | AW7: 0.53970932 | AX7: 0.78995876 | AY7: 0.75171244 | AZ7: 0.42560379 | BA7: 0.027965355 | BB7: 264.7942 | BC7: 250.68086 | BD7: 0.40927152 | BE7: 30.275644 | BF7: 44.134 | BG7: 211.778 | BH7: 19.054 | BI7: 148.68159 | BJ7: 11.951171 | BK7: 48.375873 | BL7: 31.680815 | BM7: 59.703441 | BN7: 0.59175887 | BO7: 0.15174672 | BP7: 0.0168392 | BQ7: 0.0099212 | BR7: 14.890945 | BS7: 13.504636 | BT7: 0.066850601 | BU7: 65.123023 | BV7: 12.446246 | BW7: 47.208395 | BX7: 11.650437 | BY7: 37.584479 | BZ7: 50.085481 | CA7: 95.458955 | CB7: 0.051213684 | CC7: 0.78080541 | CD7: 31.463177 | CE7: 28.729992 | CF7: 20.712468 | CG7: 0.096 | CH7: 0.022835688 | CI7: 5.610336 | CJ7: 431.69609 | CK7: 1.51 | CL7: 22.98 | CM7: 16.702527 | CN7: 10.278478 | CO7: 13.276368 | CP7: 1997.4509
A8: Cartagena | B8: 2019 | C8: 192.35408 | D8: 75.61 | E8: 0.40941424 | F8: 0.030368381 | G8: 58.927849 | H8: 90.7 | I8: 0.28422725 | J8: 23.431599 | K8: 683.01055 | L8: 10.893638 | M8: 0.54023729 | N8: 421.4252 | O8: 0.258553 | P8: 45.25179 | Q8: 0.93392854 | R8: 95.802788 | S8: 344.49858 | T8: 43.94764 | U8: 174.20999 | V8: 171.04479 | W8: 5259812 | X8: 0.4566 | Y8: 25.61789 | Z8: 677.87204 | AA8: 9.9632853 | AB8: 93.413455 | AC8: 15.48 | AD8: 9.9948442 | AE8: 30.987781 | AF8: 66.898285 | AG8: 4942.26 | AH8: 941.383 | AI8: 1.5897 | AJ8: 118654.95 | AK8: 51.698414 | AL8: 0 | AM8: 27.437401 | AN8: 0.93385827 | AO8: 0.88607929 | AP8: 89.89329 | AQ8: 12.877155 | AR8: 79.482832 | AS8: 38.070441 | AT8: 18.206762 | AU8: 8.76765 | AV8: 379.11916 | AW8: 0.7467 | AX8: 1 | AY8: 0.9123 | AZ8: 0.5445 | BA8: 0.0296 | BB8: 244.87184 | BC8: 229.42514 | BD8: 0.4165937 | BE8: 33.808669 | BF8: 45.886 | BG8: 219.768 | BH8: 37.287 | BI8: 145.79044 | BJ8: 5.9440559 | BK8: 43.274131 | BL8: 25.498551 | BM8: 78.610537 | BN8: 0.3937575 | BO8: 0.20385675 | BP8: 0.3478084 | BQ8: 0.0144095 | BR8: 18.950819 | BS8: 12.607844 | BT8: 0.063009455 | BU8: 66.100392 | BV8: 7.7171083 | BW8: 42.50201 | BX8: 7.3456542 | BY8: 52.041232 | BZ8: 41.620381 | CA8: 82.640895 | CB8: 0.017814944 | CC8: 0.37043469 | CD8: 30.61497 | CE8: 28.838072 | CF8: 45.815469 | CG8: 0.107 | CH8: 0.080207008 | CI8: 3.9052665 | CJ8: 350.44628 | CK8: 0 | CL8: 23.88 | CM8: 2.0554034 | CN8: 1.0277017 | CO8: 8.2216136 | CP8: 612.51021
A9: Cúcuta AM | B9: 2019 | C9: 146.34349 | D9: 68.30965 | E9: 0.23205302 | F9: 0.029309563 | G9: 59.951141 | H9: 50 | I9: 0.13689623 | J9: 26.789807 | K9: 452.09143 | L9: 22.593813 | M9: 0.56000844 | N9: 527.45545 | O9: 0.58007449 | P9: 69.084382 | Q9: 0.73048297 | R9: 98.141035 | S9: 414.31567 | T9: 68.720825 | U9: 167.07386 | V9: 131.95566 | W9: 909214 | X9: 0.2514 | Y9: 13.282548 | Z9: 754.08464 | AA9: 4.0879774 | AB9: 23.50587 | AC9: 13.068041 | AD9: 8.837763 | AE9: 39.469189 | AF9: 74.579021 | AG9: 5727.211 | AH9: 952.619 | AI9: 1.7391 | AJ9: 93883.225 | AK9: 45.332494 | AL9: 1.4519056 | AM9: 27.068235 | AN9: 1 | AO9: 0.9846526 | AP9: 89.058241 | AQ9: 10.066638 | AR9: 56.433409 | AS9: 46.14903 | AT9: 12.053451 | AU9: 6.3351007 | AV9: 235.62119 | AW9: 0.68544458 | AX9: 0.92299251 | AY9: 0.80385345 | AZ9: 0.44518881 | BA9: 0.036967435 | BB9: 266.42892 | BC9: 262.30305 | BD9: 0.64638493 | BE9: 31.652495 | BF9: 48.106 | BG9: 161.673 | BH9: 16.524 | BI9: 142.32564 | BJ9: 6.1524334 | BK9: 16.786082 | BL9: 11.535386 | BM9: 74.948415 | BN9: 0.37247278 | BO9: 0.090342679 | BP9: 0.0125115 | BQ9: 0.0068909 | BR9: 9.0052482 | BS9: 6.1035571 | BT9: 0.048475234 | BU9: 65.61958 | BV9: 15.99521 | BW9: 29.686868 | BX9: 12.585851 | BY9: 64.956299 | BZ9: 29.752443 | CA9: 57.529148 | CB9: 0.0215484 | CC9: 0.38236228 | CD9: 29.860028 | CE9: 26.780554 | CF9: 6.6742125 | CG9: 0.077 | CH9: 0.32438924 | CI9: 0.86071668 | CJ9: 145.24594 | CK9: 1.12 | CL9: 29.79 | CM9: 2.1517917 | CN9: 5.3794792 | CO9: 4.3035834 | CP9: 568.07301
A10: Florencia | B10: 2019 | C10: 156.45196 | D10: 56.255 | E10: 0.18721412 | F10: 0.021905053 | G10: 40.609882 | H10: 61.96 | I10: 0.099370739 | J10: 22.572559 | K10: 906.46644 | L10: 33.264824 | M10: 0.53018679 | N10: 660.51282 | O10: 0.56238004 | P10: 74.686722 | Q10: 0.89457851 | R10: 90.558367 | S10: 434.08757 | T10: 74.686722 | U10: 471.56935 | V10: 421.1808 | W10: 110539 | X10: 0.1192 | Y10: 14.631355 | Z10: 638.86282 | AA10: 5.8560352 | AB10: 5.8560352 | AC10: 11.36 | AD10: 6.1853125 | AE10: 32.606844 | AF10: 67.634542 | AG10: 4545.18 | AH10: 513.068 | AI10: 2.4286 | AJ10: 67122.495 | AK10: 59.578653 | AL10: 7.9854809 | AM10: 28.413185 | AN10: 0.79041057 | AO10: 0.79701407 | AP10: 84.389535 | AQ10: 8.1620314 | AR10: 60.295448 | AS10: 31.429716 | AT10: 8.5106595 | AU10: 3.3097009 | AV10: 370.66518 | AW10: 0.6966 | AX10: 0.981 | AY10: 0.7918 | AZ10: 0.397 | BA10: 0.0498 | BB10: 260 | BC10: 255.74196 | BD10: 0.74040067 | BE10: 28.786311 | BF10: 58.167 | BG10: 216.922 | BH10: 9.083 | BI10: 138.33391 | BJ10: 3.9577836 | BK10: 1.1225444 | BL10: 11.237016 | BM10: 0 | BN10: 0.36120401 | BO10: 0.11904762 | BP10: 0.0399122 | BQ10: 0.0359186 | BR10: 9.4448339 | BS10: 4.562033 | BT10: 0.0390625 | BU10: 61.359637 | BV10: 13.491916 | BW10: 39.729544 | BX10: 6.7605728 | BY10: 47.258958 | BZ10: 53.182153 | CA10: 81.056271 | CB10: 0.011956269 | CC10: 0.46138676 | CD10: 28.221095 | CE10: 19.9213 | CF10: 0.063201732 | CG10: 0.443 | CH10: 0.38555 | CI10: 0 | CJ10: 279.18691 | CK10: 1.4 | CL10: 15.16 | CM10: 5.9401471 | CN10: 0 | CO10: 0 | CP10: 160.38397
A11: Ibagué | B11: 2019 | C11: 166.88325 | D11: 69.86125 | E11: 0.26674732 | F11: 0.019950981 | G11: 56.04685 | H11: 45.35 | I11: 0.56433555 | J11: 15.67117 | K11: 943.10233 | L11: 16.992835 | M11: 0.46223473 | N11: 397.46729 | O11: 0.63340892 | P11: 51.774626 | Q11: 0.96886369 | R11: 98.306345 | S11: 355.16013 | T11: 51.452263 | U11: 134.82491 | V11: 130.09677 | W11: 125335 | X11: 0.2258 | Y11: 21.681067 | Z11: 734.95898 | AA11: 9.3268443 | AB11: 18.653689 | AC11: 20.75 | AD11: 8.5610762 | AE11: 43.924345 | AF11: 78.468172 | AG11: 9662.736 | AH11: 2225.139 | AI11: 1.8571 | AJ11: 59721.499 | AK11: 52.802332 | AL11: 3.8112523 | AM11: 29.113827 | AN11: 0.91719745 | AO11: 0.83642829 | AP11: 92.644217 | AQ11: 7.7463779 | AR11: 14.289797 | AS11: 42.700763 | AT11: 13.374059 | AU11: 6.2021355 | AV11: 312.10173 | AW11: 0.8133 | AX11: 1 | AY11: 0.8778 | AZ11: 0.5059 | BA11: 0.0245 | BB11: 265 | BC11: 258.66043 | BD11: 0.53666557 | BE11: 26.786583 | BF11: 54.001 | BG11: 165.69 | BH11: 32.082 | BI11: 145.96223 | BJ11: 9.2996556 | BK11: 49.386601 | BL11: 16.21919 | BM11: 47.068677 | BN11: 0.43084857 | BO11: 0.28032345 | BP11: 0.0164071 | BQ11: 0.49150035 | BR11: 11.422961 | BS11: 8.7192123 | BT11: 0.038977913 | BU11: 60.936853 | BV11: 15.849759 | BW11: 46.901157 | BX11: 9.418777 | BY11: 39.652223 | BZ11: 50.387127 | CA11: 96.156023 | CB11: 0.023090048 | CC11: 0.5412442 | CD11: 29.692683 | CE11: 26.038854 | CF11: 3.579116 | CG11: 0.206 | CH11: 0.37205178 | CI11: 2.076902 | CJ11: 303.98293 | CK11: 1.64 | CL11: 24.9 | CM11: 5.6642782 | CN11: 3.7761855 | CO11: 15.104742 | CP11: 745.79663
A12: Inírida | B12: 2019 | C12: 108.29779 | D12: 39.751429 | E12: 0.15977471 | F12: 0.015038995 | G12: 46.966529 | H12: 37.79 | I12: 0.0011648224 | J12: 9.5195786 | K12: 339.53164 | L12: 60.290664 | M12: 0 | N12: 291.75 | O12: 0.95238095 | P12: 15.921505 | Q12: n/a | R12: 65.588954 | S12: 487.59824 | T12: 11.468447 | U12: - | V12: - | W12: 50938 | X12: 0.0064 | Y12: N/A | Z12: 2493.495 | AA12: 30.606311 | AB12: 0 | AC12: 2.72 | AD12: 1.1109908 | AE12: 22.482312 | AF12: 49.375557 | AG12: 3212.496 | AH12: 265.252 | AI12: 2.6667 | AJ12: 71352.27 | AK12: 36.348825 | AL12: 3.4482759 | AM12: 31.354344 | AN12: 1 | AO12: 1 | AP12: 37.232525 | AQ12: 13.677812 | AR12: 146.62757 | AS12: 45.101218 | AT12: 7.6900694 | AU12: 2.7019163 | AV12: 142.79368 | AW12: 0.5114 | AX12: 0.7079 | AY12: 0.3764 | AZ12: 0.0919 | BA12: 0.0697 | BB12: 247 | BC12: 247.20513 | BD12: 0.19072165 | BE12: 31.136598 | BF12: 6.098 | BG12: 26.412 | BH12: 12.196 | BI12: 132.61802 | BJ12: 0 | BK12: 4.2031524 | BL12: 4.5454545 | BM12: 0 | BN12: 0.38636364 | BO12: 0 | BP12: 0.2132241 | BQ12: 0.0284747 | BR12: 6.0290664 | BS12: 2.5068224 | BT12: 0.012658228 | BU12: 56.630991 | BV12: 10.561862 | BW12: 39.661555 | BX12: 10.961496 | BY12: 57.186505 | BZ12: 15.711801 | CA12: 87.604512 | CB12: 0 | CC12: 0.020188756 | CD12: 26.264231 | CE12: 19.20545 | CF12: 0.25731801 | CG12: 0.833 | CH12: 0.8330284 | CI12: 0 | CJ12: 0 | CK12: 0 | CL12: 0 | CM12: 0 | CN12: 0 | CO12: 0 | CP12: 0
A13: Leticia | B13: 2019 | C13: 127.32749 | D13: 16.915714 | E13: 0.3715485 | F13: 0.020482322 | G13: 35.822957 | H13: 88.37 | I13: 0 | J13: 14.539714 | K13: 461.11665 | L13: 2.077102 | M13: 0.58212744 | N13: 232.55556 | O13: 0.66666667 | P13: 80.046264 | Q13: n/a | R13: 85.479294 | S13: 473.48746 | T13: 80.046264 | U13: - | V13: - | W13: 247911 | X13: 0.2282 | Y13: N/A | Z13: 793.86839 | AA13: 39.777786 | AB13: 0 | AC13: 1.78 | AD13: 1.7913721 | AE13: 16.252225 | AF13: 44.746427 | AG13: 691.81 | AH13: 66.949 | AI13: 0.5556 | AJ13: 53791.953 | AK13: 13.49192 | AL13: 8.7114338 | AM13: 32.537543 | AN13: 0.78654485 | AO13: 0.826 | AP13: 59.095023 | AQ13: 24.663677 | AR13: 0 | AS13: 57.710637 | AT13: 11.489901 | AU13: 3.9170116 | AV13: 324.02792 | AW13: 0.5555 | AX13: 0.9074 | AY13: 0.8077 | AZ13: 0.4439 | BA13: 0.0592 | BB13: 223 | BC13: 218.93321 | BD13: 0.17716535 | BE13: 26.849081 | BF13: 8.191 | BG13: 40.251 | BH13: 7.05 | BI13: 138.67157 | BJ13: 47.058824 | BK13: 8.8033012 | BL13: 5.8823529 | BM13: 0 | BN13: 0.43298969 | BO13: 0.10638298 | BP13: 0.1589874 | BQ13: 0.018875 | BR13: 7.4775673 | BS13: 5.2342971 | BT13: 0.031746032 | BU13: 60.972763 | BV13: 4.9296759 | BW13: 35.571326 | BX13: 2.0145262 | BY13: 60.46183 | BZ13: 19.442873 | CA13: 67.541007 | CB13: 0.0023012869 | CC13: 0.23587804 | CD13: 26.997833 | CE13: 16.42027 | CF13: 0.30523899 | CG13: 1 | CH13: 1 | CI13: 8.3084081 | CJ13: 373.87836 | CK13: 1.22 | CL13: 63.64 | CM13: 0 | CN13: 0 | CO13: 0 | CP13: 415.42041
A14: Manizales AM | B14: 2019 | C14: 167.83918 | D14: 57.076482 | E14: 0.31097453 | F14: 0.022046608 | G14: 61.653444 | H14: 42.842381 | I14: 0.087453001 | J14: 17.032191 | K14: 474.29642 | L14: 11.221208 | M14: 0.63081647 | N14: 448.82759 | O14: 0.47584541 | P14: 96.610203 | Q14: 0.81584222 | R14: 99.708547 | S14: 440.22713 | T14: 94.567093 | U14: 185.45292 | V14: 172.57167 | W14: 217271 | X14: 0.1268 | Y14: 17.630089 | Z14: 984.84135 | AA14: 9.8658832 | AB14: 27.624473 | AC14: 18.856535 | AD14: 8.3292733 | AE14: 49.998966 | AF14: 77.125178 | AG14: 11628.66 | AH14: 1989.098 | AI14: 3.3846 | AJ14: 87426.13 | AK14: 39.674377 | AL14: 2.3593466 | AM14: 31.642355 | AN14: 0.97418799 | AO14: 0.95699445 | AP14: 94.85957 | AQ14: 9.4928126 | AR14: 54.215234 | AS14: 56.53866 | AT14: 19.12337 | AU14: 10.818879 | AV14: 391.13925 | AW14: 0.65940857 | AX14: 0.78779016 | AY14: 0.75518726 | AZ14: 0.449532 | BA14: 0.026029674 | BB14: 273.19805 | BC14: 262.73574 | BD14: 0.66448363 | BE14: 22.701763 | BF14: 86.31 | BG14: 597.205 | BH14: 27.42 | BI14: 151.10054 | BJ14: 17.542588 | BK14: 66.472142 | BL14: 26.620725 | BM14: 39.042238 | BN14: 0.52691066 | BO14: 0.089068826 | BP14: 0.0616892 | BQ14: 0.0564867 | BR14: 9.5580647 | BS14: 8.792618 | BT14: 0.072242479 | BU14: 62.812797 | BV14: 11.007527 | BW14: 63.727761 | BX14: 5.8938885 | BY14: 30.402534 | BZ14: 26.995728 | CA14: 87.217932 | CB14: 0.042325436 | CC14: 0.54254428 | CD14: 29.590936 | CE14: 27.952462 | CF14: 26.903747 | CG14: 0.127 | CH14: 0.38963531 | CI14: 11.822344 | CJ14: 795.5035 | CK14: 0.97 | CL14: 22.49 | CM14: 18.034084 | CN14: 14.02651 | CO14: 10.018936 | CP14: 1478.7949
A15: Medellín AM | B15: 2019 | C15: 220.95023 | D15: 72.962923 | E15: 0.43794048 | F15: 0.02685362 | G15: 65.461828 | H15: 66.458912 | I15: 0.032156884 | J15: 22.893714 | K15: 1026.1087 | L15: 20.749043 | M15: 0.61549014 | N15: 623.72585 | O15: 0.4875766 | P15: 95.567633 | Q15: 0.92263804 | R15: 99.330783 | S15: 406.44041 | T15: 93.115601 | U15: 363.62828 | V15: 305.0077 | W15: 8785527 | X15: 0.5348 | Y15: 33.21248 | Z15: 2444.4827 | AA15: 6.5504021 | AB15: 13.352743 | AC15: 24.111712 | AD15: 11.062505 | AE15: 50.082136 | AF15: 77.57069 | AG15: 9078.343 | AH15: 1170.358 | AI15: 2.3375 | AJ15: 26807.442 | AK15: 51.485873 | AL15: 1.9963702 | AM15: 31.171347 | AN15: 0.95937267 | AO15: 0.93220021 | AP15: 93.283942 | AQ15: 6.6544918 | AR15: 59.26804 | AS15: 64.147566 | AT15: 23.876629 | AU15: 12.575108 | AV15: 214.13116 | AW15: 0.73357763 | AX15: 0.93130084 | AY15: 0.84449888 | AZ15: 0.48009718 | BA15: 0.037627167 | BB15: 265.22349 | BC15: 256.31555 | BD15: 0.54118801 | BE15: 29.689339 | BF15: 57.847 | BG15: 353.122 | BH15: 28.192 | BI15: 153.66915 | BJ15: 11.5072 | BK15: 39.900369 | BL15: 35.270473 | BM15: 56.669322 | BN15: 0.62269667 | BO15: 0.13841084 | BP15: 0.0076057 | BQ15: 0.0344897 | BR15: 16.312417 | BS15: 14.703656 | BT15: 0.079449599 | BU15: 63.979281 | BV15: 12.672424 | BW15: 60.133688 | BX15: 9.0482298 | BY15: 29.667659 | BZ15: 33.389071 | CA15: 109.48483 | CB15: 0.075281886 | CC15: 0.87029543 | CD15: 32.041474 | CE15: 29.831471 | CF15: 27.78735 | CG15: 0.116 | CH15: 0.0819835 | CI15: 6.4340121 | CJ15: 605.67568 | CK15: 1.28 | CL15: 19.54 | CM15: 28.423347 | CN15: 9.5605802 | CO15: 52.970782 | CP15: 3138.971
A16: Mitú | B16: 2019 | C16: 93.953911 | D16: 16.388333 | E16: 0.14626956 | F16: 0.015483511 | G16: 35.484857 | H16: 73.26 | I16: 0.00068073519 | J16: 10.050251 | K16: 70.351759 | L16: 0 | M16: 0.70775348 | N16: 139 | O16: 0 | P16: 100 | Q16: n/a | R16: 58.050665 | S16: 516.94976 | T16: 100 | U16: - | V16: - | W16: 29768 | X16: 0.0198 | Y16: N/A | Z16: 4111.2228 | AA16: 0 | AB16: 0 | AC16: 0.18 | AD16: 2.4505863 | AE16: 30.926321 | AF16: 43.633623 | AG16: 0 | AH16: 0 | AI16: 0 | AJ16: 65181.287 | AK16: 11.944389 | AL16: 3.4482759 | AM16: 26.25243 | AN16: 0.90833333 | AO16: 0.9094 | AP16: 39.54023 | AQ16: 11.600928 | AR16: 0 | AS16: 27.452999 | AT16: 2.6962767 | AU16: 0.24511606 | AV16: 46.901173 | AW16: 0.2236 | AX16: 0.5591 | AY16: 0.3597 | AZ16: 0.1361 | BA16: 0.0412 | BB16: 215 | BC16: 215.85782 | BD16: 0.17647059 | BE16: 26.894118 | BF16: 1.377 | BG16: 0 | BH16: 5.93 | BI16: 128.53824 | BJ16: 0 | BK16: 0.46948357 | BL16: 0 | BM16: 0 | BN16: 0.375 | BO16: 0.038461538 | BP16: 0.36829102 | BQ16: 0.062254 | BR16: 4.0201005 | BS16: 1.3735343 | BT16: 0 | BU16: 49.090899 | BV16: 7.5628145 | BW16: 52.195869 | BX16: 1.3627559 | BY16: 45.411235 | BZ16: 16.033817 | CA16: 36.885067 | CB16: 0.021418557 | CC16: 0.01515224 | CD16: 26.014343 | CE16: 20.50861 | CF16: 0.40889153 | CG16: 0.877 | CH16: 0.87624985 | CI16: 0 | CJ16: 603.01508 | CK16: 0 | CL16: 0 | CM16: 0 | CN16: 0 | CO16: 0 | CP16: 33.500838
A17: Mocoa | B17: 2019 | C17: 121.2876 | D17: 10.282857 | E17: 0.21072712 | F17: 0.016696154 | G17: 12.07167 | H17: 37.82 | I17: 0.44848036 | J17: 19.504238 | K17: 498.24462 | L17: 19.504238 | M17: 0.56025302 | N17: 311.26087 | O17: 0.53448276 | P17: 49.05938 | Q17: 0.66555296 | R17: 82.604396 | S17: 539.73855 | T17: 45.086705 | U17: 279.30751 | V17: 393.40165 | W17: 34176 | X17: 0 | Y17: N/A | Z17: 1700.4149 | AA17: 0 | AB17: 0 | AC17: 7.09 | AD17: 5.356704 | AE17: 32.153429 | AF17: 60.587651 | AG17: 3203.051 | AH17: 953.289 | AI17: 0.5 | AJ17: 40156.857 | AK17: 6.8907231 | AL17: 4.7186933 | AM17: 36.059756 | AN17: 0.92048193 | AO17: 0.8883 | AP17: 85.227273 | AQ17: 15.963512 | AR17: 0 | AS17: 33.775439 | AT17: 8.3289774 | AU17: 3.3028703 | AV17: 287.24423 | AW17: 0.5065 | AX17: 0.8443 | AY17: 0.8327 | AZ17: 0.3929 | BA17: 0.0473 | BB17: 266 | BC17: 265.68657 | BD17: 0.54941278 | BE17: 21.939559 | BF17: 9.19 | BG17: 38.253 | BH17: 18.571 | BI17: 134.72392 | BJ17: 0 | BK17: 4.5820433 | BL17: 2.2556391 | BM17: 0 | BN17: 0.37139272 | BO17: 0.044444444 | BP17: 0.0701256 | BQ17: 0.0335703 | BR17: 13.121033 | BS17: 6.4186673 | BT17: 0.019337017 | BU17: 59.496235 | BV17: 11.884224 | BW17: 40.957658 | BX17: 2.9530497 | BY17: 41.410057 | BZ17: 19.59138 | CA17: 120.0519 | CB17: 0.017591012 | CC17: 0.32812412 | CD17: 27.211328 | CE17: 25.61826 | CF17: 20.462222 | CG17: 0.232 | CH17: 0.90193047 | CI17: 0 | CJ17: 0 | CK17: 0 | CL17: 0 | CM17: 0 | CN17: 0 | CO17: 0 | CP17: 141.849
A18: Montería | B18: 2019 | C18: 155.16671 | D18: 53.695714 | E18: 0.1756239 | F18: 0.027537717 | G18: 53.802595 | H18: 40.405 | I18: 0.30917052 | J18: 18.943445 | K18: 457.08699 | L18: 14.869586 | M18: 0.54708857 | N18: 439.52542 | O18: 0.49903661 | P18: 85.818141 | Q18: 0.97032855 | R18: 97.942677 | S18: 349.56437 | T18: 45.057205 | U18: 253.24802 | V18: 222.60259 | W18: 925753 | X18: 0.2496 | Y18: 18.014773 | Z18: 326.64202 | AA18: 0 | AB18: 0 | AC18: 11.02 | AD18: 8.0136316 | AE18: 28.751742 | AF18: 61.656988 | AG18: 6138.802 | AH18: 854.741 | AI18: 1.15 | AJ18: 122926.03 | AK18: 36.768132 | AL18: 1.814882 | AM18: 27.104076 | AN18: 0.88900659 | AO18: 0.88631803 | AP18: 88.971808 | AQ18: 20.876572 | AR18: 36.571986 | AS18: 25.532516 | AT18: 11.200241 | AU18: 4.5383668 | AV18: 501.89944 | AW18: 0.6491 | AX18: 0.9512 | AY18: 0.8229 | AZ18: 0.4693 | BA18: 0.0254 | BB18: 263.45934 | BC18: 252.56307 | BD18: 0.40755778 | BE18: 27.135853 | BF18: 65.211 | BG18: 129.026 | BH18: 10.848 | BI18: 142.38257 | BJ18: 8.5295657 | BK18: 66.698354 | BL18: 15.551839 | BM18: 57.534579 | BN18: 0.32232497 | BO18: 0.063636364 | BP18: 0.1092625 | BQ18: 0.1315077 | BR18: 8.555104 | BS18: 6.3389247 | BT18: 0.065874036 | BU18: 69.984093 | BV18: 9.343628 | BW18: 34.011316 | BX18: 7.2911187 | BY18: 48.464089 | BZ18: 23.194459 | CA18: 65.611655 | CB18: 0.020516664 | CC18: 0.64858309 | CD18: 29.162601 | CE18: 26.756417 | CF18: 10.169704 | CG18: 0.232 | CH18: 0.72391246 | CI18: 2.4443154 | CJ18: 315.72408 | CK18: 1.57 | CL18: 26.23 | CM18: 2.0369295 | CN18: 2.0369295 | CO18: 0 | CP18: 258.69005
A19: Neiva | B19: 2019 | C19: 149.95221 | D19: 58.66125 | E19: 0.22765172 | F19: 0.022607482 | G19: 44.732504 | H19: 95.93 | I19: 0.2404943 | J19: 23.503604 | K19: 1089.0003 | L19: 16.508484 | M19: 0.54334043 | N19: 514.14286 | O19: 0.45040984 | P19: 94.752798 | Q19: 0.8967703 | R19: 98.754414 | S19: 371.41246 | T19: 94.752798 | U19: 164.46571 | V19: 150.32974 | W19: 262455 | X19: 0.14 | Y19: 13.583249 | Z19: 748.22604 | AA19: 13.848536 | AB19: 8.3091215 | AC19: 21.05 | AD19: 6.9987286 | AE19: 41.140235 | AF19: 75.008927 | AG19: 8483.581 | AH19: 1162.134 | AI19: 1.1304 | AJ19: 77886.351 | AK19: 53.853321 | AL19: 1.814882 | AM19: 30.834356 | AN19: 0.87143901 | AO19: 0.84421889 | AP19: 95.492123 | AQ19: 9.3739538 | AR19: 33.45041 | AS19: 44.48439 | AT19: 21.901406 | AU19: 9.7874746 | AV19: 429.22058 | AW19: 0.7354 | AX19: 0.9262 | AY19: 0.7924 | AZ19: 0.4643 | BA19: 0.0481 | BB19: 275 | BC19: 265.52419 | BD19: 0.63950276 | BE19: 27.146869 | BF19: 68.709 | BG19: 167.706 | BH19: 17.526 | BI19: 143.4953 | BJ19: 4.3003413 | BK19: 46.842222 | BL19: 13.376988 | BM19: 0 | BN19: 0.38631791 | BO19: 0.10659898 | BP19: 0.0190888 | BQ19: 0.0262272 | BR19: 10.688544 | BS19: 9.9974258 | BT19: 0.037223622 | BU19: 65.949985 | BV19: 11.666187 | BW19: 43.968758 | BX19: 10.064947 | BY19: 52.461997 | BZ19: 43.388146 | CA19: 142.03 | CB19: 0.032899825 | CC19: 0.62507119 | CD19: 29.327077 | CE19: 26.99726 | CF19: 9.9816124 | CG19: 0.235 | CH19: 0.73831909 | CI19: 2.2384385 | CJ19: 235.03604 | CK19: 1.61 | CL19: 16.29 | CM19: 16.788288 | CN19: 0 | CO19: 0 | CP19: 554.01352
A20: Pasto | B20: 2019 | C20: 166.60924 | D20: 42.69375 | E20: 0.2440623 | F20: 0.022255849 | G20: 59.268139 | H20: 45.93 | I20: 0.17287671 | J20: 12.979411 | K20: 1370.7276 | L20: 16.03339 | M20: 0.54149888 | N20: 438.96203 | O20: 0.4862239 | P20: 57.331301 | Q20: 0.23910316 | R20: 97.647431 | S20: 421.17255 | T20: 55.338916 | U20: 227.88356 | V20: 162.00725 | W20: 320855 | X20: 0.129 | Y20: 16.222466 | Z20: 426.84448 | AA20: 25.461619 | AB20: 15.276971 | AC20: 19.64 | AD20: 7.8268089 | AE20: 42.78149 | AF20: 72.128252 | AG20: 8659.218 | AH20: 1326.048 | AI20: 1.3043 | AJ20: 48723.681 | AK20: 30.859835 | AL20: 2.1778584 | AM20: 28.330555 | AN20: 0.9827044 | AO20: 0.93136118 | AP20: 90.659451 | AQ20: 11.012283 | AR20: 63.424947 | AS20: 47.25891 | AT20: 14.037846 | AU20: 5.5439987 | AV20: 612.32281 | AW20: 0.7522 | AX20: 1 | AY20: 0.9836 | AZ20: 0.5491 | BA20: 0.0166 | BB20: 280.31664 | BC20: 273.41802 | BD20: 0.7454844 | BE20: 23.116995 | BF20: 93.752 | BG20: 301.233 | BH20: 12.718 | BI20: 150.57425 | BJ20: 6.870229 | BK20: 33.079035 | BL20: 15.444799 | BM20: 41.480277 | BN20: 0.37359098 | BO20: 0.19285714 | BP20: 0.0157584 | BQ20: 0.5792709 | BR20: 8.0675947 | BS20: 6.1919426 | BT20: 0.060830251 | BU20: 63.872417 | BV20: 9.174385 | BW20: 39.235306 | BX20: 11.803796 | BY20: 44.351318 | BZ20: 44.027336 | CA20: 95.987584 | CB20: 0.027950925 | CC20: 0.53252738 | CD20: 29.28248 | CE20: 25.601987 | CF20: 7.1285296 | CG20: 0.164 | CH20: 0.27679371 | CI20: 1.017993 | CJ20: 463.18683 | CK20: 0.66 | CL20: 19.16 | CM20: 0 | CN20: 0 | CO20: 0 | CP20: 290.12801
A21: Pereira AM | B21: 2019 | C21: 212.94549 | D21: 68.687031 | E21: 0.35678044 | F21: 0.029528508 | G21: 54.712714 | H21: 96.378402 | I21: 0.25860324 | J21: 23.864003 | K21: 538.90534 | L21: 12.914637 | M21: 0.61513804 | N21: 575.96703 | O21: 0.67710985 | P21: 61.13564 | Q21: 0.80084021 | R21: 99.675523 | S21: 390.00571 | T21: 56.387065 | U21: 313.41883 | V21: 256.97066 | W21: 1742190 | X21: 0.2754 | Y21: 26.381994 | Z21: 1081.4043 | AA21: 6.9339184 | AB21: 22.188539 | AC21: 21.649968 | AD21: 9.3829529 | AE21: 51.421193 | AF21: 84.527515 | AG21: 13890.201 | AH21: 1719.192 | AI21: 1.4839 | AJ21: 55847.789 | AK21: 49.307349 | AL21: 4.9001815 | AM21: 31.038908 | AN21: 0.92866525 | AO21: 0.89929386 | AP21: 93.26104 | AQ21: 8.9359362 | AR21: 95.85102 | AS21: 58.511704 | AT21: 24.284477 | AU21: 11.755341 | AV21: 284.26239 | AW21: 0.72912058 | AX21: 1 | AY21: 0.88778685 | AZ21: 0.51215717 | BA21: 0.044599694 | BB21: 266.18296 | BC21: 259.45425 | BD21: 0.49303182 | BE21: 27.213253 | BF21: 77.772 | BG21: 308.497 | BH21: 26.136 | BI21: 146.89639 | BJ21: 7.9752066 | BK21: 49.386757 | BL21: 25.666891 | BM21: 23.998065 | BN21: 0.58693878 | BO21: 0.082932692 | BP21: 0.0262021 | BQ21: 0.0434395 | BR21: 9.1806224 | BS21: 8.9363673 | BT21: 0.068803016 | BU21: 66.903887 | BV21: 8.9596854 | BW21: 48.101108 | BX21: 7.3239056 | BY21: 40.860859 | BZ21: 30.807147 | CA21: 92.216244 | CB21: 0.041327521 | CC21: 0.51491583 | CD21: 30.014016 | CE21: 27.778096 | CF21: 21.374127 | CG21: 0.109 | CH21: 0.26233758 | CI21: 3.2286593 | CJ21: 280.75298 | CK21: 1.32 | CL21: 30.19 | CM21: 19.652709 | CN21: 11.230119 | CO21: 18.248944 | CP21: 1323.7503
A22: Popayán | B22: 2019 | C22: 141.23465 | D22: 28.315 | E22: 0.26275231 | F22: 0.019501512 | G22: 61.323227 | H22: 51.285 | I22: 0.29664651 | J22: 20.750867 | K22: 1493.4336 | L22: 44.016991 | M22: 0.49257691 | N22: 342.17568 | O22: 0.62003454 | P22: 89.829511 | Q22: 0.78968843 | R22: 96.265853 | S22: 380.95534 | T22: 89.829511 | U22: 265.07929 | V22: 253.05493 | W22: 110207 | X22: 0.1192 | Y22: 14.918002 | Z22: 497.26623 | AA22: 18.634061 | AB22: 93.170306 | AC22: 18.09 | AD22: 8.4401735 | AE22: 44.266117 | AF22: 73.673502 | AG22: 17235.375 | AH22: 1837.65 | AI22: 1.75 | AJ22: 47015.21 | AK22: 45.761315 | AL22: 3.8112523 | AM22: 28.117544 | AN22: 0.99199634 | AO22: 0.96424452 | AP22: 91.840316 | AQ22: 10.004764 | AR22: 23.707918 | AS22: 34.544496 | AT22: 11.526213 | AU22: 5.0597888 | AV22: 471.92502 | AW22: 0.6311 | AX22: 0.9699 | AY22: 0.8484 | AZ22: 0.4778 | BA22: 0.0249 | BB22: 272.24484 | BC22: 265.90487 | BD22: 0.67995019 | BE22: 27.283935 | BF22: 105.046 | BG22: 297.083 | BH22: 51.416 | BI22: 147.31347 | BJ22: 8.2398619 | BK22: 40.104986 | BL22: 15.844233 | BM22: 12.520495 | BN22: 0.38963804 | BO22: 0.10055866 | BP22: 0.0279216 | BQ22: 0.0421175 | BR22: 7.5457698 | BS22: 5.6498951 | BT22: 0.042849193 | BU22: 63.383561 | BV22: 10.391371 | BW22: 41.448531 | BX22: 10.54322 | BY22: 51.854207 | BZ22: 47.199287 | CA22: 104.72826 | CB22: 0.033783761 | CC22: 0.43439693 | CD22: 29.061727 | CE22: 26.433097 | CF22: 13.484793 | CG22: 0.109 | CH22: 0.26200494 | CI22: 3.4584778 | CJ22: 468.46654 | CK22: 2.23 | CL22: 20.85 | CM22: 18.864425 | CN22: 0 | CO22: 3.1440708 | CP22: 537.6361
A23: Puerto Carreño | B23: 2019 | C23: 111.293 | D23: 24.574286 | E23: 0.2201201 | F23: 0.025282097 | G23: 48.946475 | H23: 71.79 | I23: 0.0056959772 | J23: 52.541078 | K23: 620.94001 | L23: 57.317539 | M23: 0.62853842 | N23: 253.5 | O23: 0.68571429 | P23: 61.333786 | Q23: n/a | R23: 69.074038 | S23: 405.59447 | T23: 0 | U23: 130.32652 | V23: 135.62295 | W23: 40482 | X23: 0.0034 | Y23: N/A | Z23: 2408.7696 | AA23: 0 | AB23: 0 | AC23: 3.91 | AD23: 1.0861625 | AE23: 23.427662 | AF23: 52.970145 | AG23: 2676.864 | AH23: 286.807 | AI23: 1.25 | AJ23: 77761.886 | AK23: 31.174866 | AL23: 0 | AM23: 28.200001 | AN23: 1 | AO23: 0.9807 | AP23: 65.068493 | AQ23: 26.258206 | AR23: 0 | AS23: 43.039478 | AT23: 4.6378747 | AU23: 2.8754823 | AV23: 200.61139 | AW23: 0.6279 | AX23: 0.9155 | AY23: 0.6097 | AZ23: 0.2633 | BA23: 0.0837 | BB23: 240 | BC23: 239.55758 | BD23: 0.23913043 | BE23: 31.302795 | BF23: 5.635 | BG23: 14.531 | BH23: 33.07 | BI23: 134.4361 | BJ23: 0 | BK23: 0 | BL23: 4.3478261 | BM23: 0 | BN23: 0.46296296 | BO23: 0.014388489 | BP23: 0.2314768 | BQ23: 0.0349768 | BR23: 4.7764616 | BS23: 4.2510508 | BT23: 0.02247191 | BU23: 69.94931 | BV23: 18.072743 | BW23: 36.862535 | BX23: 12.266318 | BY23: 52.424778 | BZ23: 45.276185 | CA23: 78.297615 | CB23: 0.019869875 | CC23: 0.21231397 | CD23: 25.546077 | CE23: 14.741756 | CF23: 0.36134081 | CG23: 1 | CH23: 1 | CI23: 0 | CJ23: 0 | CK23: 0 | CL23: 0 | CM23: 0 | CN23: 0 | CO23: 0 | CP23: 0
A24: Quibdó | B24: 2019 | C24: 116.55622 | D24: 52.468571 | E24: 0.088192172 | F24: 0.0145922 | G24: 54.090672 | H24: 25 | I24: 0.44373866 | J24: 73.508361 | K24: 901.44463 | L24: 64.996866 | M24: 0.48732175 | N24: 242.9697 | O24: 0.58655222 | P24: 43.688484 | Q24: 0.12944822 | R24: 84.901817 | S24: 384.21926 | T24: 16.743591 | U24: 313.78177 | V24: 376.1778 | W24: 329654 | X24: 0.0162 | Y24: 22.556875 | Z24: 293.33705 | AA24: 7.6898233 | AB24: 38.449116 | AC24: 12.1 | AD24: 5.4617991 | AE24: 25.807755 | AF24: 61.449661 | AG24: 5077.838 | AH24: 317.874 | AI24: 1 | AJ24: 75067.205 | AK24: 11.383675 | AL24: 9.2558984 | AM24: 30.886301 | AN24: 0.86061453 | AO24: 0.8481914 | AP24: 73.389884 | AQ24: 23.393855 | AR24: 30.646644 | AS24: 1.2714416 | AT24: 23.933017 | AU24: 2.3746041 | AV24: 326.53188 | AW24: 0.7622 | AX24: 0.967 | AY24: 0.7815 | AZ24: 0.4012 | BA24: 0.0103 | BB24: 220 | BC24: 222.12317 | BD24: 0.59453782 | BE24: 23.953782 | BF24: 98.916 | BG24: 160.669 | BH24: 7.786 | BI24: 125.92891 | BJ24: 3.248731 | BK24: 0.55061095 | BL24: 3.7142857 | BM24: 0 | BN24: 0.25272727 | BO24: 0 | BP24: 0.0569312 | BQ24: 0.0418191 | BR24: 11.68396 | BS24: 7.0800158 | BT24: 0.016393443 | BU24: 62.547303 | BV24: 18.337845 | BW24: 40.016656 | BX24: 4.4187752 | BY24: 51.649352 | BZ24: 46.101949 | CA24: 89.765117 | CB24: 0.007771124 | CC24: 0.27534824 | CD24: 27.916273 | CE24: 25.92316 | CF24: 13.691245 | CG24: 0.564 | CH24: 0.5686953 | CI24: 0.77377222 | CJ24: 123.80355 | CK24: 0 | CL24: 33.33 | CM24: 0 | CN24: 0 | CO24: 0 | CP24: 263.08255
A25: Riohacha | B25: 2019 | C25: 107.56127 | D25: 38.6925 | E25: 0.078742389 | F25: 0.0084998989 | G25: 42.574254 | H25: 53.55 | I25: 0.21068702 | J25: 34.040018 | K25: 658.4616 | L25: 23.402513 | M25: 0.34361027 | N25: 167.82857 | O25: 0.37719298 | P25: 86.087553 | Q25: 0.84676832 | R25: 68.453627 | S25: 402.10983 | T25: 90.001444 | U25: 272.54337 | V25: 211.91106 | W25: 170019 | X25: 0.218 | Y25: N/A | Z25: 1066.6759 | AA25: 0 | AB25: 15.325905 | AC25: 11.59 | AD25: 5.8922053 | AE25: 21.274722 | AF25: 63.880453 | AG25: 4965.623 | AH25: 600.24 | AI25: 1.4444 | AJ25: 99720.75 | AK25: 28.549156 | AL25: 1.9963702 | AM25: 30.770971 | AN25: 0.9205298 | AO25: 0.82188916 | AP25: 74.028238 | AQ25: 17.111786 | AR25: 109.56331 | AS25: 27.596075 | AT25: 10.300263 | AU25: 3.8611792 | AV25: 391.46021 | AW25: 0.8064 | AX25: 1 | AY25: 0.7726 | AZ25: 0.338 | BA25: 0.0316 | BB25: 240 | BC25: 232.30077 | BD25: 0.20585162 | BE25: 26.343783 | BF25: 53.255 | BG25: 38.851 | BH25: 13.164 | BI25: 138.70181 | BJ25: 6.4963504 | BK25: 4.5865417 | BL25: 7.1428571 | BM25: 20.801034 | BN25: 0.32056194 | BO25: 0.047337278 | BP25: 0.0586722 | BQ25: 0.0248476 | BR25: 10.10563 | BS25: 4.6379525 | BT25: 0.029816514 | BU25: 67.152643 | BV25: 14.16324 | BW25: 31.666393 | BX25: 16.517691 | BY25: 62.102157 | BZ25: 21.730506 | CA25: 73.398615 | CB25: 0.016507084 | CC25: 0.25103845 | CD25: 28.329014 | CE25: 27.95877 | CF25: 85.738717 | CG25: 0.159 | CH25: 0.99425058 | CI25: 3.723127 | CJ25: 420.18148 | CK25: 1.67 | CL25: 13.64 | CM25: 0 | CN25: 0 | CO25: 0 | CP25: 101.0563
A26: San Andrés | B26: 2019 | C26: 129.70612 | D26: 71.24 | E26: 0.36534561 | F26: 0.038897161 | G26: 52.03 | H26: 55.95 | I26: 0.44179793 | J26: 45.215315 | K26: 1148.469 | L26: 18.086126 | M26: 0.4717174 | N26: 189.31818 | O26: 0.43181818 | P26: 20.498095 | Q26: n/a | R26: 99.806392 | S26: 423.9339 | T26: 6.7865044 | U26: - | V26: - | W26: 1983714 | X26: 0.264 | Y26: N/A | Z26: 0 | AA26: 0 | AB26: 17.74371 | AC26: 7.27 | AD26: 1.6699863 | AE26: 36.909532 | AF26: 77.338454 | AG26: 6825.282 | AH26: 144.196 | AI26: 0.5 | AJ26: 1822.7651 | AK26: 7.3232895 | AL26: 4.9001815 | AM26: 28.43903 | AN26: 0.95887192 | AO26: 0.9689 | AP26: 92.144638 | AQ26: 16.021362 | AR26: 132.1004 | AS26: 85.672324 | AT26: 44.5256 | AU26: 28.8584 | AV26: 283.95218 | AW26: 0.6952 | AX26: 0.9529 | AY26: 0.8596 | AZ26: 0.5132 | BA26: 0.0219 | BB26: 237 | BC26: 229.58713 | BD26: 0.45945946 | BE26: 23.564865 | BF26: 1.593 | BG26: 18.035 | BH26: 29.405 | BI26: 134.52527 | BJ26: 40.740741 | BK26: 9.3220339 | BL26: 40.123457 | BM26: 83.00885 | BN26: 0.68243243 | BO26: 0 | BP26: 0.2503977 | BQ26: 0.0228667 | BR26: 16.639236 | BS26: 16.132825 | BT26: 0.06838565 | BU26: 72.94158 | BV26: 7.0936768 | BW26: 64.94183 | BX26: 1.2342078 | BY26: 35.211783 | BZ26: 43.244045 | CA26: 112.91391 | CB26: 0.0028047564 | CC26: 0.23938926 | CD26: 27.81758 | CE26: 21.959229 | CF26: 0.67034096 | CG26: 0.334 | CH26: 0.12241218 | CI26: 0 | CJ26: 72.344505 | CK26: 0 | CL26: 0 | CM26: 18.086126 | CN26: 0 | CO26: 0 | CP26: 1501.1485
A27: San José del Guaviare | B27: 2019 | C27: 114.39855 | D27: 43.812857 | E27: 0.16215435 | F27: 0.018614027 | G27: 43.717002 | H27: 90.7 | I27: 0.00047483381 | J27: 32.187825 | K27: 325.66506 | L27: 51.12184 | M27: 0.51636479 | N27: 380 | O27: 0 | P27: 27.156869 | Q27: 0.37061619 | R27: 83.954403 | S27: 538.90693 | T27: 27.156869 | U27: 222.70486 | V27: 238.01354 | W27: 26677 | X27: 0.021 | Y27: N/A | Z27: 2296.696 | AA27: 0 | AB27: 0 | AC27: 4.07 | AD27: 7.0729199 | AE27: 37.631111 | AF27: 69.987768 | AG27: 7627.925 | AH27: 323.378 | AI27: 1.4 | AJ27: 72257.527 | AK27: 20.799281 | AL27: 5.0816697 | AM27: 32.362648 | AN27: 0.96329365 | AO27: 0.9423 | AP27: 67.136659 | AQ27: 19.328586 | AR27: 97.465887 | AS27: 44.945449 | AT27: 8.6991192 | AU27: 2.7788853 | AV27: 200.70056 | AW27: 0.4965 | AX27: 0.9302 | AY27: 0.7797 | AZ27: 0.3641 | BA27: 0.0383 | BB27: 240 | BC27: 237.18345 | BD27: 0.41796875 | BE27: 27.0625 | BF27: 10.827 | BG27: 11.648 | BH27: 29.468 | BI27: 138.47952 | BJ27: 0 | BK27: 0 | BL27: 4 | BM27: 0 | BN27: 0.44954128 | BO27: 0.10638298 | BP27: 0.2060204 | BQ27: 0.0444669 | BR27: 9.8456878 | BS27: 3.9761431 | BT27: 0.014285714 | BU27: 85.349123 | BV27: 11.188238 | BW27: 23.440571 | BX27: 14.344108 | BY27: 45.346824 | BZ27: 50.080923 | CA27: 78.056005 | CB27: 0 | CC27: 0.1541265 | CD27: 26.929023 | CE27: 18.934738 | CF27: 0.10706745 | CG27: 0.69 | CH27: 0.69045677 | CI27: 0 | CJ27: 0 | CK27: 0 | CL27: 0 | CM27: 0 | CN27: 0 | CO27: 0 | CP27: 18.934015
A28: Santa Marta | B28: 2019 | C28: 155.51216 | D28: 78.956667 | E28: 0.2839725 | F28: 0.034354895 | G28: 56.148738 | H28: 43.895 | I28: 0.18933333 | J28: 21.434638 | K28: 756.02173 | L28: 14.623632 | M28: 0.4560801 | N28: 330 | O28: 0.41573816 | P28: 20.685848 | Q28: 0.88160665 | R28: 94.98991 | S28: 314.68221 | T28: 16.953673 | U28: 136.2439 | V28: 138.69181 | W28: 1985735 | X28: 0.2664 | Y28: 39.716099 | Z28: 32.272152 | AA28: 9.5925286 | AB28: 32.614597 | AC28: 14.98 | AD28: 9.5452522 | AE28: 32.415684 | AF28: 65.502062 | AG28: 7050.773 | AH28: 1207.506 | AI28: 2 | AJ28: 167979.51 | AK28: 15.931754 | AL28: 1.6333938 | AM28: 28.382429 | AN28: 0.90235281 | AO28: 0.84314817 | AP28: 89.33506 | AQ28: 10.087862 | AR28: 94.161959 | AS28: 29.513783 | AT28: 12.275051 | AU28: 4.5090501 | AV28: 414.26946 | AW28: 0.6811 | AX28: 0.959 | AY28: 0.8677 | AZ28: 0.5086 | BA28: 0.0377 | BB28: 243.40528 | BC28: 234.35996 | BD28: 0.34204355 | BE28: 31.357789 | BF28: 59.212 | BG28: 194.552 | BH28: 21.593 | BI28: 143.20719 | BJ28: 8.1266491 | BK28: 65.894543 | BL28: 18.660812 | BM28: 43.665437 | BN28: 0.3623431 | BO28: 0.042372881 | BP28: 0.0850895 | BQ28: 0.0412927 | BR28: 16.606837 | BS28: 10.20449 | BT28: 0.056733412 | BU28: 61.420714 | BV28: 8.7916481 | BW28: 35.910617 | BX28: 9.6967028 | BY28: 61.543285 | BZ28: 38.883256 | CA28: 68.961082 | CB28: 0.013764698 | CC28: 0.526567 | CD28: 29.304111 | CE28: 27.582568 | CF28: 22.581276 | CG28: 0.138 | CH28: 0.32337919 | CI28: 4.4071219 | CJ28: 320.51796 | CK28: 1.4 | CL28: 27.23 | CM28: 2.0032372 | CN28: 2.0032372 | CO28: 2.0032372 | CP28: 282.45645
A29: Sincelejo | B29: 2019 | C29: 144.12615 | D29: 43.60375 | E29: 0.17517011 | F29: 0.027402649 | G29: 54.735316 | H29: 43.16 | I29: 0.42192531 | J29: 14.400248 | K29: 774.73333 | L29: 16.560285 | M29: 0.48783668 | N29: 316.33333 | O29: 0.47494033 | P29: 78.058686 | Q29: 0.94503096 | R29: 97.644088 | S29: 380.76289 | T29: 71.326746 | U29: 291.7291 | V29: 248.27287 | W29: 93063 | X29: 0.1116 | Y29: 10.783179 | Z29: 339.88185 | AA29: 3.4887575 | AB29: 0 | AC29: 13.3 | AD29: 7.3443375 | AE29: 28.712519 | AF29: 58.86425 | AG29: 4505.713 | AH29: 927.168 | AI29: 1.125 | AJ29: 98218.52 | AK29: 29.594946 | AL29: 1.814882 | AM29: 25.24472 | AN29: 0.95603968 | AO29: 0.94222752 | AP29: 90.988372 | AQ29: 11.24978 | AR29: 87.443162 | AS29: 33.883582 | AT29: 12.863826 | AU29: 5.2383621 | AV29: 697.33199 | AW29: 0.7975 | AX29: 1 | AY29: 0.8452 | AZ29: 0.5051 | BA29: 0.0267 | BB29: 260 | BC29: 252.52997 | BD29: 0.51019313 | BE29: 28.666309 | BF29: 79.448 | BG29: 91.732 | BH29: 14.46 | BI29: 140.77264 | BJ29: 5.5281343 | BK29: 3.7766259 | BL29: 11.072056 | BM29: 55.3206 | BN29: 0.26790451 | BO29: 0.095652174 | BP29: 0.0234135 | BQ29: 0.065118 | BR29: 10.080173 | BS29: 6.5845133 | BT29: 0.046473483 | BU29: 70.087319 | BV29: 9.994997 | BW29: 29.353862 | BX29: 10.591129 | BY29: 58.120367 | BZ29: 45.649163 | CA29: 67.794253 | CB29: 0.011859836 | CC29: 0.43116737 | CD29: 28.762979 | CE29: 27.64656 | CF29: 33.615867 | CG29: 0.189 | CH29: 0.99255653 | CI29: 1.800031 | CJ29: 324.00557 | CK29: 0.87 | CL29: 16.67 | CM29: 3.6000619 | CN29: 0 | CO29: 0 | CP29: 223.20384
A30: Tunja | B30: 2019 | C30: 176.70667 | D30: 77.376667 | E30: 0.40121735 | F30: 0.024713387 | G30: 51.533474 | H30: 55.43 | I30: 0.28424089 | J30: 4.0568422 | K30: 721.53835 | L30: 16.806917 | M30: 0.50346084 | N30: 255.91892 | O30: 0.54352159 | P30: 92.840528 | Q30: 1 | R30: 98.538834 | S30: 397.9965 | T30: 90.95431 | U30: 273.53083 | V30: 273.53083 | W30: N/A | X30: NA | Y30: 10.3747 | Z30: 503.3382 | AA30: 39.694466 | AB30: 62.377018 | AC30: 23.94 | AD30: 8.0160199 | AE30: 47.805259 | AF30: 76.247644 | AG30: 21081.282 | AH30: 2616.603 | AI30: 3.2308 | AJ30: 35336.873 | AK30: 41.719452 | AL30: 0.1814882 | AM30: 29.995695 | AN30: 0.93272727 | AO30: 0.89433826 | AP30: 91.853035 | AQ30: 9.2670598 | AR30: 0 | AS30: 53.253884 | AT30: 14.038391 | AU30: 5.7336435 | AV30: 460.74136 | AW30: 0.8264 | AX30: 1 | AY30: 0.9462 | AZ30: 0.5286 | BA30: 0.0176 | BB30: 284 | BC30: 275.58228 | BD30: 0.81220096 | BE30: 29.94378 | BF30: 190.859 | BG30: 1301.4873 | BH30: 46.421 | BI30: 153.21666 | BJ30: 9.4611931 | BK30: 60.868014 | BL30: 21.776156 | BM30: 0 | BN30: 0.55945252 | BO30: 0.069565217 | BP30: 0.0148993 | BQ30: 0.0354844 | BR30: 15.76373 | BS30: 10.704268 | BT30: 0.028153763 | BU30: 57.731734 | BV30: 12.68416 | BW30: 56.054846 | BX30: 7.4374328 | BY30: 36.901107 | BZ30: 58.251964 | CA30: 137.91312 | CB30: 0.050307466 | CC30: 0.47190993 | CD30: 28.803472 | CE30: 25.926308 | CF30: 7.3721599 | CG30: 0.278 | CH30: 0.51864539 | CI30: 8.6932332 | CJ30: 1244.7371 | CK30: 1.28 | CL30: 17.22 | CM30: 5.7954888 | CN30: 11.590978 | CO30: 5.7954888 | CP30: 730.23159
A31: Valledupar | B31: 2019 | C31: 144.53203 | D31: 19.667143 | E31: 0.22513223 | F31: 0.028574742 | G31: 63.53361 | H31: 52.565 | I31: 0.38360942 | J31: 17.548334 | K31: 705.60628 | L31: 17.752385 | M31: 0.51081565 | N31: 583.19118 | O31: 0.65326633 | P31: 88.204467 | Q31: 0.90607028 | R31: 95.440166 | S31: 363.93913 | T31: 88.204467 | U31: 204.76159 | V31: 195.07044 | W31: 389395 | X31: 0.2354 | Y31: 11.666302 | Z31: 469.72402 | AA31: 3.8934366 | AB31: 9.7335916 | AC31: 13.81 | AD31: 8.5151088 | AE31: 32.025988 | AF31: 72.015974 | AG31: 6428.461 | AH31: 920.239 | AI31: 1.3125 | AJ31: 116781.84 | AK31: 41.240053 | AL31: 3.6297641 | AM31: 27.576504 | AN31: 0.92075628 | AO31: 0.87414501 | AP31: 88.062244 | AQ31: 11.595745 | AR31: 91.687042 | AS31: 44.895192 | AT31: 16.725333 | AU31: 6.7717608 | AV31: 571.34112 | AW31: 0.6092 | AX31: 0.8625 | AY31: 0.7582 | AZ31: 0.4745 | BA31: 0.0268 | BB31: 256.75113 | BC31: 245.99338 | BD31: 0.35505529 | BE31: 32.855055 | BF31: 53.944 | BG31: 240.836 | BH31: 17.537 | BI31: 141.97336 | BJ31: 6.6225166 | BK31: 1.8222587 | BL31: 12.164074 | BM31: 31.318739 | BN31: 0.35922897 | BO31: 0.036697248 | BP31: 0.0900724 | BQ31: 0.0117954 | BR31: 10.36576 | BS31: 6.2010917 | BT31: 0.048371175 | BU31: 63.547888 | BV31: 15.03892 | BW31: 33.080669 | BX31: 7.9107363 | BY31: 60.173676 | BZ31: 24.353376 | CA31: 63.405243 | CB31: 0.010616879 | CC31: 0.53648057 | CD31: 29.192159 | CE31: 28.79043 | CF31: 72.97288 | CG31: 0.087 | CH31: 0.93268315 | CI31: 1.020252 | CJ31: 102.0252 | CK31: 1.32 | CL31: 41.79 | CM31: 0 | CN31: 0 | CO31: 2.040504 | CP31: 199.96939
A32: Villavicencio | B32: 2019 | C32: 145.99526 | D32: 45.861429 | E32: 0.24882873 | F32: 0.02145242 | G32: 44.040958 | H32: 42.95 | I32: 0.14250914 | J32: 22.587172 | K32: 1126.1588 | L32: 40.65691 | M32: 0.48862663 | N32: 523.65333 | O32: 0.61634506 | P32: 41.236269 | Q32: 0.91566336 | R32: 97.409934 | S32: 371.00246 | T32: 41.136122 | U32: 203.27064 | V32: 212.55383 | W32: 114688 | X32: 0.2742 | Y32: 14.309638 | Z32: 1108.202 | AA32: 1.8558936 | AB32: 0 | AC32: 17.26 | AD32: 9.0018468 | AE32: 42.738748 | AF32: 80.937944 | AG32: 3456.029 | AH32: 768.238 | AI32: 1.1304 | AJ32: 111129.84 | AK32: 31.464776 | AL32: 3.6297641 | AM32: 33.017136 | AN32: 0.8112067 | AO32: 0.77554342 | AP32: 85.281491 | AQ32: 7.9291661 | AR32: 52.687039 | AS32: 44.386865 | AT32: 12.98424 | AU32: 5.3475833 | AV32: 350.47762 | AW32: 0.669 | AX32: 0.9327 | AY32: 0.825 | AZ32: 0.481 | BA32: 0.0382 | BB32: 267 | BC32: 263.92289 | BD32: 0.68347761 | BE32: 30.502823 | BF32: 44.085 | BG32: 128.81 | BH32: 11.107 | BI32: 144.11812 | BJ32: 4.9056604 | BK32: 16.802248 | BL32: 12.330226 | BM32: 20.667168 | BN32: 0.52376514 | BO32: 0.079136691 | BP32: 0.0148065 | BQ32: 0.0778745 | BR32: 13.552303 | BS32: 9.6108418 | BT32: 0.048374461 | BU32: 69.418795 | BV32: 11.934315 | BW32: 41.412114 | BX32: 8.1607865 | BY32: 46.345209 | BZ32: 56.836472 | CA32: 85.211963 | CB32: 0.018638141 | CC32: 0.43308801 | CD32: 29.627254 | CE32: 27.176 | CF32: 9.1731717 | CG32: 0.325 | CH32: 0.99024972 | CI32: 0.75290575 | CJ32: 124.22945 | CK32: 1.39 | CL32: 7 | CM32: 5.6467931 | CN32: 3.7645287 | CO32: 1.8822644 | CP32: 346.33664
A33: Yopal | B33: 2019 | C33: 150.38228 | D33: 44.8925 | E33: 0.35083829 | F33: 0.020819421 | G33: 40.118503 | H33: 70.93 | I33: 0.16153295 | J33: 8.3119104 | K33: 989.71104 | L33: 42.15326 | M33: 0.36123921 | N33: 339.62069 | O33: 0.50431034 | P33: 46.427879 | Q33: 0.9011338 | R33: 97.581804 | S33: 404.16274 | T33: 46.767506 | U33: 156.84955 | V33: 142.11612 | W33: 322762 | X33: 0.1456 | Y33: N/A | Z33: 952.12933 | AA33: 5.7600369 | AB33: 0 | AC33: 13.51 | AD33: 8.8933978 | AE33: 43.496832 | AF33: 75.662099 | AG33: 4859.024 | AH33: 306.886 | AI33: 1 | AJ33: 41216.348 | AK33: 37.824672 | AL33: 1.6333938 | AM33: 34.13717 | AN33: 0.8730209 | AO33: 0.8619 | AP33: 85.791978 | AQ33: 8.5337471 | AR33: 38.299502 | AS33: 48.156498 | AT33: 12.366113 | AU33: 4.9464452 | AV33: 327.72675 | AW33: 0.8297 | AX33: 0.972 | AY33: 0.8716 | AZ33: 0.4852 | BA33: 0.0201 | BB33: 268 | BC33: 262.78808 | BD33: 0.64637198 | BE33: 28.464554 | BF33: 43.513 | BG33: 140.601 | BH33: 15.849 | BI33: 143.91635 | BJ33: 1.6574586 | BK33: 11.935484 | BL33: 9.0666667 | BM33: 0 | BN33: 0.57355372 | BO33: 0.096774194 | BP33: 0.0651126 | BQ33: 0.019376 | BR33: 11.102337 | BS33: 12.242257 | BT33: 0.045101843 | BU33: 71.703718 | BV33: 10.785128 | BW33: 41.158684 | BX33: 6.7966447 | BY33: 42.751285 | BZ33: 59.193011 | CA33: 96.220953 | CB33: 0.00933886 | CC33: 0.29745406 | CD33: 29.110204 | CE33: 27.971055 | CF33: 33.311302 | CG33: 0.428 | CH33: 0.9997913 | CI33: 0 | CJ33: 71.244946 | CK33: 0.08 | CL33: 0 | CM33: 0 | CN33: 0 | CO33: 0 | CP33: 207.79776
A34: Arauca | B34: 2020 | C34: 126.80201 | D34: 21.032857 | E34: 0.1461256 | F34: 0.012 | G34: 55.585659 | H34: 37.82 | I34: 0.072591526 | J34: 35.918367 | K34: 773.87755 | L34: 48.979592 | M34: 0.46868513 | N34: 351.65217 | O34: 0.65502183 | P34: 47.322365 | Q34: n/a | R34: 97.950245 | S34: 447.05829 | T34: 47.37097 | U34: 523.38495 | V34: 360.51223 | W34: 135799 | X34: 0.1088 | Y34: N/A | Z34: 2024.9252 | AA34: 0 | AB34: 0 | AC34: 8.04 | AD34: 7.2683088 | AE34: 22.427528 | AF34: 68.294633 | AG34: 936.308 | AH34: 439.256 | AI34: 0.2857 | AJ34: 36953.685 | AK34: 41.551358 | AL34: 0 | AM34: 28.831922 | AN34: 1 | AO34: 1 | AP34: 75.063776 | AQ34: 10.631229 | AR34: 130.80445 | AS34: 51.587061 | AT34: 11.06712 | AU34: 4.2483462 | AV34: 170.88435 | AW34: 0.5415 | AX34: 0.958 | AY34: 0.7495 | AZ34: 0.3984 | BA34: 0.0343 | BB34: 255 | BC34: 250.66424 | BD34: 0.54151329 | BE34: 26.641309 | BF34: 17.654 | BG34: 40.895 | BH34: 8.796 | BI34: 133.02991 | BJ34: 54.545455 | BK34: 1.1866728 | BL34: 5.4631829 | BM34: 0 | BN34: 0.40883978 | BO34: 0.083916084 | BP34: 0.1386173 | BQ34: 0.064505 | BR34: 11.428571 | BS34: 7.1836735 | BT34: 0.036363636 | BU34: 66.889776 | BV34: 27.200176 | BW34: 38.480528 | BX34: 13.983287 | BY34: 51.732804 | BZ34: 43.633097 | CA34: 73.106292 | CB34: 0.0039138006 | CC34: 0.1827006 | CD34: 28.410281 | CE34: 26.466404 | CF34: 14.35078 | CG34: 0.503 | CH34: 0.98958014 | CI34: 0 | CJ34: 54.421769 | CK34: 0 | CL34: 0 | CM34: 0 | CN34: 0 | CO34: 0 | CP34: 97.959184
A35: Armenia | B35: 2020 | C35: 192.11554 | D35: 53.9325 | E35: 0.31850267 | F35: 0.031 | G35: 52.10838 | H35: 42.44 | I35: 0.39631976 | J35: 22.652018 | K35: 812.14148 | L35: 10.992891 | M35: 0.62494669 | N35: 481.74576 | O35: 0.24316748 | P35: 100 | Q35: 0.85474955 | R35: 99.648786 | S35: 406.44898 | T35: 99.998082 | U35: 357.97343 | V35: 378.80844 | W35: 443476 | X35: 0.244 | Y35: 16.787657 | Z35: 262.86335 | AA35: 9.8436823 | AB35: 13.12491 | AC35: 25.14 | AD35: 12.874529 | AE35: 41.797892 | AF35: 74.634168 | AG35: 11731.626 | AH35: 1146.343 | AI35: 1.2632 | AJ35: 62669.815 | AK35: 51.516226 | AL35: 1.4519056 | AM35: 31.269909 | AN35: 0.98597852 | AO35: 0.9487 | AP35: 95.322012 | AQ35: 10.228435 | AR35: 0 | AS35: 54.722509 | AT35: 20.279088 | AU35: 9.8748757 | AV35: 295.14247 | AW35: 0.7441 | AX35: 0.9333 | AY35: 0.8984 | AZ35: 0.5603 | BA35: 0.0449 | BB35: 269 | BC35: 262.25743 | BD35: 0.6025641 | BE35: 24.217338 | BF35: 74.775 | BG35: 185.293 | BH35: 46.061 | BI35: 145.05158 | BJ35: 7.1810089 | BK35: 50.512317 | BL35: 25.108413 | BM35: 57.174482 | BN35: 0.53039514 | BO35: 0.019480519 | BP35: 0.0544573 | BQ35: 0.0782741 | BR35: 11.126138 | BS35: 8.477851 | BT35: 0.058153242 | BU35: 63.139771 | BV35: 15.939118 | BW35: 48.532213 | BX35: 11.325036 | BY35: 49.47834 | BZ35: 34.106354 | CA35: 110.84098 | CB35: 0.037271891 | CC35: 0.59756169 | CD35: 29.033852 | CE35: 26.773255 | CF35: 14.077305 | CG35: 0.21 | CH35: 0.85464445 | CI35: 1.9987075 | CJ35: 513.00159 | CK35: 1.61 | CL35: 25 | CM35: 43.305329 | CN35: 13.324717 | CO35: 19.987075 | CP35: 912.74309
A36: Barranquilla AM | B36: 2020 | C36: 196.5267 | D36: 71.188127 | E36: 0.35998238 | F36: 0.043 | G36: 63.382243 | H36: 49.067451 | I36: 0.28163933 | J36: 23.124509 | K36: 865.65404 | L36: 9.6219222 | M36: 0.48124264 | N36: 451.515 | O36: 0.45247225 | P36: 94.206461 | Q36: 0.89461665 | R36: 99.658033 | S36: 388.90374 | T36: 86.178068 | U36: 239.79167 | V36: 242.99577 | W36: 2671774 | X36: 0.3164 | Y36: 20.683537 | Z36: 651.73373 | AA36: 5.6722346 | AB36: 10.313154 | AC36: 16.920492 | AD36: 22.279679 | AE36: 44.982809 | AF36: 77.643446 | AG36: 7280.061 | AH36: 1057.296 | AI36: 2 | AJ36: 99990.406 | AK36: 55.333194 | AL36: 3.4482759 | AM36: 28.368488 | AN36: 1 | AO36: 0.98027061 | AP36: 87.638808 | AQ36: 15.805585 | AR36: 102.29703 | AS36: 62.782608 | AT36: 27.966557 | AU36: 11.947762 | AV36: 275.20824 | AW36: 0.64760642 | AX36: 0.91376019 | AY36: 0.80062101 | AZ36: 0.50949049 | BA36: 0.0086670813 | BB36: 255.24775 | BC36: 251.02746 | BD36: 0.46319164 | BE36: 29.547495 | BF36: 54.239 | BG36: 432.473 | BH36: 23.911 | BI36: 144.04587 | BJ36: 12.004245 | BK36: 53.155787 | BL36: 33.232423 | BM36: 51.425757 | BN36: 0.4785753 | BO36: 0.11333333 | BP36: 0.0287095 | BQ36: 0.0736313 | BR36: 21.545663 | BS36: 14.29201 | BT36: 0.058322485 | BU36: 63.193759 | BV36: 7.2081099 | BW36: 38.07934 | BX36: 12.879118 | BY36: 48.582146 | BZ36: 34.257098 | CA36: 80.912117 | CB36: 0.041266947 | CC36: 0.76229181 | CD36: 31.094365 | CE36: 28.838129 | CF36: 30.772571 | CG36: 0.131 | CH36: 0.049781166 | CI36: 6.7512935 | CJ36: 640.04389 | CK36: 1.63 | CL36: 21.6 | CM36: 16.479535 | CN36: 3.7211854 | CO36: 3.7211854 | CP36: 1166.3258
A37: Bogotá D.C. | B37: 2020 | C37: 207.78411 | D37: 91.9025 | E37: 0.54928466 | F37: 0.039 | G37: 68.086232 | H37: 48.215 | I37: 0.65729288 | J37: 14.039485 | K37: 1916.9297 | L37: 11.958586 | M37: 0.54546787 | N37: 614.14305 | O37: 0.45201067 | P37: 98.101949 | Q37: 0.96331068 | R37: 99.996899 | S37: 398.5898 | T37: 98.056066 | U37: 324.19767 | V37: 268.78317 | W37: 13937027 | X37: 0.60508 | Y37: 29.186139 | Z37: 769.61797 | AA37: 8.9101757 | AB37: 20.532144 | AC37: 25.24 | AD37: 25.779728 | AE37: 63.897082 | AF37: 87.173928 | AG37: 9825.395 | AH37: 1638.182 | AI37: 2.814 | AJ37: 40850.186 | AK37: 39.10817 | AL37: 3.0852995 | AM37: 33.456585 | AN37: 0.89949711 | AO37: 0.8604 | AP37: 87.819285 | AQ37: 4.9161433 | AR37: 47.017338 | AS37: 122.76516 | AT37: 44.013654 | AU37: 27.319047 | AV37: 183.85667 | AW37: 0.6911 | AX37: 0.9622 | AY37: 0.8752 | AZ37: 0.5549 | BA37: 0.016 | BB37: 274.57283 | BC37: 257.90472 | BD37: 0.37160875 | BE37: 24.15716 | BF37: 82.817 | BG37: 592.791 | BH37: 31.188 | BI37: 152.57052 | BJ37: 8.8106305 | BK37: 33.25359 | BL37: 38.23509 | BM37: 48.549404 | BN37: 0.67928233 | BO37: 0.28574327 | BP37: 0.0052617 | BQ37: 0.0066994 | BR37: 26.835699 | BS37: 26.707947 | BT37: 0.025114651 | BU37: 69.266032 | BV37: 10.624677 | BW37: 56.221686 | BX37: 8.187498 | BY37: 32.937071 | BZ37: 67.224772 | CA37: 116.64923 | CB37: 0.071459118 | CC37: 0.80642076 | CD37: 33.056247 | CE37: 29.668577 | CF37: 36.166201 | CG37: 0.144 | CH37: 0.017302412 | CI37: 7.6519145 | CJ37: 707.63747 | CK37: 2.14 | CL37: 18.8 | CM37: 36.218184 | CN37: 16.594513 | CO37: 30.950085 | CP37: 3573.0885
A38: Bucaramanga AM | B38: 2020 | C38: 197.39408 | D38: 77.063775 | E38: 0.37492822 | F38: 0.027 | G38: 59.348526 | H38: 64.75984 | I38: 0.19091127 | J38: 13.942685 | K38: 939.1567 | L38: 8.3817298 | M38: 0.5347224 | N38: 539.82065 | O38: 0.42752581 | P38: 69.843314 | Q38: 0.95811708 | R38: 99.330587 | S38: 409.23512 | T38: 64.615611 | U38: 246.26885 | V38: 217.31259 | W38: 1844269 | X38: 0.2756 | Y38: 12.858729 | Z38: 935.97326 | AA38: 7.0855709 | AB38: 5.5109996 | AC38: 21.434924 | AD38: 18.768382 | AE38: 50.178464 | AF38: 80.175522 | AG38: 9382.307 | AH38: 1392.245 | AI38: 2.5429 | AJ38: 57402.322 | AK38: 52.176762 | AL38: 3.8112523 | AM38: 28.578598 | AN38: 0.89411116 | AO38: 0.87755518 | AP38: 92.232543 | AQ38: 7.6967855 | AR38: 64.499484 | AS38: 62.598683 | AT38: 22.497449 | AU38: 12.222988 | AV38: 249.11468 | AW38: 0.72790024 | AX38: 0.96302957 | AY38: 0.85611993 | AZ38: 0.50299938 | BA38: 0.034582955 | BB38: 287.38174 | BC38: 277.20161 | BD38: 0.71239728 | BE38: 28.227045 | BF38: 55.166 | BG38: 1123.214 | BH38: 28.625 | BI38: 150.68992 | BJ38: 8.9258489 | BK38: 41.954348 | BL38: 33.426069 | BM38: 51.177343 | BN38: 0.55356619 | BO38: 0.073908175 | BP38: 0.0163077 | BQ38: 0.0052737 | BR38: 12.371111 | BS38: 12.553252 | BT38: 0.057331793 | BU38: 67.619067 | BV38: 11.499574 | BW38: 46.903813 | BX38: 7.1060417 | BY38: 41.478444 | BZ38: 48.57413 | CA38: 90.887295 | CB38: 0.057415759 | CC38: 0.59650357 | CD38: 30.847826 | CE38: 27.850038 | CF38: 8.9234939 | CG38: 0.125 | CH38: 0.34084352 | CI38: 6.8504522 | CJ38: 660.86715 | CK38: 1.36 | CL38: 22.6 | CM38: 26.595873 | CN38: 6.4474844 | CO38: 12.894969 | CP38: 1188.7549
A39: Cali AM | B39: 2020 | C39: 225.73723 | D39: 76.953977 | E39: 0.46183801 | F39: 0.031 | G39: 65.691118 | H39: 65.233563 | I39: 0.42674671 | J39: 52.502149 | K39: 1242.3948 | L39: 22.038989 | M39: 0.55378819 | N39: 436.86081 | O39: 0.44746601 | P39: 81.743899 | Q39: 0.82887373 | R39: 99.407516 | S39: 366.43629 | T39: 81.363658 | U39: 326.93962 | V39: 262.49154 | W39: 5294580 | X39: 0.3974 | Y39: 28.45063 | Z39: 2110.9991 | AA39: 9.3114402 | AB39: 8.4649456 | AC39: 21.833962 | AD39: 21.326559 | AE39: 50.949048 | AF39: 82.960341 | AG39: 5934.428 | AH39: 989.422 | AI39: 1.7627 | AJ39: 77366.662 | AK39: 51.305689 | AL39: 1.9963702 | AM39: 30.038185 | AN39: 0.99056753 | AO39: 0.98422368 | AP39: 92.578746 | AQ39: 8.1983684 | AR39: 44.123546 | AS39: 63.863949 | AT39: 26.085212 | AU39: 12.95607 | AV39: 232.47305 | AW39: 0.57765936 | AX39: 0.80107723 | AY39: 0.76371343 | AZ39: 0.4471526 | BA39: 0.037752168 | BB39: 264.7942 | BC39: 250.68086 | BD39: 0.40927152 | BE39: 30.275644 | BF39: 44.61 | BG39: 265.752 | BH39: 17.896 | BI39: 145.29501 | BJ39: 12.81753 | BK39: 47.41215 | BL39: 32.426493 | BM39: 62.44153 | BN39: 0.59175887 | BO39: 0.15174672 | BP39: 0.0168392 | BQ39: 0.0099212 | BR39: 15.814464 | BS39: 14.736341 | BT39: 0.064124033 | BU39: 65.430467 | BV39: 12.610534 | BW39: 46.963105 | BX39: 11.888363 | BY39: 38.473958 | BZ39: 47.951801 | CA39: 96.454938 | CB39: 0.051213684 | CC39: 0.73252494 | CD39: 31.525095 | CE39: 28.779321 | CF39: 20.606396 | CG39: 0.11 | CH39: 0.025796677 | CI39: 6.4670394 | CJ39: 497.79185 | CK39: 1.51 | CL39: 22.98 | CM39: 23.825935 | CN39: 9.7856517 | CO39: 14.465746 | CP39: 2082.642
A40: Cartagena | B40: 2020 | C40: 190.08831 | D40: 75.61 | E40: 0.39249923 | F40: 0.03 | G40: 58.409707 | H40: 90.7 | I40: 0.28422725 | J40: 18.432078 | K40: 762.29096 | L40: 9.6643867 | M40: 0.54223266 | N40: 477.04615 | O40: 0.38089172 | P40: 45.25179 | Q40: 0.94313443 | R40: 98.324821 | S40: 374.68133 | T40: 43.94764 | U40: 211.45645 | V40: 206.09606 | W40: 5529945 | X40: 0.4714 | Y40: 25.062434 | Z40: 695.43731 | AA40: 9.7206669 | AB40: 92.320676 | AC40: 15.61 | AD40: 23.726601 | AE40: 30.987781 | AF40: 66.898285 | AG40: 4762.974 | AH40: 850.892 | AI40: 1.45 | AJ40: 118654.95 | AK40: 51.698414 | AL40: 0 | AM40: 27.437401 | AN40: 0.98131509 | AO40: 0.9089 | AP40: 88.812931 | AQ40: 11.344696 | AR40: 114.23349 | AS40: 39.201844 | AT40: 19.122164 | AU40: 8.9274315 | AV40: 298.20113 | AW40: 0.7505 | AX40: 1 | AY40: 0.9248 | AZ40: 0.5498 | BA40: 0.0309 | BB40: 244.87184 | BC40: 229.42514 | BD40: 0.4165937 | BE40: 33.808669 | BF40: 44.155 | BG40: 214.995 | BH40: 36.186 | BI40: 140.92172 | BJ40: 6.9120763 | BK40: 40.457132 | BL40: 25.941742 | BM40: 64.324048 | BN40: 0.3937575 | BO40: 0.20385675 | BP40: 0.3478084 | BQ40: 0.0144095 | BR40: 19.737268 | BS40: 13.796161 | BT40: 0.017332274 | BU40: 59.623348 | BV40: 5.716733 | BW40: 41.212352 | BX40: 7.2924414 | BY40: 47.10217 | BZ40: 31.255976 | CA40: 83.660689 | CB40: 0.017814944 | CC40: 0.38170488 | CD40: 30.673628 | CE40: 29.026168 | CF40: 47.0197 | CG40: 0.123 | CH40: 0.069817912 | CI40: 5.0812755 | CJ40: 444.36252 | CK40: 0 | CL40: 23.88 | CM40: 2.9889856 | CN40: 0.99632853 | CO40: 8.9669568 | CP40: 681.48871
A41: Cúcuta AM | B41: 2020 | C41: 149.03775 | D41: 68.30965 | E41: 0.22326164 | F41: 0.025 | G41: 50.886349 | H41: 50 | I41: 0.13689623 | J41: 27.185049 | K41: 551.36595 | L41: 24.527864 | M41: 0.56273499 | N41: 578.0396 | O41: 0.56982422 | P41: 69.084382 | Q41: 0.7600756 | R41: 99.352597 | S41: 427.3878 | T41: 68.720825 | U41: 159.48142 | V41: 150.57238 | W41: 1057441 | X41: 0.2554 | Y41: 13.187929 | Z41: 756.38823 | AA41: 3.9409954 | AB41: 22.660724 | AC41: 13.443165 | AD41: 21.239597 | AE41: 39.469189 | AF41: 74.579021 | AG41: 5290.618 | AH41: 872.716 | AI41: 1.4667 | AJ41: 93883.225 | AK41: 45.332494 | AL41: 1.4519056 | AM41: 27.068235 | AN41: 0.95621527 | AO41: 0.94099285 | AP41: 83.94879 | AQ41: 10.951688 | AR41: 103.59831 | AS41: 46.353495 | AT41: 11.843906 | AU41: 6.2988625 | AV41: 159.63552 | AW41: 0.66405803 | AX41: 0.91859661 | AY41: 0.81998478 | AZ41: 0.46333002 | BA41: 0.032812329 | BB41: 266.42892 | BC41: 262.30305 | BD41: 0.64638493 | BE41: 31.652495 | BF41: 37.568 | BG41: 181.401 | BH41: 17.534 | BI41: 140.73483 | BJ41: 7.1494893 | BK41: 13.889837 | BL41: 12.248854 | BM41: 72.062012 | BN41: 0.37247278 | BO41: 0.090342679 | BP41: 0.0125115 | BQ41: 0.0068909 | BR41: 12.069753 | BS41: 6.7492506 | BT41: 0.04436705 | BU41: 58.391279 | BV41: 15.609517 | BW41: 28.087004 | BX41: 12.724274 | BY41: 66.781626 | BZ41: 32.107301 | CA41: 59.769783 | CB41: 0.0215484 | CC41: 0.41317445 | CD41: 29.927411 | CE41: 27.164931 | CF41: 8.4161442 | CG41: 0.091 | CH41: 0.32758702 | CI41: 1.8395898 | CJ41: 225.86075 | CK41: 1.12 | CL41: 29.79 | CM41: 8.1759547 | CN41: 4.0879774 | CO41: 2.0439887 | CP41: 597.86669
A42: Florencia | B42: 2020 | C42: 158.35892 | D42: 56.255 | E42: 0.16558006 | F42: 0.022 | G42: 34.085079 | H42: 61.96 | I42: 0.099370739 | J42: 24.595348 | K42: 1000.2108 | L42: 35.721815 | M42: 0.55617468 | N42: 572.275 | O42: 0.26794258 | P42: 74.686722 | Q42: 0.90129837 | R42: 92.189937 | S42: 462.25847 | T42: 74.686722 | U42: 620.48533 | V42: 503.40729 | W42: 129321 | X42: 0.12 | Y42: 12.130726 | Z42: 644.281 | AA42: 5.7799793 | AB42: 5.7799793 | AC42: 12.62 | AD42: 9.2775116 | AE42: 32.606844 | AF42: 67.634542 | AG42: 5017.104 | AH42: 306.067 | AI42: 1.8889 | AJ42: 67122.495 | AK42: 59.578653 | AL42: 7.9854809 | AM42: 28.413185 | AN42: 0.95460317 | AO42: 0.8816 | AP42: 85.520362 | AQ42: 7.5164422 | AR42: 93.370682 | AS42: 33.80591 | AT42: 9.6764186 | AU42: 3.4716922 | AV42: 289.87374 | AW42: 0.6835 | AX42: 0.9618 | AY42: 0.7868 | AZ42: 0.4053 | BA42: 0.0354 | BB42: 260 | BC42: 255.74196 | BD42: 0.74040067 | BE42: 28.786311 | BF42: 55.87 | BG42: 245.922 | BH42: 8.547 | BI42: 136.21917 | BJ42: 4.6767538 | BK42: 0.59397163 | BL42: 9.4233474 | BM42: 0 | BN42: 0.36120401 | BO42: 0.11904762 | BP42: 0.0399122 | BQ42: 0.0359186 | BR42: 8.3741304 | BS42: 5.2294395 | BT42: 0.033594625 | BU42: 58.608228 | BV42: 14.407338 | BW42: 42.518319 | BX42: 6.9121874 | BY42: 40.938637 | BZ42: 61.209598 | CA42: 83.205563 | CB42: 0.011956269 | CC42: 0.014191574 | CD42: 28.291404 | CE42: 18.663076 | CF42: 0.054478702 | CG42: 0.508 | CH42: 0.50755066 | CI42: 1.171207 | CJ42: 234.24141 | CK42: 1.4 | CL42: 15.16 | CM42: 5.8560352 | CN42: 0 | CO42: 0 | CP42: 158.11295
A43: Ibagué | B43: 2020 | C43: 149.17364 | D43: 69.86125 | E43: 0.24912574 | F43: 0.021 | G43: 51.603562 | H43: 45.35 | I43: 0.56433555 | J43: 13.80373 | K43: 955.44193 | L43: 20.332521 | M43: 0.49429594 | N43: 412.83178 | O43: 0.80057448 | P43: 51.774626 | Q43: 0.97062832 | R43: 98.678975 | S43: 393.82901 | T43: 51.452263 | U43: 212.75907 | V43: 253.01384 | W43: 139838 | X43: 0.2304 | Y43: 18.81343 | Z43: 927.14429 | AA43: 11.088503 | AB43: 18.480838 | AC43: 21.43 | AD43: 18.689942 | AE43: 43.924345 | AF43: 78.468172 | AG43: 9092.833 | AH43: 1675.942 | AI43: 1.8571 | AJ43: 59721.499 | AK43: 52.802332 | AL43: 3.8112523 | AM43: 29.113827 | AN43: 0.99155168 | AO43: 0.9213 | AP43: 92.563993 | AQ43: 8.2426128 | AR43: 139.59981 | AS43: 45.801995 | AT43: 14.026674 | AU43: 6.2382378 | AV43: 194.93105 | AW43: 0.8405 | AX43: 1 | AY43: 0.9077 | AZ43: 0.5296 | BA43: 0.0321 | BB43: 265 | BC43: 258.66043 | BD43: 0.53666557 | BE43: 26.786583 | BF43: 49.52 | BG43: 263.389 | BH43: 33.419 | BI43: 143.35458 | BJ43: 12.632275 | BK43: 47.678254 | BL43: 17.826564 | BM43: 47.722543 | BN43: 0.43084857 | BO43: 0.28032345 | BP43: 0.0164071 | BQ43: 0.49150035 | BR43: 14.270072 | BS43: 9.4965929 | BT43: 0.0037320762 | BU43: 64.113865 | BV43: 16.189152 | BW43: 49.636459 | BX43: 9.9298845 | BY43: 37.680777 | BZ43: 55.889993 | CA43: 97.737656 | CB43: 0.023090048 | CC43: 0.59841089 | CD43: 29.741245 | CE43: 25.591596 | CF43: 2.4227233 | CG43: 0.254 | CH43: 0.36758827 | CI43: 2.6115164 | CJ43: 380.53525 | CK43: 1.64 | CL43: 24.9 | CM43: 5.5961066 | CN43: 1.8653689 | CO43: 37.307377 | CP43: 871.12726
A44: Inírida | B44: 2020 | C44: 118.06777 | D44: 39.751429 | E44: 0.10552138 | F44: 0.018 | G44: 52.257973 | H44: 37.79 | I44: 0.0011648224 | J44: 9.1818933 | K44: 468.27656 | L44: 24.485049 | M44: 0 | N44: 325.5 | O44: 0.6 | P44: 15.921505 | Q44: n/a | R44: 70.18638 | S44: 557.19037 | T44: 11.468447 | U44: - | V44: - | W44: 49999 | X44: 0.0048 | Y44: N/A | Z44: 2143.666 | AA44: 29.688567 | AB44: 0 | AC44: 3.87 | AD44: 1.235364 | AE44: 22.482312 | AF44: 49.375557 | AG44: 5369.318 | AH44: 426.136 | AI44: 1.8 | AJ44: 71352.27 | AK44: 36.348825 | AL44: 3.4482759 | AM44: 31.354344 | AN44: 1 | AO44: 1 | AP44: 34.660767 | AQ44: 24.07932 | AR44: 518.80674 | AS44: 51.745396 | AT44: 13.13848 | AU44: 3.2340873 | AV44: 119.36461 | AW44: 0.5086 | AX44: 0.7324 | AY44: 0.4053 | AZ44: 0.1213 | BA44: 0.0535 | BB44: 247 | BC44: 247.20513 | BD44: 0.19072165 | BE44: 31.136598 | BF44: 3.714 | BG44: 47.598 | BH44: 10.64 | BI44: 136.30952 | BJ44: 0 | BK44: 0 | BL44: 0 | BM44: 0 | BN44: 0.38636364 | BO44: 0 | BP44: 0.2132241 | BQ44: 0.0284747 | BR44: 6.1212622 | BS44: 3.0912374 | BT44: 0.0099009901 | BU44: 54.529502 | BV44: 13.509882 | BW44: 36.04672 | BX44: 3.8505747 | BY44: 59.719245 | BZ44: 24.413544 | CA44: 88.764462 | CB44: 0 | CC44: 0.088866438 | CD44: 26.333224 | CE44: 18.048396 | CF44: 0.061376671 | CG44: 1 | CH44: 1 | CI44: 0 | CJ44: 0 | CK44: 0 | CL44: 0 | CM44: 0 | CN44: 0 | CO44: 0 | CP44: 91.818933
A45: Leticia | B45: 2020 | C45: 108.23377 | D45: 16.915714 | E45: 0.28798946 | F45: 0.024 | G45: 43.617013 | H45: 88.37 | I45: 0 | J45: 14.309661 | K45: 560.12102 | L45: 12.265424 | M45: 0.53962818 | N45: 254.77778 | O45: 0.3 | P45: 80.046264 | Q45: n/a | R45: 84.71246 | S45: 519.05189 | T45: 80.046264 | U45: - | V45: - | W45: 302957 | X45: 0.2268 | Y45: N/A | Z45: 1032.9531 | AA45: 39.130164 | AB45: 0 | AC45: 2.45 | AD45: 2.0031022 | AE45: 16.252225 | AF45: 44.746427 | AG45: 734.341 | AH45: 64.795 | AI45: 0.5455 | AJ45: 53791.953 | AK45: 13.49192 | AL45: 8.7114338 | AM45: 32.537543 | AN45: 0.90643275 | AO45: 0.8368 | AP45: 55.811623 | AQ45: 12.484395 | AR45: 232.28804 | AS45: 62.377014 | AT45: 12.604015 | AU45: 4.1155968 | AV45: 288.23746 | AW45: 0.6284 | AX45: 0.9188 | AY45: 0.7903 | AZ45: 0.4234 | BA45: 0.0496 | BB45: 223 | BC45: 218.93321 | BD45: 0.17716535 | BE45: 26.849081 | BF45: 7.097 | BG45: 186.939 | BH45: 7.119 | BI45: 134.62613 | BJ45: 52.631579 | BK45: 16.787265 | BL45: 10.810811 | BM45: 0 | BN45: 0.43298969 | BO45: 0.10638298 | BP45: 0.1589874 | BQ45: 0.018875 | BR45: 9.4034916 | BS45: 5.8056339 | BT45: 0.031690141 | BU45: 62.769374 | BV45: 6.7018608 | BW45: 33.995625 | BX45: 4.796422 | BY45: 63.496341 | BZ45: 19.303023 | CA45: 70.514632 | CB45: 0.0023012869 | CC45: 0.31234203 | CD45: 27.020017 | CE45: 0 | CF45: 0.78531145 | CG45: 1 | CH45: 1 | CI45: 8.1769492 | CJ45: 429.28983 | CK45: 1.22 | CL45: 63.64 | CM45: 0 | CN45: 0 | CO45: 0 | CP45: 388.40509
A46: Manizales AM | B46: 2020 | C46: 175.90855 | D46: 57.076482 | E46: 0.29115533 | F46: 0.022 | G46: 59.403945 | H46: 42.842381 | I46: 0.087453001 | J46: 11.444424 | K46: 483.62559 | L46: 10.457836 | M46: 0.63699011 | N46: 443.94253 | O46: 0.42790025 | P46: 96.610203 | Q46: 0.69101709 | R46: 99.801879 | S46: 424.7323 | T46: 94.567093 | U46: 230.96117 | V46: 177.19453 | W46: 241602 | X46: 0.126 | Y46: 16.09015 | Z46: 1049.0394 | AA46: 9.735411 | AB46: 27.259151 | AC46: 19.10211 | AD46: 14.139951 | AE46: 49.998966 | AF46: 77.125178 | AG46: 11529.37 | AH46: 2113.347 | AI46: 2.6875 | AJ46: 87426.13 | AK46: 39.674377 | AL46: 2.3593466 | AM46: 31.642355 | AN46: 0.85844952 | AO46: 0.85104641 | AP46: 95.523808 | AQ46: 11.325028 | AR46: 28.24061 | AS46: 59.315075 | AT46: 20.320446 | AU46: 10.958562 | AV46: 318.47071 | AW46: 0.6475206 | AX46: 0.78223311 | AY46: 0.7589456 | AZ46: 0.4589712 | BA46: 0.023696413 | BB46: 273.19805 | BC46: 262.73574 | BD46: 0.66448363 | BE46: 22.701763 | BF46: 76.557 | BG46: 766.799 | BH46: 27.129 | BI46: 147.45522 | BJ46: 18.299965 | BK46: 68.491137 | BL46: 28.368164 | BM46: 38.730057 | BN46: 0.52691066 | BO46: 0.089068826 | BP46: 0.0616892 | BQ46: 0.0564867 | BR46: 10.457836 | BS46: 9.6113434 | BT46: 0.055635393 | BU46: 57.982978 | BV46: 12.03984 | BW46: 64.632196 | BX46: 5.8722439 | BY46: 30.220542 | BZ46: 28.317101 | CA46: 88.185824 | CB46: 0.042325436 | CC46: 0.57412071 | CD46: 29.648695 | CE46: 27.895658 | CF46: 25.100907 | CG46: 0.126 | CH46: 0.36974319 | CI46: 14.404189 | CJ46: 964.88338 | CK46: 0.97 | CL46: 22.49 | CM46: 39.463533 | CN46: 15.785413 | CO46: 9.8658832 | CP46: 1470.0166
A47: Medellín AM | B47: 2020 | C47: 229.7946 | D47: 72.962923 | E47: 0.38312027 | F47: 0.028 | G47: 65.516132 | H47: 66.458912 | I47: 0.032156884 | J47: 22.120204 | K47: 1158.9173 | L47: 22.87602 | M47: 0.62136997 | N47: 634.08738 | O47: 0.46881633 | P47: 95.567633 | Q47: 0.80082054 | R47: 99.770068 | S47: 428.75324 | T47: 93.115601 | U47: 421.2142 | V47: 333.44059 | W47: 9941050 | X47: 0.5424 | Y47: 30.529313 | Z47: 2455.3124 | AA47: 7.6443249 | AB47: 13.06933 | AC47: 24.67411 | AD47: 17.950821 | AE47: 50.082136 | AF47: 77.57069 | AG47: 9080.978 | AH47: 1179.549 | AI47: 2.3924 | AJ47: 26807.442 | AK47: 51.485873 | AL47: 1.9963702 | AM47: 31.171347 | AN47: 0.96709413 | AO47: 0.93849512 | AP47: 92.717314 | AQ47: 7.0096383 | AR47: 55.013753 | AS47: 67.22384 | AT47: 25.058754 | AU47: 12.787384 | AV47: 146.25032 | AW47: 0.74561991 | AX47: 0.92773785 | AY47: 0.868077 | AZ47: 0.48859919 | BA47: 0.038649625 | BB47: 265.22349 | BC47: 256.31555 | BD47: 0.54118801 | BE47: 29.689339 | BF47: 59.973 | BG47: 330.219 | BH47: 29.65 | BI47: 148.77666 | BJ47: 12.281414 | BK47: 39.074414 | BL47: 35.381185 | BM47: 57.766698 | BN47: 0.62269667 | BO47: 0.13841084 | BP47: 0.0076057 | BQ47: 0.0344897 | BR47: 18.094226 | BS47: 14.604121 | BT47: 0.058102024 | BU47: 63.9467 | BV47: 12.073341 | BW47: 60.323509 | BX47: 9.077269 | BY47: 29.670924 | BZ47: 34.919393 | CA47: 107.9718 | CB47: 0.075281886 | CC47: 0.93164994 | CD47: 32.104961 | CE47: 29.82 | CF47: 27.862752 | CG47: 0.103 | CH47: 0.10469787 | CI47: 8.2635841 | CJ47: 716.26127 | CK47: 1.28 | CL47: 19.54 | CM47: 38.798535 | CN47: 10.581419 | CO47: 55.426479 | CP47: 3409.7362
A48: Mitú | B48: 2020 | C48: 76.92257 | D48: 16.388333 | E48: 0.16699694 | F48: 0.014 | G48: 43.356407 | H48: 73.26 | I48: 0.00068073519 | J48: 9.5840521 | K48: 146.95547 | L48: 3.194684 | M48: 0.66251416 | N48: 178 | O48: 0 | P48: 100 | Q48: n/a | R48: 49.340086 | S48: 581.07439 | T48: 100 | U48: - | V48: - | W48: 30736 | X48: 0.0232 | Y48: N/A | Z48: 3990.1604 | AA48: 0 | AB48: 0 | AC48: 0.22 | AD48: 4.2728899 | AE48: 30.926321 | AF48: 43.633623 | AG48: 28.719 | AH48: 0 | AI48: 0.25 | AJ48: 65181.287 | AK48: 11.944389 | AL48: 3.4482759 | AM48: 26.25243 | AN48: 0.89130435 | AO48: 0.8441 | AP48: 35.841584 | AQ48: 17.699115 | AR48: 0 | AS48: 27.855153 | AT48: 3.5111538 | AU48: 0.70223075 | AV48: 63.893681 | AW48: 0.2353 | AX48: 0.558 | AY48: 0.3413 | AZ48: 0.152 | BA48: 0.0207 | BB48: 215 | BC48: 215.85782 | BD48: 0.17647059 | BE48: 26.894118 | BF48: 1.195 | BG48: 3.35 | BH48: 4.133 | BI48: 130.51471 | BJ48: 0 | BK48: 15.853659 | BL48: 2.9411765 | BM48: 0 | BN48: 0.375 | BO48: 0.038461538 | BP48: 0.36829102 | BQ48: 0.062254 | BR48: 3.194684 | BS48: 1.6612357 | BT48: 0 | BU48: 52.16325 | BV48: 10.925504 | BW48: 47.228063 | BX48: 4.5721543 | BY48: 49.174733 | BZ48: 17.47077 | CA48: 34.914662 | CB48: 0.021418557 | CC48: 0.031061934 | CD48: 26.095726 | CE48: 20.330969 | CF48: 0.32520412 | CG48: 0.214 | CH48: 0.15710277 | CI48: 0 | CJ48: 0 | CK48: 0 | CL48: 0 | CM48: 0 | CN48: 0 | CO48: 0 | CP48: 0
A49: Mocoa | B49: 2020 | C49: 130.03866 | D49: 10.282857 | E49: 0.17687399 | F49: 0.014 | G49: 40.044127 | H49: 37.82 | I49: 0.44848036 | J49: 13.860974 | K49: 608.15025 | L49: 29.454571 | M49: 0.58437681 | N49: 304.21739 | O49: 0.54042553 | P49: 49.05938 | Q49: 0.69536314 | R49: 87.902486 | S49: 491.4669 | T49: 45.086705 | U49: 440.65615 | V49: 402.47708 | W49: 30712 | X49: 0 | Y49: N/A | Z49: 1709.2314 | AA49: 0 | AB49: 0 | AC49: 5.85 | AD49: 6.339925 | AE49: 32.153429 | AF49: 60.587651 | AG49: 3773.585 | AH49: 792.453 | AI49: 0.3333 | AJ49: 40156.857 | AK49: 6.8907231 | AL49: 4.7186933 | AM49: 36.059756 | AN49: 0.98763906 | AO49: 1 | AP49: 83.823529 | AQ49: 7.585335 | AR49: 0 | AS49: 35.560933 | AT49: 8.7347601 | AU49: 3.194265 | AV49: 173.26218 | AW49: 0.5589 | AX49: 0.8257 | AY49: 0.8275 | AZ49: 0.4254 | BA49: 0.0387 | BB49: 266 | BC49: 265.68657 | BD49: 0.54941278 | BE49: 21.939559 | BF49: 10.543 | BG49: 193.269 | BH49: 18.513 | BI49: 132.20128 | BJ49: 0 | BK49: 2.6841448 | BL49: 3.2786885 | BM49: 0 | BN49: 0.37139272 | BO49: 0.044444444 | BP49: 0.0701256 | BQ49: 0.0335703 | BR49: 10.395731 | BS49: 6.8438561 | BT49: 0.020253165 | BU49: 60.501241 | BV49: 15.908315 | BW49: 44.694329 | BX49: 5.4119231 | BY49: 43.863563 | BZ49: 26.131545 | CA49: 125.90474 | CB49: 0.017591012 | CC49: 0.35196762 | CD49: 27.241265 | CE49: 27.098477 | CF49: 87.362619 | CG49: 0.628 | CH49: 0.99995561 | CI49: 0 | CJ49: 0 | CK49: 0 | CL49: 0 | CM49: 0 | CN49: 0 | CO49: 0 | CP49: 190.5884
A50: Montería | B50: 2020 | C50: 153.69705 | D50: 53.695714 | E50: 0.16979665 | F50: 0.029 | G50: 55.887587 | H50: 40.405 | I50: 0.30917052 | J50: 18.241664 | K50: 447.62237 | L50: 16.437543 | M50: 0.58503089 | N50: 514.81034 | O50: 0.43959553 | P50: 85.818141 | Q50: 0.97238054 | R50: 98.437115 | S50: 381.97202 | T50: 45.057205 | U50: 319.26322 | V50: 302.25938 | W50: 1029318 | X50: 0.247 | Y50: 13.950617 | Z50: 326.46565 | AA50: 0 | AB50: 0 | AC50: 11.56 | AD50: 16.530816 | AE50: 28.751742 | AF50: 61.656988 | AG50: 6621.948 | AH50: 940.024 | AI50: 1.45 | AJ50: 122926.03 | AK50: 36.768132 | AL50: 1.814882 | AM50: 27.104076 | AN50: 0.91385812 | AO50: 0.8614 | AP50: 87.48019 | AQ50: 18.352258 | AR50: 66.006601 | AS50: 26.227039 | AT50: 11.83894 | AU50: 4.5342973 | AV50: 483.70478 | AW50: 0.6163 | AX50: 0.9508 | AY50: 0.8272 | AZ50: 0.4879 | BA50: 0.0306 | BB50: 263.45934 | BC50: 252.56307 | BD50: 0.40755778 | BE50: 27.135853 | BF50: 66.27 | BG50: 234.858 | BH50: 9.725 | BI50: 138.35914 | BJ50: 8.3713851 | BK50: 70.11864 | BL50: 16.502385 | BM50: 60.864064 | BN50: 0.32232497 | BO50: 0.063636364 | BP50: 0.1092625 | BQ50: 0.1315077 | BR50: 9.4816561 | BS50: 6.9017636 | BT50: 0.062155097 | BU50: 63.205118 | BV50: 13.045928 | BW50: 35.700014 | BX50: 7.3445149 | BY50: 44.832673 | BZ50: 28.26847 | CA50: 66.245501 | CB50: 0.020516664 | CC50: 0.647852 | CD50: 29.222194 | CE50: 27.132665 | CF50: 13.691349 | CG50: 0.364 | CH50: 0.65235325 | CI50: 4.4100726 | CJ50: 441.00726 | CK50: 1.57 | CL50: 26.23 | CM50: 2.0045785 | CN50: 0 | CO50: 0 | CP50: 290.66388
A51: Neiva | B51: 2020 | C51: 151.39388 | D51: 58.66125 | E51: 0.25281654 | F51: 0.023 | G51: 48.059621 | H51: 95.93 | I51: 0.2404943 | J51: 18.280067 | K51: 1144.166 | L51: 16.618243 | M51: 0.55948776 | N51: 559.83117 | O51: 0.51505547 | P51: 94.752798 | Q51: 0.8964422 | R51: 99.034718 | S51: 400.09727 | T51: 94.752798 | U51: 218.69674 | V51: 182.61167 | W51: 297393 | X51: 0.2388 | Y51: 12.371121 | Z51: 744.3034 | AA51: 19.209238 | AB51: 10.976707 | AC51: 21.47 | AD51: 13.017852 | AE51: 41.140235 | AF51: 75.008927 | AG51: 8129.973 | AH51: 1307.08 | AI51: 1.1538 | AJ51: 77886.351 | AK51: 53.853321 | AL51: 1.814882 | AM51: 30.834356 | AN51: 0.87365314 | AO51: 0.8175 | AP51: 95.61653 | AQ51: 6.864564 | AR51: 18.528812 | AS51: 46.796133 | AT51: 22.485169 | AU51: 9.9834149 | AV51: 341.50489 | AW51: 0.7391 | AX51: 0.936 | AY51: 0.804 | AZ51: 0.4697 | BA51: 0.0509 | BB51: 275 | BC51: 265.52419 | BD51: 0.63950276 | BE51: 27.146869 | BF51: 68.818 | BG51: 227.761 | BH51: 16.931 | BI51: 138.21437 | BJ51: 36.134454 | BK51: 48.848628 | BL51: 13.021992 | BM51: 0 | BN51: 0.38631791 | BO51: 0.10659898 | BP51: 0.0190888 | BQ51: 0.0262272 | BR51: 12.96223 | BS51: 11.040053 | BT51: 0.010536879 | BU51: 63.191891 | BV51: 11.021271 | BW51: 44.226266 | BX51: 10.020207 | BY51: 50.88426 | BZ51: 61.013804 | CA51: 147.15044 | CB51: 0.032899825 | CC51: 0.6313906 | CD51: 29.396783 | CE51: 27.026484 | CF51: 9.7756989 | CG51: 0.209 | CH51: 0.73459678 | CI51: 3.3236486 | CJ51: 310.2072 | CK51: 1.61 | CL51: 16.29 | CM51: 27.697072 | CN51: 0 | CO51: 0 | CP51: 645.34177
A52: Pasto | B52: 2020 | C52: 162.61266 | D52: 42.69375 | E52: 0.21290673 | F52: 0.025 | G52: 61.372122 | H52: 45.93 | I52: 0.17287671 | J52: 13.494658 | K52: 1449.53 | L52: 19.350831 | M52: 0.56843098 | N52: 420.44304 | O52: 0.51299968 | P52: 57.331301 | Q52: 0.27933643 | R52: 98.593436 | S52: 454.42255 | T52: 55.338916 | U52: 295.25166 | V52: 237.1617 | W52: 326092 | X52: 0.2316 | Y52: 13.285728 | Z52: 458.51284 | AA52: 33.113511 | AB52: 15.283159 | AC52: 19.96 | AD52: 14.86693 | AE52: 42.78149 | AF52: 72.128252 | AG52: 8620.962 | AH52: 1130.514 | AI52: 1.1852 | AJ52: 48723.681 | AK52: 30.859835 | AL52: 2.1778584 | AM52: 28.330555 | AN52: 0.96921255 | AO52: 0.9101 | AP52: 91.91192 | AQ52: 10.119595 | AR52: 92.123445 | AS52: 49.773447 | AT52: 15.224241 | AU52: 5.5187875 | AV52: 444.81449 | AW52: 0.8625 | AX52: 0.988 | AY52: 0.9935 | AZ52: 0.5814 | BA52: 0.0157 | BB52: 280.31664 | BC52: 273.41802 | BD52: 0.7454844 | BE52: 23.116995 | BF52: 96.958 | BG52: 304.634 | BH52: 11.667 | BI52: 145.96178 | BJ52: 7.0530099 | BK52: 33.601312 | BL52: 15.769231 | BM52: 36.032822 | BN52: 0.37359098 | BO52: 0.19285714 | BP52: 0.0157584 | BQ52: 0.5792709 | BR52: 10.795727 | BS52: 6.9688452 | BT52: 0.016075996 | BU52: 65.382041 | BV52: 9.4942601 | BW52: 40.69805 | BX52: 12.061905 | BY52: 42.760454 | BZ52: 41.212659 | CA52: 99.798906 | CB52: 0.027950925 | CC52: 0.53733447 | CD52: 29.351651 | CE52: 25.576098 | CF52: 7.29197 | CG52: 0.178 | CH52: 0.23755982 | CI52: 2.0369295 | CJ52: 593.25573 | CK52: 0.66 | CL52: 19.16 | CM52: 0 | CN52: 0 | CO52: 0 | CP52: 381.92429
A53: Pereira AM | B53: 2020 | C53: 204.0665 | D53: 68.687031 | E53: 0.3377812 | F53: 0.03 | G53: 54.851811 | H53: 96.378402 | I53: 0.25860324 | J53: 23.297966 | K53: 607.82728 | L53: 17.889509 | M53: 0.62322465 | N53: 577.82418 | O53: 0.64375436 | P53: 61.13564 | Q53: 0.82979221 | R53: 99.768854 | S53: 399.88345 | T53: 56.387065 | U53: 393.33355 | V53: 307.27091 | W53: 1818632 | X53: 0.268 | Y53: 25.514888 | Z53: 1098.2356 | AA53: 6.8606869 | AB53: 21.954198 | AC53: 22.652462 | AD53: 14.942126 | AE53: 51.421193 | AF53: 84.527515 | AG53: 13598.171 | AH53: 2159.631 | AI53: 1.4706 | AJ53: 55847.789 | AK53: 49.307349 | AL53: 4.9001815 | AM53: 31.038908 | AN53: 0.97577683 | AO53: 0.92964017 | AP53: 92.147932 | AQ53: 6.3614991 | AR53: 27.597627 | AS53: 60.818195 | AT53: 25.574508 | AU53: 11.873879 | AV53: 203.02513 | AW53: 0.73476657 | AX53: 0.99811933 | AY53: 0.91081499 | AZ53: 0.52440445 | BA53: 0.052189503 | BB53: 266.18296 | BC53: 259.45425 | BD53: 0.49303182 | BE53: 27.213253 | BF53: 79.923 | BG53: 305.21 | BH53: 25.927 | BI53: 143.23181 | BJ53: 8.879668 | BK53: 48.382947 | BL53: 25.92668 | BM53: 17.619362 | BN53: 0.58693878 | BO53: 0.082932692 | BP53: 0.0262021 | BQ53: 0.0434395 | BR53: 10.539556 | BS53: 9.667269 | BT53: 0.06670492 | BU53: 61.449487 | BV53: 8.1042382 | BW53: 51.158139 | BX53: 7.3765018 | BY53: 36.470903 | BZ53: 26.379325 | CA53: 93.441952 | CB53: 0.041327521 | CC53: 0.52368642 | CD53: 30.082692 | CE53: 27.61619 | CF53: 19.674543 | CG53: 0.116 | CH53: 0.25682327 | CI53: 7.2112751 | CJ53: 439.61042 | CK53: 1.32 | CL53: 30.19 | CM53: 33.282808 | CN53: 15.25462 | CO53: 26.34889 | CP53: 1428.3872
A54: Popayán | B54: 2020 | C54: 150.73679 | D54: 28.315 | E54: 0.25467791 | F54: 0.021 | G54: 58.065024 | H54: 51.285 | I54: 0.29664651 | J54: 18.944629 | K54: 1773.0309 | L54: 42.547773 | M54: 0.47361292 | N54: 416.52703 | O54: 0.46525424 | P54: 89.829511 | Q54: 0.81696445 | R54: 98.049454 | S54: 375.66028 | T54: 89.829511 | U54: 354.93962 | V54: 354.00757 | W54: 119624 | X54: 0.128 | Y54: 14.11273 | Z54: 538.4312 | AA54: 18.434482 | AB54: 92.172412 | AC54: 17.97 | AD54: 14.600811 | AE54: 44.266117 | AF54: 73.673502 | AG54: 19013.287 | AH54: 1826.967 | AI54: 1.7143 | AJ54: 47015.21 | AK54: 45.761315 | AL54: 3.8112523 | AM54: 28.117544 | AN54: 0.96630759 | AO54: 0.9419 | AP54: 91.223909 | AQ54: 5.9709242 | AR54: 0 | AS54: 36.654318 | AT54: 12.229379 | AU54: 5.0662639 | AV54: 403.42742 | AW54: 0.7469 | AX54: 1 | AY54: 0.9068 | AZ54: 0.5576 | BA54: 0.0237 | BB54: 272.24484 | BC54: 265.90487 | BD54: 0.67995019 | BE54: 27.283935 | BF54: 99.441 | BG54: 353.394 | BH54: 49.331 | BI54: 144.77978 | BJ54: 8.8003321 | BK54: 36.710697 | BL54: 16.229508 | BM54: 13.629432 | BN54: 0.38963804 | BO54: 0.10055866 | BP54: 0.0279216 | BQ54: 0.0421175 | BR54: 7.8884192 | BS54: 6.1647686 | BT54: 0.04231738 | BU54: 59.586989 | BV54: 12.679398 | BW54: 41.641622 | BX54: 10.424428 | BY54: 50.129372 | BZ54: 49.549107 | CA54: 105.24705 | CB54: 0.033783761 | CC54: 0.41413479 | CD54: 29.121683 | CE54: 26.035785 | CF54: 10.582535 | CG54: 0.117 | CH54: 0.23062438 | CI54: 7.4536245 | CJ54: 698.7773 | CK54: 2.23 | CL54: 20.85 | CM54: 31.056769 | CN54: 0 | CO54: 0 | CP54: 521.75371
A55: Puerto Carreño | B55: 2020 | C55: 122.7468 | D55: 24.574286 | E55: 0.19139718 | F55: 0.024 | G55: 42.354909 | H55: 71.79 | I55: 0.0056959772 | J55: 73.263651 | K55: 903.58503 | L55: 78.147895 | M55: 0.62255407 | N55: 272 | O55: 0.28571429 | P55: 61.333786 | Q55: n/a | R55: 39.252178 | S55: 622.30238 | T55: 0 | U55: 184.3443 | V55: 184.87616 | W55: 47919 | X55: 0.0056 | Y55: N/A | Z55: 2367.3928 | AA55: 0 | AB55: 0 | AC55: 5.33 | AD55: 1.199737 | AE55: 23.427662 | AF55: 52.970145 | AG55: 1871.921 | AH55: 344.828 | AI55: 1.2 | AJ55: 77761.886 | AK55: 31.174866 | AL55: 0 | AM55: 28.200001 | AN55: 1 | AO55: 1 | AP55: 55.723542 | AQ55: 26.809651 | AR55: 263.15789 | AS55: 61.754627 | AT55: 9.40334 | AU55: 4.1591696 | AV55: 170.94852 | AW55: 0.6905 | AX55: 1 | AY55: 0.6912 | AZ55: 0.2602 | BA55: 0.0717 | BB55: 240 | BC55: 239.55758 | BD55: 0.23913043 | BE55: 31.302795 | BF55: 4.446 | BG55: 210.164 | BH55: 23.231 | BI55: 130.38384 | BJ55: 0 | BK55: 0 | BL55: 9.0909091 | BM55: 0 | BN55: 0.46296296 | BO55: 0.014388489 | BP55: 0.2314768 | BQ55: 0.0349768 | BR55: 15.629579 | BS55: 6.0564619 | BT55: 0.024193548 | BU55: 66.759554 | BV55: 21.118348 | BW55: 34.228222 | BX55: 11.739065 | BY55: 46.738299 | BZ55: 40.273556 | CA55: 86.770517 | CB55: 0.019869875 | CC55: 0.50290879 | CD55: 25.582621 | CE55: 12.081428 | CF55: 0.22615158 | CG55: 1 | CH55: 0.99990614 | CI55: 0 | CJ55: 48.842434 | CK55: 0 | CL55: 0 | CM55: 0 | CN55: 0 | CO55: 0 | CP55: 0
A56: Quibdó | B56: 2020 | C56: 118.71515 | D56: 52.468571 | E56: 0.091798719 | F56: 0.016 | G56: 65.626345 | H56: 25 | I56: 0.44373866 | J56: 71.515357 | K56: 1037.3572 | L56: 66.13248 | M56: 0.49687038 | N56: 312.58824 | O56: 0.51179673 | P56: 43.688484 | Q56: 0.12944822 | R56: 95.862765 | S56: 518.37212 | T56: 16.743591 | U56: 572.79412 | V56: 494.51048 | W56: 345882 | X56: 0.1126 | Y56: 20.320288 | Z56: 332.73865 | AA56: 7.643799 | AB56: 38.218995 | AC56: 13.05 | AD56: 6.6516146 | AE56: 25.807755 | AF56: 61.449661 | AG56: 5398.395 | AH56: 543.082 | AI56: 0.8462 | AJ56: 75067.205 | AK56: 11.383675 | AL56: 9.2558984 | AM56: 30.886301 | AN56: 0.95828604 | AO56: 0.9154 | AP56: 76.920665 | AQ56: 23.352794 | AR56: 225.80645 | AS56: 25.280914 | AT56: 5.648849 | AU56: 2.3336229 | AV56: 266.83687 | AW56: 0.7641 | AX56: 1 | AY56: 0.8129 | AZ56: 0.405 | BA56: 0.0181 | BB56: 220 | BC56: 222.12317 | BD56: 0.59453782 | BE56: 23.953782 | BF56: 95.167 | BG56: 249.155 | BH56: 7.181 | BI56: 121.71463 | BJ56: 2.6708562 | BK56: 1.012443 | BL56: 3.5071942 | BM56: 0 | BN56: 0.25272727 | BO56: 0 | BP56: 0.0569312 | BQ56: 0.0418191 | BR56: 10.381261 | BS56: 8.135833 | BT56: 0.017013233 | BU56: 52.624826 | BV56: 16.30411 | BW56: 41.721715 | BX56: 4.469608 | BY56: 49.439421 | BZ56: 43.236718 | CA56: 92.716276 | CB56: 0.007771124 | CC56: 0.33072654 | CD56: 27.960501 | CE56: 25.16331 | CF56: 6.2410525 | CG56: 0.465 | CH56: 0.92401698 | CI56: 1.5379647 | CJ56: 276.83364 | CK56: 0 | CL56: 33.33 | CM56: 0 | CN56: 0 | CO56: 0 | CP56: 276.83364
A57: Riohacha | B57: 2020 | C57: 103.29743 | D57: 38.6925 | E57: 0.068901245 | F57: 0.012 | G57: 46.362904 | H57: 53.55 | I57: 0.21068702 | J57: 33.206128 | K57: 767.82786 | L57: 22.988858 | M57: 0.43936034 | N57: 188.82857 | O57: 0.49337748 | P57: 86.087553 | Q57: 0.84372739 | R57: 65.518797 | S57: 414.46141 | T57: 90.001444 | U57: 271.53966 | V57: 261.27771 | W57: 258693 | X57: 0.2196 | Y57: N/A | Z57: 1045.6865 | AA57: 0 | AB57: 14.863332 | AC57: 10.97 | AD57: 12.219702 | AE57: 21.274722 | AF57: 63.880453 | AG57: 4632.655 | AH57: 490.144 | AI57: 1.5 | AJ57: 99720.75 | AK57: 28.549156 | AL57: 1.9963702 | AM57: 30.770971 | AN57: 0.94490501 | AO57: 0.8285 | AP57: 67.214655 | AQ57: 22.916313 | AR57: 183.36389 | AS57: 29.573933 | AT57: 10.695349 | AU57: 3.6765261 | AV57: 240.10585 | AW57: 0.8572 | AX57: 1 | AY57: 0.8121 | AZ57: 0.3572 | BA57: 0.0299 | BB57: 240 | BC57: 232.30077 | BD57: 0.20585162 | BE57: 26.343783 | BF57: 54.545 | BG57: 82.973 | BH57: 14.477 | BI57: 132.91972 | BJ57: 8.4158416 | BK57: 4.522003 | BL57: 5.8723404 | BM57: 13.459399 | BN57: 0.32056194 | BO57: 0.047337278 | BP57: 0.0586722 | BQ57: 0.0248476 | BR57: 10.166184 | BS57: 5.3180892 | BT57: 0.02209414 | BU57: 64.51174 | BV57: 11.219053 | BW57: 32.098455 | BX57: 16.598406 | BY57: 60.781344 | BZ57: 27.697065 | CA57: 74.026779 | CB57: 0.016507084 | CC57: 0.26692299 | CD57: 28.388421 | CE57: 28.045187 | CF57: 89.544523 | CG57: 0.172 | CH57: 0.98590509 | CI57: 6.1303622 | CJ57: 577.27577 | CK57: 1.67 | CL57: 13.64 | CM57: 0 | CN57: 10.21727 | CO57: 10.21727 | CP57: 97.064067
A58: San Andrés | B58: 2020 | C58: 133.03105 | D58: 71.24 | E58: 0.34498449 | F58: 0.037 | G58: 44.085314 | H58: 55.95 | I58: 0.44179793 | J58: 40.810533 | K58: 947.51411 | L58: 10.646226 | M58: 0.42484805 | N58: 190.36364 | O58: 0.63106796 | P58: 20.498095 | Q58: n/a | R58: 100 | S58: 504.01289 | T58: 6.7865044 | U58: - | V58: - | W58: 2235218 | X58: 0.2632 | Y58: N/A | Z58: 0 | AA58: 0 | AB58: 17.411593 | AC58: 7.2 | AD58: 1.6701513 | AE58: 36.909532 | AF58: 77.338454 | AG58: 6229.037 | AH58: 239.578 | AI58: 0.5 | AJ58: 1822.7651 | AK58: 7.3232895 | AL58: 4.9001815 | AM58: 28.43903 | AN58: 0.88200935 | AO58: 0.9058 | AP58: 91.413474 | AQ58: 12.552301 | AR58: 139.47001 | AS58: 114.43296 | AT58: 35.050094 | AU58: 22.566499 | AV58: 184.53458 | AW58: 0.7544 | AX58: 0.9296 | AY58: 0.835 | AZ58: 0.5147 | BA58: 0.0179 | BB58: 237 | BC58: 229.58713 | BD58: 0.45945946 | BE58: 23.564865 | BF58: 1.346 | BG58: 77.77 | BH58: 31.603 | BI58: 127.32374 | BJ58: 29.72973 | BK58: 7.183908 | BL58: 27.338129 | BM58: 81.431335 | BN58: 0.68243243 | BO58: 0 | BP58: 0.2503977 | BQ58: 0.0228667 | BR58: 17.033961 | BS58: 17.246886 | BT58: 0.070987654 | BU58: 71.419345 | BV58: 7.0942712 | BW58: 66.771955 | BX58: 1.2092195 | BY58: 33.618965 | BZ58: 50.588178 | CA58: 115.30474 | CB58: 0.0028047564 | CC58: 0.30204132 | CD58: 27.872851 | CE58: 21.911102 | CF58: 0.52810473 | CG58: 0.336 | CH58: 0.32700416 | CI58: 0 | CJ58: 106.46226 | CK58: 0 | CL58: 0 | CM58: 17.74371 | CN58: 0 | CO58: 0 | CP58: 1863.0895
A59: San José del Guaviare | B59: 2020 | C59: 114.15591 | D59: 43.812857 | E59: 0.14860691 | F59: 0.018 | G59: 42.438627 | H59: 90.7 | I59: 0.00047483381 | J59: 36.810042 | K59: 274.23481 | L59: 47.853054 | M59: 0.55552706 | N59: 406.25 | O59: 0.81453426 | P59: 27.156869 | Q59: 0.38534241 | R59: 85.704827 | S59: 557.13359 | T59: 27.156869 | U59: 297.97881 | V59: 298.67085 | W59: 31114 | X59: 0.019 | Y59: N/A | Z59: 2666.8875 | AA59: 0 | AB59: 0 | AC59: 4.14 | AD59: 8.9879141 | AE59: 37.631111 | AF59: 69.987768 | AG59: 8002.964 | AH59: 500.185 | AI59: 1 | AJ59: 72257.527 | AK59: 20.799281 | AL59: 5.0816697 | AM59: 32.362648 | AN59: 0.98821218 | AO59: 0.9823 | AP59: 62.756598 | AQ59: 14.721346 | AR59: 100.80645 | AS59: 50.403702 | AT59: 9.4433165 | AU59: 2.8329949 | AV59: 167.48569 | AW59: 0.4805 | AX59: 0.8976 | AY59: 0.7991 | AZ59: 0.3658 | BA59: 0.0504 | BB59: 240 | BC59: 237.18345 | BD59: 0.41796875 | BE59: 27.0625 | BF59: 12.231 | BG59: 37.868 | BH59: 29.161 | BI59: 134.53862 | BJ59: 0 | BK59: 0 | BL59: 2.4390244 | BM59: 0 | BN59: 0.44954128 | BO59: 0.10638298 | BP59: 0.2060204 | BQ59: 0.0444669 | BR59: 11.043013 | BS59: 4.6932803 | BT59: 0.011764706 | BU59: 77.337921 | BV59: 12.416289 | BW59: 28.096669 | BX59: 14.175079 | BY59: 44.469101 | BZ59: 37.020714 | CA59: 85.588365 | CB59: 0 | CC59: 0.28460869 | CD59: 26.939351 | CE59: 18.42866 | CF59: 0.039575949 | CG59: 0.862 | CH59: 0.86135856 | CI59: 1.8405021 | CJ59: 0 | CK59: 0 | CL59: 0 | CM59: 0 | CN59: 0 | CO59: 0 | CP59: 18.405021
A60: Santa Marta | B60: 2020 | C60: 152.76533 | D60: 78.956667 | E60: 0.2527213 | F60: 0.039 | G60: 47.588413 | H60: 43.895 | I60: 0.18933333 | J60: 25.132425 | K60: 794.64507 | L60: 16.115448 | M60: 0.50186809 | N60: 343.94872 | O60: 0.53214774 | P60: 20.685848 | Q60: 0.87635262 | R60: 97.984561 | S60: 363.70383 | T60: 16.953673 | U60: 148.44876 | V60: 204.10839 | W60: 2316304 | X60: 0.269 | Y60: 36.982147 | Z60: 30.907127 | AA60: 14.852993 | AB60: 31.562609 | AC60: 15.94 | AD60: 18.941845 | AE60: 32.415684 | AF60: 65.502062 | AG60: 6761.905 | AH60: 749.206 | AI60: 1.8235 | AJ60: 167979.51 | AK60: 15.931754 | AL60: 1.6333938 | AM60: 28.382429 | AN60: 0.92004381 | AO60: 0.8752 | AP60: 81.479544 | AQ60: 10.945666 | AR60: 67.230119 | AS60: 29.578812 | AT60: 12.377307 | AU60: 4.3777793 | AV60: 349.93544 | AW60: 0.7043 | AX60: 0.9685 | AY60: 0.8644 | AZ60: 0.5084 | BA60: 0.0374 | BB60: 243.40528 | BC60: 234.35996 | BD60: 0.34204355 | BE60: 31.357789 | BF60: 55.585 | BG60: 204.931 | BH60: 17.355 | BI60: 141.78751 | BJ60: 9.7826087 | BK60: 65.669697 | BL60: 17.59322 | BM60: 45.940325 | BN60: 0.3623431 | BO60: 0.042372881 | BP60: 0.0850895 | BQ60: 0.0412927 | BR60: 15.232935 | BS60: 10.661136 | BT60: 0.0588447 | BU60: 59.874159 | BV60: 9.7296079 | BW60: 36.417194 | BX60: 9.6832727 | BY60: 59.257321 | BZ60: 37.430966 | CA60: 70.558484 | CB60: 0.013764698 | CC60: 0.60533553 | CD60: 29.373747 | CE60: 27.638335 | CF60: 27.269963 | CG60: 0.136 | CH60: 0.29640738 | CI60: 5.5636666 | CJ60: 439.33781 | CK60: 1.4 | CL60: 27.23 | CM60: 3.8370114 | CN60: 1.9185057 | CO60: 3.8370114 | CP60: 351.08655
A61: Sincelejo | B61: 2020 | C61: 147.15862 | D61: 43.60375 | E61: 0.17179151 | F61: 0.027 | G61: 57.887443 | H61: 43.16 | I61: 0.42192531 | J61: 17.094912 | K61: 820.55576 | L61: 13.606154 | M61: 0.50769069 | N61: 400.36842 | O61: 0.53475568 | P61: 78.058686 | Q61: 0.95526124 | R61: 93.09205 | S61: 413.26474 | T61: 71.326746 | U61: 255.80414 | V61: 255.80414 | W61: 87341 | X61: 0.1178 | Y61: 10.671653 | Z61: 430.86155 | AA61: 3.4019275 | AB61: 0 | AC61: 12.66 | AD61: 13.507654 | AE61: 28.712519 | AF61: 58.86425 | AG61: 4155.977 | AH61: 1006.433 | AI61: 1.3333 | AJ61: 98218.52 | AK61: 29.594946 | AL61: 1.814882 | AM61: 25.24472 | AN61: 0.9849508 | AO61: 1 | AP61: 86.744878 | AQ61: 15.095043 | AR61: 74.390924 | AS61: 134.7264 | AT61: 12.949631 | AU61: 5.2422862 | AV61: 521.91812 | AW61: 0.7465 | AX61: 1 | AY61: 0.8625 | AZ61: 0.5159 | BA61: 0.0264 | BB61: 260 | BC61: 252.52997 | BD61: 0.51019313 | BE61: 28.666309 | BF61: 76.609 | BG61: 74.881 | BH61: 12.57 | BI61: 136.08493 | BJ61: 5.5801594 | BK61: 3.5596363 | BL61: 11.933535 | BM61: 75.805758 | BN61: 0.26790451 | BO61: 0.095652174 | BP61: 0.0234135 | BQ61: 0.065118 | BR61: 8.861444 | BS61: 6.9216948 | BT61: 0.041330645 | BU61: 63.626304 | BV61: 11.932065 | BW61: 29.507592 | BX61: 10.749821 | BY61: 56.578824 | BZ61: 34.409861 | CA61: 71.121449 | CB61: 0.011859836 | CC61: 0.42059857 | CD61: 28.835439 | CE61: 28.204743 | CF61: 53.537669 | CG61: 0.247 | CH61: 0.99390007 | CI61: 4.186509 | CJ61: 558.2012 | CK61: 0.87 | CL61: 16.67 | CM61: 3.4887575 | CN61: 0 | CO61: 0 | CP61: 202.34793
A62: Tunja | B62: 2020 | C62: 167.6468 | D62: 77.376667 | E62: 0.35978208 | F62: 0.026 | G62: 49.980305 | H62: 55.43 | I62: 0.28424089 | J62: 3.9694466 | K62: 839.25442 | L62: 17.578978 | M62: 0.49908018 | N62: 261.45946 | O62: 0.49786142 | P62: 92.840528 | Q62: 0.9999813 | R62: 98.363818 | S62: 407.66404 | T62: 90.95431 | U62: 398.71071 | V62: 351.16586 | W62: N/A | X62: NA | Y62: 8.8417358 | Z62: 509.62024 | AA62: 39.048772 | AB62: 61.362356 | AC62: 24.89 | AD62: 14.071484 | AE62: 47.805259 | AF62: 76.247644 | AG62: 21307.716 | AH62: 2454.292 | AI62: 2.6875 | AJ62: 35336.873 | AK62: 41.719452 | AL62: 0.1814882 | AM62: 29.995695 | AN62: 0.89598198 | AO62: 0.9393 | AP62: 92.63468 | AQ62: 5.5147059 | AR62: 0 | AS62: 54.845602 | AT62: 14.144007 | AU62: 5.6787255 | AV62: 332.86645 | AW62: 0.8314 | AX62: 1 | AY62: 0.9647 | AZ62: 0.5557 | BA62: 0.0181 | BB62: 284 | BC62: 275.58228 | BD62: 0.81220096 | BE62: 29.94378 | BF62: 187.344 | BG62: 1179.6008 | BH62: 51.089 | BI62: 150.45557 | BJ62: 9.488342 | BK62: 65.182073 | BL62: 22.30585 | BM62: 0 | BN62: 0.55945252 | BO62: 0.069565217 | BP62: 0.0148993 | BQ62: 0.0354844 | BR62: 21.548424 | BS62: 12.152177 | BT62: 0.0060662622 | BU62: 60.107301 | BV62: 10.080843 | BW62: 57.047461 | BX62: 7.6115431 | BY62: 35.241899 | BZ62: 73.772459 | CA62: 142.81667 | CB62: 0.050307466 | CC62: 0.51622545 | CD62: 28.888408 | CE62: 25.948625 | CF62: 7.0261696 | CG62: 0.303 | CH62: 0.49797337 | CI62: 16.44485 | CJ62: 1044.2393 | CK62: 1.28 | CL62: 17.22 | CM62: 28.35319 | CN62: 5.670638 | CO62: 5.670638 | CP62: 929.98463
A63: Valledupar | B63: 2020 | C63: 156.31287 | D63: 19.667143 | E63: 0.23579383 | F63: 0.029 | G63: 62.775049 | H63: 52.565 | I63: 0.38360942 | J63: 16.547106 | K63: 644.55844 | L63: 12.264325 | M63: 0.52303859 | N63: 541.76812 | O63: 0.44148936 | P63: 88.204467 | Q63: 0.90610745 | R63: 96.486323 | S63: 394.81262 | T63: 88.204467 | U63: 212.88486 | V63: 209.91924 | W63: 446615 | X63: 0.2346 | Y63: 9.000376 | Z63: 557.20918 | AA63: 3.752655 | AB63: 9.3816375 | AC63: 14 | AD63: 16.585055 | AE63: 32.025988 | AF63: 72.015974 | AG63: 5910.914 | AH63: 667.089 | AI63: 1.3889 | AJ63: 116781.84 | AK63: 41.240053 | AL63: 3.6297641 | AM63: 27.576504 | AN63: 0.98432698 | AO63: 0.9044 | AP63: 87.953058 | AQ63: 11.433685 | AR63: 48.671274 | AS63: 46.127509 | AT63: 17.159082 | AU63: 6.5554241 | AV63: 472.66321 | AW63: 0.5766 | AX63: 0.8752 | AY63: 0.7582 | AZ63: 0.4778 | BA63: 0.0309 | BB63: 256.75113 | BC63: 245.99338 | BD63: 0.35505529 | BE63: 32.855055 | BF63: 51.333 | BG63: 224.251 | BH63: 18.995 | BI63: 138.56676 | BJ63: 10.939013 | BK63: 1.5399536 | BL63: 13.076369 | BM63: 49.832258 | BN63: 0.35922897 | BO63: 0.036697248 | BP63: 0.0900724 | BQ63: 0.0117954 | BR63: 9.6167885 | BS63: 6.7356454 | BT63: 0.047398844 | BU63: 59.791184 | BV63: 14.528078 | BW63: 31.964921 | BX63: 8.1135533 | BY63: 57.058202 | BZ63: 25.89934 | CA63: 63.098738 | CB63: 0.010616879 | CC63: 0.54002102 | CD63: 29.272707 | CE63: 28.608778 | CF63: 56.435514 | CG63: 0.083 | CH63: 0.98147912 | CI63: 1.5573747 | CJ63: 153.79075 | CK63: 1.32 | CL63: 41.79 | CM63: 0 | CN63: 0 | CO63: 1.9467183 | CP63: 210.24558
A64: Villavicencio | B64: 2020 | C64: 144.95605 | D64: 45.861429 | E64: 0.26753468 | F64: 0.02 | G64: 33.798014 | H64: 42.95 | I64: 0.14250914 | J64: 17.4454 | K64: 1206.5164 | L64: 36.375514 | M64: 0.50803133 | N64: 509.53333 | O64: 0.57355372 | P64: 41.236269 | Q64: 0.93637403 | R64: 96.141482 | S64: 395.72792 | T64: 41.136122 | U64: 274.75768 | V64: 206.45984 | W64: 286413 | X64: 0.2844 | Y64: 13.325538 | Z64: 1003.1662 | AA64: 1.8338462 | AB64: 0 | AC64: 18.36 | AD64: 20.677042 | AE64: 42.738748 | AF64: 80.937944 | AG64: 3448.132 | AH64: 766.484 | AI64: 1 | AJ64: 111129.84 | AK64: 31.464776 | AL64: 3.6297641 | AM64: 33.017136 | AN64: 0.92284644 | AO64: 0.8561 | AP64: 86.892373 | AQ64: 11.629461 | AR64: 53.297801 | AS64: 46.781514 | AT64: 13.905192 | AU64: 5.4746347 | AV64: 292.30324 | AW64: 0.6634 | AX64: 0.9295 | AY64: 0.8379 | AZ64: 0.4916 | BA64: 0.0322 | BB64: 267 | BC64: 263.92289 | BD64: 0.68347761 | BE64: 30.502823 | BF64: 44.158 | BG64: 141.17 | BH64: 10.718 | BI64: 141.66783 | BJ64: 5.9925094 | BK64: 17.281174 | BL64: 12.278142 | BM64: 30.456888 | BN64: 0.52376514 | BO64: 0.079136691 | BP64: 0.0148065 | BQ64: 0.0778745 | BR64: 13.77073 | BS64: 10.654685 | BT64: 0.011670441 | BU64: 64.856985 | BV64: 13.98294 | BW64: 42.152148 | BX64: 8.2808093 | BY64: 42.703493 | BZ64: 56.130558 | CA64: 88.00584 | CB64: 0.018638141 | CC64: 0.52386844 | CD64: 29.700738 | CE64: 27.288193 | CF64: 9.4313822 | CG64: 0.329 | CH64: 0.96724537 | CI64: 0.74235743 | CJ64: 228.27491 | CK64: 1.39 | CL64: 7 | CM64: 7.4235743 | CN64: 3.7117872 | CO64: 1.8558936 | CP64: 352.61978
A65: Yopal | B65: 2020 | C65: 148.23001 | D65: 44.8925 | E65: 0.32323672 | F65: 0.013 | G65: 29.092057 | H65: 70.93 | I65: 0.16153295 | J65: 12.672081 | K65: 1078.2789 | L65: 31.104199 | M65: 0.39299334 | N65: 334.93103 | O65: 0.28846154 | P65: 46.427879 | Q65: 0.91843649 | R65: 96.522139 | S65: 408.84141 | T65: 46.767506 | U65: 189.09233 | V65: 149.29266 | W65: 313945 | X65: 0.2464 | Y65: N/A | Z65: 1302.0563 | AA65: 5.6278421 | AB65: 0 | AC65: 16.92 | AD65: 12.650765 | AE65: 43.496832 | AF65: 75.662099 | AG65: 5156.191 | AH65: 470.455 | AI65: 0.8889 | AJ65: 41216.348 | AK65: 37.824672 | AL65: 1.6333938 | AM65: 34.13717 | AN65: 0.88935893 | AO65: 0.8259 | AP65: 81.595092 | AQ65: 7.6121795 | AR65: 79.649542 | AS65: 50.050984 | AT65: 13.183593 | AU65: 4.7834274 | AV65: 238.46553 | AW65: 0.7944 | AX65: 0.9776 | AY65: 0.8945 | AZ65: 0.5088 | BA65: 0.0254 | BB65: 268 | BC65: 262.78808 | BD65: 0.64637198 | BE65: 28.464554 | BF65: 43.661 | BG65: 115.179 | BH65: 13.26 | BI65: 138.7174 | BJ65: 1.8181818 | BK65: 11.279557 | BL65: 8.3948339 | BM65: 0 | BN65: 0.57355372 | BO65: 0.096774194 | BP65: 0.0651126 | BQ65: 0.019376 | BR65: 14.457693 | BS65: 13.167444 | BT65: 0.040682415 | BU65: 72.277781 | BV65: 9.4123239 | BW65: 42.557702 | BX65: 7.0444084 | BY65: 40.31241 | BZ65: 66.097975 | CA65: 95.088796 | CB65: 0.00933886 | CC65: 0.25066352 | CD65: 29.2545 | CE65: 28.028948 | CF65: 31.036852 | CG65: 0.478 | CH65: 0.99989739 | CI65: 0 | CJ65: 74.880479 | CK65: 0.08 | CL65: 0 | CM65: 0 | CN65: 0 | CO65: 5.7600369 | CP65: 316.80203
A66: Arauca | B66: 2021 | C66: 141.54343 | D66: 21.032857 | E66: 0.17379432 | F66: 0.013555592 | G66: 51.05988 | H66: 37.82 | I66: 0.072591526 | J66: 27.820281 | K66: 458.61136 | L66: 46.010465 | M66: 0.34376272 | N66: 402.47826 | O66: 0.73394495 | P66: 47.699374 | Q66: n/a | R66: 98.279209 | S66: 518.51351 | T66: 47.748627 | U66: 415.41377 | V66: 431.52527 | W66: 42157 | X66: 0.0066 | Y66: N/A | Z66: 1935.1145 | AA66: 0 | AB66: 0 | AC66: 10.05 | AD66: 8.7806192 | AE66: 22.427528 | AF66: 68.294633 | AG66: 870.793 | AH66: 188.28 | AI66: 0.2857 | AJ66: 29544.381 | AK66: 39.824446 | AL66: 0 | AM66: 28.831922 | AN66: 1 | AO66: 1 | AP66: 76.15894 | AQ66: 10.18011 | AR66: 0 | AS66: 60.806449 | AT66: 11.845412 | AU66: 4.2574815 | AV66: 192.12097 | AW66: 0.5362 | AX66: 0.9707 | AY66: 0.788 | AZ66: 0.4074 | BA66: 0.0296 | BB66: 255.62408 | BC66: 251.95337 | BD66: 0.53892944 | BE66: 26.006083 | BF66: 16.461 | BG66: 42.449 | BH66: 7.571 | BI66: 133.14667 | BJ66: 57.142857 | BK66: 0.94029149 | BL66: 13.5 | BM66: 43.097239 | BN66: 0.39962121 | BO66: 0.081474139 | BP66: 0.1386173 | BQ66: 0.064505 | BR66: 13.268134 | BS66: 7.4365751 | BT66: 0.035971223 | BU66: 58.298524 | BV66: 32.399432 | BW66: 24.397043 | BX66: 13.983287 | BY66: 48.012484 | BZ66: 57.404238 | CA66: 73.394836 | CB66: 0.0068786032 | CC66: 0.16 | CD66: 28.39507 | CE66: 25.327997 | CF66: 4.6907463 | CG66: 0.532 | CH66: 0.990311 | CI66: 0 | CJ66: 53.50054 | CK66: 0 | CL66: 0 | CM66: 0 | CN66: 0 | CO66: 0 | CP66: 117.70119
A67: Armenia | B67: 2021 | C67: 194.04181 | D67: 53.9325 | E67: 0.31401248 | F67: 0.027301265 | G67: 53.432254 | H67: 42.44 | I67: 0.39631976 | J67: 28.419136 | K67: 556.16805 | L67: 11.235472 | M67: 0.50489829 | N67: 472.91525 | O67: 0.30769231 | P67: 83.710613 | Q67: 0.90099433 | R67: 99.474448 | S67: 492.96135 | T67: 75.691736 | U67: 495.35992 | V67: 363.76445 | W67: 157165 | X67: 0.144 | Y67: 12.827448 | Z67: 246.35425 | AA67: 9.7256397 | AB67: 12.96752 | AC67: 28.24 | AD67: 26.085015 | AE67: 41.797892 | AF67: 74.634168 | AG67: 12812.76 | AH67: 1034.135 | AI67: 1.3889 | AJ67: 60400.976 | AK67: 51.10351 | AL67: 0.96038415 | AM67: 31.269909 | AN67: 0.93880012 | AO67: 0.8907563 | AP67: 92.297205 | AQ67: 10.484928 | AR67: 32.743942 | AS67: 57.778396 | AT67: 21.054686 | AU67: 10.030344 | AV67: 281.20119 | AW67: 0.7834 | AX67: 0.9267 | AY67: 0.8967 | AZ67: 0.6011 | BA67: 0.037 | BB67: 267 | BC67: 259.53028 | BD67: 0.63607595 | BE67: 24.417089 | BF67: 74.568 | BG67: 244.509 | BH67: 41.177 | BI67: 148.67425 | BJ67: 9.2623405 | BK67: 50.476868 | BL67: 34.404284 | BM67: 73.003863 | BN67: 0.51135371 | BO67: 0.017866821 | BP67: 0.0544573 | BQ67: 0.0782741 | BR67: 7.9970127 | BS67: 8.4133861 | BT67: 0.061272584 | BU67: 57.610429 | BV67: 22.409954 | BW67: 30.762658 | BX67: 9.8297485 | BY67: 41.805961 | BZ67: 40.681075 | CA67: 111.58343 | CB67: 0.042263083 | CC67: 0.68 | CD67: 29.10661 | CE67: 26.932134 | CF67: 14.455019 | CG67: 0.18 | CH67: 0.8325571 | CI67: 1.9827304 | CJ67: 508.90081 | CK67: 1.01 | CL67: 19.86 | CM67: 56.177362 | CN67: 19.827304 | CO67: 23.131855 | CP67: 938.4924
A68: Barranquilla AM | B68: 2021 | C68: 185.36154 | D68: 71.188127 | E68: 0.34197039 | F68: 0.044711324 | G68: 59.733463 | H68: 49.067451 | I68: 0.28163933 | J68: 24.142248 | K68: 650.50217 | L68: 8.0647595 | M68: 0.36131018 | N68: 470.15 | O68: 0.38970588 | P68: 94.430386 | Q68: 0.88488023 | R68: 99.767144 | S68: 435.60338 | T68: 86.383685 | U68: 262.63639 | V68: 290.60589 | W68: 963544 | X68: 0.31 | Y68: 16.601367 | Z68: 549.5067 | AA68: 5.5720127 | AB68: 10.130932 | AC68: 17.822438 | AD68: 37.778913 | AE68: 44.982809 | AF68: 77.643446 | AG68: 6870.28 | AH68: 1008.939 | AI68: 1.9524 | AJ68: 119869.2 | AK68: 62.806516 | AL68: 6.242497 | AM68: 28.368488 | AN68: 0.99762929 | AO68: 0.97994485 | AP68: 83.246647 | AQ68: 14.565922 | AR68: 129.44543 | AS68: 63.445157 | AT68: 29.157301 | AU68: 11.8723 | AV68: 272.73135 | AW68: 0.66282325 | AX68: 0.91247789 | AY68: 0.81987401 | AZ68: 0.52568576 | BA68: 0.0082322669 | BB68: 253.70579 | BC68: 246.29348 | BD68: 0.492583 | BE68: 29.789616 | BF68: 53.655 | BG68: 400.465 | BH68: 20.119 | BI68: 142.27608 | BJ68: 13.529222 | BK68: 55.379183 | BL68: 37.165387 | BM68: 61.639308 | BN68: 0.4670724 | BO68: 0.12200165 | BP68: 0.0287095 | BQ68: 0.0736313 | BR68: 14.797533 | BS68: 13.825079 | BT68: 0.063452636 | BU68: 58.856436 | BV68: 11.008988 | BW68: 21.841775 | BX68: 14.013588 | BY68: 53.562108 | BZ68: 44.655246 | CA68: 88.64041 | CB68: 0.040762874 | CC68: 0.77 | CD68: 31.167598 | CE68: 28.932267 | CF68: 30.644741 | CG68: 0.124 | CH68: 0.054935835 | CI68: 6.6078997 | CJ68: 626.44971 | CK68: 1.17 | CL68: 21.06 | CM68: 17.69044 | CN68: 5.2030706 | CO68: 5.7233777 | CP68: 1145.7162
A69: Bogotá D.C. | B69: 2021 | C69: 218.75817 | D69: 91.9025 | E69: 0.51387492 | F69: 0.037901692 | G69: 66.446841 | H69: 48.215 | I69: 0.65729288 | J69: 13.605511 | K69: 1276.4537 | L69: 13.062325 | M69: 0.43166684 | N69: 643.80541 | O69: 0.39865823 | P69: 98.99616 | Q69: 0.96366089 | R69: 99.998401 | S69: 439.36151 | T69: 98.983301 | U69: 406.18352 | V69: 345.28285 | W69: 3716693.3 | X69: 0.60508 | Y69: 18.718942 | Z69: 685.65955 | AA69: 9.1905113 | AB69: 20.295712 | AC69: 26.8 | AD69: 44.954478 | AE69: 63.897082 | AF69: 87.173928 | AG69: 10571.802 | AH69: 1551.204 | AI69: 2.5985 | AJ69: 36563.804 | AK69: 37.767243 | AL69: 6.002401 | AM69: 33.456585 | AN69: 0.92568644 | AO69: 0.89323048 | AP69: 85.359632 | AQ69: 7.9176963 | AR69: 63.034215 | AS69: 123.39371 | AT69: 44.633059 | AU69: 27.041599 | AV69: 182.34868 | AW69: 0.6916 | AX69: 0.9379 | AY69: 0.8907 | AZ69: 0.573 | BA69: 0.0047 | BB69: 272.38782 | BC69: 256.86069 | BD69: 0.39982475 | BE69: 24.656944 | BF69: 82.39 | BG69: 596.704 | BH69: 28.895 | BI69: 151.33609 | BJ69: 10.839106 | BK69: 34.39278 | BL69: 41.334932 | BM69: 31.233906 | BN69: 0.65643911 | BO69: 0.37315341 | BP69: 0.0052617 | BQ69: 0.0066994 | BR69: 16.214096 | BS69: 24.276654 | BT69: 0.07561624 | BU69: 66.091963 | BV69: 18.382675 | BW69: 35.436867 | BX69: 10.532041 | BY69: 34.273043 | BZ69: 77.407326 | CA69: 114.14494 | CB69: 0.068188498 | CC69: 0.8 | CD69: 33.129108 | CE69: 29.722466 | CF69: 39.770778 | CG69: 0.168 | CH69: 0.02886307 | CI69: 7.5140701 | CJ69: 694.88982 | CK69: 1.72 | CL69: 19.85 | CM69: 37.505686 | CN69: 15.778254 | CO69: 29.099239 | CP69: 3389.8673
A70: Bucaramanga AM | B70: 2021 | C70: 203.52955 | D70: 77.063775 | E70: 0.36709161 | F70: 0.026311455 | G70: 59.208389 | H70: 64.75984 | I70: 0.19091127 | J70: 15.371118 | K70: 674.93999 | L70: 9.0650183 | M70: 0.43805268 | N70: 554.27174 | O70: 0.53415929 | P70: 71.452391 | Q70: 0.96361755 | R70: 99.729281 | S70: 441.23776 | T70: 67.477571 | U70: 341.39818 | V70: 271.22523 | W70: 606608 | X70: 0.1846 | Y70: 7.9599711 | Z70: 907.20338 | AA70: 7.0066446 | AB70: 6.2281286 | AC70: 23.035552 | AD70: 37.425953 | AE70: 50.178464 | AF70: 80.175522 | AG70: 10160.879 | AH70: 1137.499 | AI70: 2.3889 | AJ70: 55568.247 | AK70: 51.74 | AL70: 5.2821128 | AM70: 28.578598 | AN70: 0.88009976 | AO70: 0.82773782 | AP70: 90.914126 | AQ70: 6.5836047 | AR70: 77.793494 | AS70: 64.639156 | AT70: 23.280087 | AU70: 11.997154 | AV70: 261.92994 | AW70: 0.71943492 | AX70: 0.95329931 | AY70: 0.86586145 | AZ70: 0.52020182 | BA70: 0.015345083 | BB70: 280.58904 | BC70: 272.71119 | BD70: 0.736138 | BE70: 28.53899 | BF70: 54.823 | BG70: 703.179 | BH70: 27.705 | BI70: 147.43366 | BJ70: 9.9087003 | BK70: 43.022738 | BL70: 37.090505 | BM70: 70.625732 | BN70: 0.5093149 | BO70: 0.070872714 | BP70: 0.0163077 | BQ70: 0.0052737 | BR70: 9.6404498 | BS70: 11.246929 | BT70: 0.062026913 | BU70: 63.223067 | BV70: 17.824884 | BW70: 25.136683 | BX70: 9.58202 | BY70: 47.294152 | BZ70: 59.491096 | CA70: 90.942259 | CB70: 0.053147894 | CC70: 0.57 | CD70: 30.938674 | CE70: 28.048622 | CF70: 9.7032283 | CG70: 0.15 | CH70: 0.21746571 | CI70: 6.7002309 | CJ70: 646.37521 | CK70: 1.17 | CL70: 19.36 | CM70: 43.354435 | CN70: 9.4591495 | CO70: 14.188724 | CP70: 1177.6641
A71: Cali AM | B71: 2021 | C71: 233.75399 | D71: 76.953977 | E71: 0.46646938 | F71: 0.032570146 | G71: 64.246297 | H71: 65.233563 | I71: 0.42674671 | J71: 49.01215 | K71: 846.79083 | L71: 22.630718 | M71: 0.47843436 | N71: 502.34066 | O71: 0.28177502 | P71: 72.506482 | Q71: 0.83137742 | R71: 99.873877 | S71: 417.22311 | T71: 72.285446 | U71: 364.40062 | V71: 333.04577 | W71: 1874335 | X71: 0.3856 | Y71: 20.461472 | Z71: 1848.7273 | AA71: 10.524406 | AB71: 7.5775722 | AC71: 23.537502 | AD71: 39.10647 | AE71: 50.949048 | AF71: 82.960341 | AG71: 5750.242 | AH71: 698.676 | AI71: 1.7931 | AJ71: 71671.688 | AK71: 51.581631 | AL71: 5.1620648 | AM71: 30.038185 | AN71: 0.95918113 | AO71: 0.96599694 | AP71: 92.073681 | AQ71: 8.0764185 | AR71: 53.25468 | AS71: 65.210697 | AT71: 27.247867 | AU71: 13.060907 | AV71: 230.96604 | AW71: 0.60763304 | AX71: 0.80440397 | AY71: 0.77100263 | AZ71: 0.47189142 | BA71: 0.026472831 | BB71: 262.18629 | BC71: 250.0724 | BD71: 0.40290408 | BE71: 30.649604 | BF71: 45.711 | BG71: 280.933 | BH71: 16.15 | BI71: 145.86242 | BJ71: 15.605127 | BK71: 46.128723 | BL71: 38.71221 | BM71: 75.102077 | BN71: 0.54888057 | BO71: 0.18667292 | BP71: 0.0168392 | BQ71: 0.0099212 | BR71: 10.329216 | BS71: 13.867952 | BT71: 0.071200656 | BU71: 62.378097 | BV71: 20.657006 | BW71: 27.477742 | BX71: 13.07408 | BY71: 39.43597 | BZ71: 56.833573 | CA71: 96.899413 | CB71: 0.053013209 | CC71: 0.73 | CD71: 31.59431 | CE71: 28.87868 | CF71: 21.673738 | CG71: 0.116 | CH71: 0.027408119 | CI71: 6.4057152 | CJ71: 493.0715 | CK71: 1.25 | CL71: 23.36 | CM71: 22.335718 | CN71: 7.1642868 | CO71: 21.49286 | CP71: 2029.6003
A72: Cartagena | B72: 2021 | C72: 209.54394 | D72: 75.61 | E72: 0.37844952 | F72: 0.029702241 | G72: 55.038139 | H72: 90.7 | I72: 0.28422725 | J72: 22.798384 | K72: 498.76742 | L72: 10.907847 | M72: 0.39988148 | N72: 492.84252 | O72: 0.36842105 | P72: 45.795458 | Q72: 0.95993038 | R72: 97.247355 | S72: 403.09666 | T72: 44.477487 | U72: 262.48884 | V72: 263.43563 | W72: 1814492 | X72: 0.4624 | Y72: 15.091864 | Z72: 659.37446 | AA72: 9.579223 | AB72: 91.529236 | AC72: 16.03 | AD72: 41.744775 | AE72: 30.987781 | AF72: 66.898285 | AG72: 4730.181 | AH72: 686.244 | AI72: 1.5263 | AJ72: 110164.7 | AK72: 51.532482 | AL72: 3.3613445 | AM72: 27.437401 | AN72: 0.916859 | AO72: 0.89623662 | AP72: 89.958302 | AQ72: 12.048911 | AR72: 136.94552 | AS72: 39.588917 | AT72: 19.213624 | AU72: 8.5235104 | AV72: 289.77308 | AW72: 0.7317 | AX72: 1 | AY72: 0.9472 | AZ72: 0.5694 | BA72: 0.0192 | BB72: 244.57122 | BC72: 229.97422 | BD72: 0.43955806 | BE72: 34.201473 | BF72: 44.187 | BG72: 222.381 | BH72: 31.811 | BI72: 141.30523 | BJ72: 9.0239913 | BK72: 40.13347 | BL72: 32.611412 | BM72: 76.368876 | BN72: 0.37079386 | BO72: 0.23456665 | BP72: 0.3478084 | BQ72: 0.0144095 | BR72: 13.570934 | BS72: 11.987823 | BT72: 0.065415198 | BU72: 56.892826 | BV72: 12.042572 | BW72: 17.821058 | BX72: 5.7626555 | BY72: 60.633804 | BZ72: 40.176878 | CA72: 82.219639 | CB72: 0.017316245 | CC72: 0.4 | CD72: 30.746263 | CE72: 29.065653 | CF72: 45.398064 | CG72: 0.113 | CH72: 0.069074866 | CI72: 5.0117137 | CJ72: 438.27927 | CK72: 0 | CL72: 29.32 | CM72: 2.9480669 | CN72: 1.9653779 | CO72: 14.740334 | CP72: 736.03402
A73: Cúcuta AM | B73: 2021 | C73: 193.75553 | D73: 68.30965 | E73: 0.1847952 | F73: 0.026719727 | G73: 62.058688 | H73: 50 | I73: 0.13689623 | J73: 33.367031 | K73: 443.85461 | L73: 16.584209 | M73: 0.44265402 | N73: 598.68317 | O73: 0.575 | P73: 70.706951 | Q73: 0.77928672 | R73: 99.202003 | S73: 473.57867 | T73: 70.753287 | U73: 200.23307 | V73: 164.6814 | W73: 380655 | X73: 0.2542 | Y73: 11.942362 | Z73: 708.92032 | AA73: 3.8870501 | AB73: 27.209351 | AC73: 14.597711 | AD73: 35.819177 | AE73: 39.469189 | AF73: 74.579021 | AG73: 6035.904 | AH73: 606.836 | AI73: 1.3462 | AJ73: 102764.31 | AK73: 46.008967 | AL73: 1.3205282 | AM73: 27.068235 | AN73: 1 | AO73: 1 | AP73: 79.657033 | AQ73: 9.7236046 | AR73: 99.472033 | AS73: 46.95126 | AT73: 12.14438 | AU73: 6.1773092 | AV73: 157.44277 | AW73: 0.70144596 | AX73: 0.89049557 | AY73: 0.826603 | AZ73: 0.46527177 | BA73: 0.034720031 | BB73: 263.07076 | BC73: 261.58393 | BD73: 0.65817998 | BE73: 32.581044 | BF73: 38.185 | BG73: 158.905 | BH73: 14.707 | BI73: 141.25201 | BJ73: 9.6076861 | BK73: 12.720408 | BL73: 19.928115 | BM73: 64.135347 | BN73: 0.31979892 | BO73: 0.082561855 | BP73: 0.0125115 | BQ73: 0.0068909 | BR73: 8.9177364 | BS73: 6.6982329 | BT73: 0.044329133 | BU73: 55.42422 | BV73: 22.376794 | BW73: 14.82705 | BX73: 12.667999 | BY73: 70.745936 | BZ73: 40.504218 | CA73: 62.215087 | CB73: 0.027765988 | CC73: 0.43 | CD73: 29.987513 | CE73: 27.561185 | CF73: 10.987383 | CG73: 0.086 | CH73: 0.34351407 | CI73: 1.7875195 | CJ73: 219.46768 | CK73: 1.22 | CL73: 19.56 | CM73: 9.9306641 | CN73: 0.99306641 | CO73: 2.9791992 | CP73: 595.83985
A74: Florencia | B74: 2021 | C74: 170.23904 | D74: 56.255 | E74: 0.17481589 | F74: 0.023161288 | G74: 41.83774 | H74: 61.96 | I74: 0.099370739 | J74: 25.390524 | K74: 626.54976 | L74: 16.157606 | M74: 0.44220163 | N74: 665.64103 | O74: 0.47058824 | P74: 74.675275 | Q74: 0.91675137 | R74: 94.486926 | S74: 490.45447 | T74: 74.675275 | U74: 419.69485 | V74: 476.72565 | W74: 42882 | X74: 0.005 | Y74: 9.9382714 | Z74: 906.90334 | AA74: 5.7195477 | AB74: 5.7195477 | AC74: 13.76 | AD74: 16.544086 | AE74: 32.606844 | AF74: 67.634542 | AG74: 5331.998 | AH74: 335.827 | AI74: 2.3333 | AJ74: 62952.693 | AK74: 58.607083 | AL74: 5.8823529 | AM74: 28.413185 | AN74: 0.94298099 | AO74: 0.89385475 | AP74: 85.091815 | AQ74: 6.8681319 | AR74: 66.912011 | AS74: 34.71215 | AT74: 9.7658139 | AU74: 3.6500938 | AV74: 287.84297 | AW74: 0.6906 | AX74: 0.959 | AY74: 0.803 | AZ74: 0.4176 | BA74: 0.061073 | BB74: 258 | BC74: 252.55964 | BD74: 0.75792988 | BE74: 27.957429 | BF74: 58.393 | BG74: 320.911 | BH74: 9.404 | BI74: 135.69048 | BJ74: 7.8988942 | BK74: 0.050192404 | BL74: 12.903226 | BM74: 27.728155 | BN74: 0.28453608 | BO74: 0.10030392 | BP74: 0.0399122 | BQ74: 0.0359186 | BR74: 7.7325685 | BS74: 5.4012568 | BT74: 0.03525641 | BU74: 59.198433 | BV74: 21.150533 | BW74: 16.946043 | BX74: 6.9411536 | BY74: 41.972862 | BZ74: 72.58017 | CA74: 79.852961 | CB74: 0.013374959 | CC74: 0.49 | CD74: 28.344893 | CE74: 17.745167 | CF74: 0.053068011 | CG74: 0.616 | CH74: 0.32355639 | CI74: 1.1541147 | CJ74: 230.82294 | CK74: 0.92 | CL74: 13.51 | CM74: 0 | CN74: 0 | CO74: 0 | CP74: 155.80549
A75: Ibagué | B75: 2021 | C75: 184.74437 | D75: 69.86125 | E75: 0.24138317 | F75: 0.025227799 | G75: 56.699287 | H75: 45.35 | I75: 0.56433555 | J75: 11.930527 | K75: 719.82865 | L75: 19.200692 | M75: 0.42057543 | N75: 470.94393 | O75: 0.64428312 | P75: 51.774626 | Q75: 0.97235713 | R75: 99.528757 | S75: 464.69609 | T75: 51.452263 | U75: 302.06657 | V75: 306.65242 | W75: 29106 | X75: 0.1068 | Y75: 13.942002 | Z75: 884.1639 | AA75: 11.055343 | AB75: 18.425572 | AC75: 22.42 | AD75: 36.526065 | AE75: 43.924345 | AF75: 78.468172 | AG75: 11094.165 | AH75: 1201.346 | AI75: 1.7895 | AJ75: 39309.364 | AK75: 51.699185 | AL75: 3.9615846 | AM75: 29.113827 | AN75: 0.98724603 | AO75: 0.94891159 | AP75: 91.406371 | AQ75: 7.8341766 | AR75: 48.915702 | AS75: 47.986544 | AT75: 14.58277 | AU75: 6.2318269 | AV75: 201.07152 | AW75: 0.8305 | AX75: 1 | AY75: 0.9336 | AZ75: 0.5542 | BA75: 0.0243 | BB75: 264 | BC75: 256.60222 | BD75: 0.59153999 | BE75: 27.043952 | BF75: 48.037 | BG75: 188.402 | BH75: 29.399 | BI75: 142.93695 | BJ75: 11.530126 | BK75: 46.350912 | BL75: 22.901169 | BM75: 75.169674 | BN75: 0.43840074 | BO75: 0.36608022 | BP75: 0.0164071 | BQ75: 0.49150035 | BR75: 11.371284 | BS75: 9.1902341 | BT75: 0.037931034 | BU75: 59.784419 | BV75: 22.481627 | BW75: 23.131328 | BX75: 10.630945 | BY75: 41.051451 | BZ75: 68.261962 | CA75: 96.386229 | CB75: 0.024508913 | CC75: 0.59 | CD75: 29.817797 | CE75: 25.496375 | CF75: 2.6274991 | CG75: 0.294 | CH75: 0.25463236 | CI75: 2.6098028 | CJ75: 380.28555 | CK75: 1.73 | CL75: 18.97 | CM75: 16.777304 | CN75: 3.7282897 | CO75: 58.789857 | CP75: 982.40434
A76: Inírida | B76: 2021 | C76: 126.15764 | D76: 39.751429 | E76: 0.12884349 | F76: 0.01545667 | G76: 53.009813 | H76: 37.79 | I76: 0.0011648224 | J76: 11.755716 | K76: 255.32168 | L76: 20.572503 | M76: 0.69681742 | N76: 352.5 | O76: 0.015873016 | P76: 15.482438 | Q76: n/a | R76: 61.536235 | S76: 537.44972 | T76: 11.241171 | U76: - | V76: - | W76: 19112 | X76: 0.0036 | Y76: N/A | Z76: 1981.1321 | AA76: 29.068922 | AB76: 0 | AC76: 4.2 | AD76: 1.2099505 | AE76: 22.482312 | AF76: 49.375557 | AG76: 4638.619 | AH76: 269.687 | AI76: 2.3333 | AJ76: 71087.094 | AK76: 37.366307 | AL76: 2.5210084 | AM76: 31.354344 | AN76: 0.96541787 | AO76: 1 | AP76: 31.447368 | AQ76: 15.965167 | AR76: 234.22795 | AS76: 59.993078 | AT76: 16.921124 | AU76: 3.8457101 | AV76: 115.78541 | AW76: 0.6108 | AX76: 0.7331 | AY76: 0.424 | AZ76: 0.1445 | BA76: 0.0308 | BB76: 243 | BC76: 243.01639 | BD76: 0.18489583 | BE76: 32.960938 | BF76: 5 | BG76: 104.061 | BH76: 13.438 | BI76: 125.81667 | BJ76: 0 | BK76: 1.3947001 | BL76: 0 | BM76: 0 | BN76: 0.36437247 | BO76: 0 | BP76: 0.2132241 | BQ76: 0.0284747 | BR76: 5.2900723 | BS76: 3.0858755 | BT76: 0.019047619 | BU76: 53.190742 | BV76: 15.801476 | BW76: 19.875664 | BX76: 3.8505747 | BY76: 59.707075 | BZ76: 32.906394 | CA76: 85.582329 | CB76: 0.00092199586 | CC76: 0.09 | CD76: 26.46028 | CE76: 11.759792 | CF76: 0.11735056 | CG76: 0.5 | CH76: 0.47120081 | CI76: 0 | CJ76: 0 | CK76: 0 | CL76: 0 | CM76: 0 | CN76: 0 | CO76: 0 | CP76: 146.94645
A77: Leticia | B77: 2021 | C77: 125.04569 | D77: 16.915714 | E77: 0.23180733 | F77: 0.024228901 | G77: 46.6996 | H77: 88.37 | I77: 0 | J77: 15.701668 | K77: 285.50174 | L77: 9.8135427 | M77: 0.4373608 | N77: 245.11111 | O77: 0 | P77: 79.685465 | Q77: n/a | R77: 83.168203 | S77: 515.95514 | T77: 79.685465 | U77: - | V77: - | W77: 102831 | X77: 0.1258 | Y77: N/A | Z77: 954.66143 | AA77: 38.808209 | AB77: 0 | AC77: 2.58 | AD77: 1.7942439 | AE77: 16.252225 | AF77: 44.746427 | AG77: 2771.551 | AH77: 101.895 | AI77: 0.8 | AJ77: 62313.048 | AK77: 13.278446 | AL77: 6.6026411 | AM77: 32.537543 | AN77: 0.87002653 | AO77: 0.85714286 | AP77: 60.560093 | AQ77: 12.430939 | AR77: 176.52251 | AS77: 66.482752 | AT77: 12.675216 | AU77: 3.8522716 | AV77: 255.3431 | AW77: 0.5923 | AX77: 0.9292 | AY77: 0.7768 | AZ77: 0.4487 | BA77: 0.0272 | BB77: 231 | BC77: 226.74545 | BD77: 0.18577075 | BE77: 27.305665 | BF77: 7.775 | BG77: 106.3 | BH77: 9.05 | BI77: 133.52778 | BJ77: 57.420635 | BK77: 7.0695553 | BL77: 0 | BM77: 0 | BN77: 0.35555556 | BO77: 0.14540057 | BP77: 0.1589874 | BQ77: 0.018875 | BR77: 5.6918548 | BS77: 5.1226693 | BT77: 0.038314176 | BU77: 54.633529 | BV77: 8.5239193 | BW77: 22.149565 | BX77: 4.796422 | BY77: 62.157859 | BZ77: 34.228188 | CA77: 65.779927 | CB77: 0.0030547781 | CC77: 0.31 | CD77: 27.099018 | CE77: 0 | CF77: 0.34844837 | CG77: 1 | CH77: 1 | CI77: 7.8508342 | CJ77: 412.16879 | CK77: 0.33 | CL77: 42.87 | CM77: 0 | CN77: 0 | CO77: 0 | CP77: 510.30422
A78: Manizales AM | B78: 2021 | C78: 186.21437 | D78: 57.076482 | E78: 0.30478309 | F78: 0.024057122 | G78: 54.000016 | H78: 42.842381 | I78: 0.087453001 | J78: 9.7545178 | K78: 283.68988 | L78: 9.7545178 | M78: 0.55629457 | N78: 461.11494 | O78: 0.4003268 | P78: 94.821223 | Q78: 0.71932734 | R78: 99.870685 | S78: 493.15091 | T78: 92.495042 | U78: 307.97489 | V78: 264.12442 | W78: 67681 | X78: 0.004 | Y78: 9.6568097 | Z78: 993.28304 | AA78: 9.6507584 | AB78: 27.022123 | AC78: 21.224795 | AD78: 30.450076 | AE78: 49.998966 | AF78: 77.125178 | AG78: 11055.567 | AH78: 1904.14 | AI78: 2.7333 | AJ78: 84827.46 | AK78: 39.591316 | AL78: 1.5606242 | AM78: 31.642355 | AN78: 0.92660975 | AO78: 0.9393808 | AP78: 94.726343 | AQ78: 8.3507307 | AR78: 89.392133 | AS78: 61.296118 | AT78: 20.304767 | AU78: 10.769163 | AV78: 303.55011 | AW78: 0.6371687 | AX78: 0.76645045 | AY78: 0.75142611 | AZ78: 0.486736 | BA78: 0.022374208 | BB78: 272.77213 | BC78: 263.78462 | BD78: 0.67955239 | BE78: 22.678026 | BF78: 76.518 | BG78: 654.323 | BH78: 30.984 | BI78: 146.60504 | BJ78: 20.613456 | BK78: 68.234056 | BL78: 35.434174 | BM78: 60.985407 | BN78: 0.51780586 | BO78: 0.10109667 | BP78: 0.0616892 | BQ78: 0.0564867 | BR78: 6.7696354 | BS78: 9.4774895 | BT78: 0.07307534 | BU78: 56.795366 | BV78: 18.224965 | BW78: 33.110389 | BX78: 5.6612184 | BY78: 29.189172 | BZ78: 33.938772 | CA78: 89.535213 | CB78: 0.039897057 | CC78: 0.59 | CD78: 29.725128 | CE78: 28.00125 | CF78: 25.087526 | CG78: 0.112 | CH78: 0.40266771 | CI78: 14.241596 | CJ78: 953.99184 | CK78: 0.62 | CL78: 32.67 | CM78: 50.723493 | CN78: 25.361746 | CO78: 25.361746 | CP78: 1297.3509
A79: Medellín AM | B79: 2021 | C79: 231.27431 | D79: 72.962923 | E79: 0.38149486 | F79: 0.028488555 | G79: 65.911914 | H79: 66.458912 | I79: 0.032156884 | J79: 15.560024 | K79: 797.59899 | L79: 18.940477 | M79: 0.4729321 | N79: 638.76699 | O79: 0.50531799 | P79: 93.994264 | Q79: 0.83060874 | R79: 99.674771 | S79: 471.05816 | T79: 91.620687 | U79: 424.13361 | V79: 378.8563 | W79: 3353270 | X79: 0.5612 | Y79: 23.063328 | Z79: 2372.4414 | AA79: 7.526084 | AB79: 13.35273 | AC79: 25.975314 | AD79: 37.002023 | AE79: 50.082136 | AF79: 77.57069 | AG79: 9268.905 | AH79: 1108.692 | AI79: 2.5065 | AJ79: 25612.273 | AK79: 50.978899 | AL79: 2.5210084 | AM79: 31.171347 | AN79: 0.94372908 | AO79: 0.93674483 | AP79: 92.35117 | AQ79: 6.4509416 | AR79: 49.446975 | AS79: 69.5792 | AT79: 25.815859 | AU79: 12.772579 | AV79: 150.66718 | AW79: 0.79330392 | AX79: 0.91727277 | AY79: 0.88110134 | AZ79: 0.51238841 | BA79: 0.018406857 | BB79: 262.91078 | BC79: 253.81259 | BD79: 0.56831837 | BE79: 30.35527 | BF79: 59.938 | BG79: 363.59 | BH79: 26.982 | BI79: 148.03744 | BJ79: 14.826879 | BK79: 38.933044 | BL79: 39.109829 | BM79: 63.500182 | BN79: 0.60560316 | BO79: 0.17128288 | BP79: 0.0076057 | BQ79: 0.0344897 | BR79: 11.105781 | BS79: 15.014926 | BT79: 0.082904299 | BU79: 62.528008 | BV79: 17.376127 | BW79: 35.881771 | BX79: 9.6491847 | BY79: 32.556881 | BZ79: 38.720014 | CA79: 109.07237 | CB79: 0.08307613 | CC79: 0.91 | CD79: 32.180561 | CE79: 29.975232 | CF79: 28.710891 | CG79: 0.135 | CH79: 0.20083219 | CI79: 8.1528561 | CJ79: 706.66372 | CK79: 1.02 | CL79: 21.61 | CM79: 36.538715 | CN79: 8.4511313 | CO79: 58.163669 | CP79: 3350.1279
A80: Mitú | B80: 2021 | C80: 125.52549 | D80: 16.388333 | E80: 0.1509952 | F80: 0.018609949 | G80: 48.293685 | H80: 73.26 | I80: 0.00068073519 | J80: 12.704462 | K80: 64.038057 | L80: 6.3522312 | M80: 0.59438202 | N80: 146.25 | O80: 0 | P80: 100 | Q80: n/a | R80: 87.016453 | S80: 512.35319 | T80: 100 | U80: - | V80: - | W80: 11270 | X80: 0.0372 | Y80: N/A | Z80: 3875.4963 | AA80: 0 | AB80: 0 | AC80: 0.16 | AD80: 4.8748437 | AE80: 30.926321 | AF80: 43.633623 | AG80: 26.969 | AH80: 0 | AI80: 0.2 | AJ80: 68486.83 | AK80: 11.116606 | AL80: 2.4009604 | AM80: 26.25243 | AN80: 0.89065256 | AO80: 0.82472325 | AP80: 38.130841 | AQ80: 6.2111801 | AR80: 187.26592 | AS80: 36.584236 | AT80: 4.3993702 | AU80: 1.3892748 | AV80: 60.988626 | AW80: 0.3591 | AX80: 0.6046 | AY80: 0.4019 | AZ80: 0.1784 | BA80: 0.0248 | BB80: 214 | BC80: 214.11364 | BD80: 0.18258427 | BE80: 26.769663 | BF80: 1.034 | BG80: 57.504 | BH80: 3.044 | BI80: 127.625 | BJ80: 0 | BK80: 0 | BL80: 4.1666667 | BM80: 0 | BN80: 0.30693069 | BO80: 0.038461538 | BP80: 0.36829102 | BQ80: 0.062254 | BR80: 5.081785 | BS80: 1.8739082 | BT80: 0.016949153 | BU80: 55.791081 | BV80: 16.287184 | BW80: 26.960394 | BX80: 4.5721543 | BY80: 53.084482 | BZ80: 19.265428 | CA80: 30.985454 | CB80: 0.024578678 | CC80: 0.03 | CD80: 26.16794 | CE80: 17.578082 | CF80: 0.11703482 | CG80: 0.977 | CH80: 0.97725111 | CI80: 0 | CJ80: 0 | CK80: 0 | CL80: 0 | CM80: 0 | CN80: 0 | CO80: 0 | CP80: 0
A81: Mocoa | B81: 2021 | C81: 134.49881 | D81: 10.282857 | E81: 0.24866896 | F81: 0.014580833 | G81: 32.448819 | H81: 37.82 | I81: 0.44848036 | J81: 18.285486 | K81: 337.64295 | L81: 19.947803 | M81: 0.44575739 | N81: 335.57143 | O81: 0.5 | P81: 49.812792 | Q81: 0.73365337 | R81: 87.275066 | S81: 617.55013 | T81: 46.027594 | U81: 381.31536 | V81: 327.39758 | W81: 10442 | X81: 0.001 | Y81: N/A | Z81: 1597.4866 | AA81: 0 | AB81: 0 | AC81: 5.75 | AD81: 7.5482991 | AE81: 32.153429 | AF81: 60.587651 | AG81: 3381.11 | AH81: 937.155 | AI81: 0.3333 | AJ81: 40029.942 | AK81: 9.3658951 | AL81: 3.7214886 | AM81: 36.059756 | AN81: 0.9963548 | AO81: 0.97662338 | AP81: 87.5 | AQ81: 9.3582888 | AR81: 0 | AS81: 37.601094 | AT81: 9.4002735 | AU81: 3.0968831 | AV81: 169.66982 | AW81: 0.6085 | AX81: 0.832 | AY81: 0.8301 | AZ81: 0.4913 | BA81: 0.0587 | BB81: 259.68844 | BC81: 261.15152 | BD81: 0.55156951 | BE81: 21.36463 | BF81: 11.736 | BG81: 71.037 | BH81: 27.528 | BI81: 129.66135 | BJ81: 0.96618357 | BK81: 3.0975497 | BL81: 10.106383 | BM81: 0 | BN81: 0.35554172 | BO81: 0.044265611 | BP81: 0.0701256 | BQ81: 0.0335703 | BR81: 15.958243 | BS81: 6.9983543 | BT81: 0.023752969 | BU81: 56.109791 | BV81: 28.644204 | BW81: 26.551695 | BX81: 5.4119231 | BY81: 44.720184 | BZ81: 37.36169 | CA81: 122.35965 | CB81: 0.025370368 | CC81: 0.39 | CD81: 27.313233 | CE81: 26.084316 | CF81: 29.979834 | CG81: 0.707 | CH81: 1 | CI81: 0 | CJ81: 0 | CK81: 0 | CL81: 0 | CM81: 0 | CN81: 0 | CO81: 0 | CP81: 166.23169
A82: Montería | B82: 2021 | C82: 165.7898 | D82: 53.695714 | E82: 0.16220759 | F82: 0.026146881 | G82: 56.902208 | H82: 40.405 | I82: 0.30917052 | J82: 14.188227 | K82: 283.9706 | L82: 8.4735242 | M82: 0.43684854 | N82: 592.7069 | O82: 0.42585551 | P82: 85.760196 | Q82: 0.97656677 | R82: 99.478614 | S82: 452.20712 | T82: 45.043661 | U82: 341.96553 | V82: 344.46002 | W82: 412501 | X82: 0.1488 | Y82: 10.16625 | Z82: 315.09686 | AA82: 0 | AB82: 0 | AC82: 12.47 | AD82: 33.224642 | AE82: 28.751742 | AF82: 61.656988 | AG82: 7434.266 | AH82: 713.781 | AI82: 1 | AJ82: 117326.38 | AK82: 37.433516 | AL82: 1.4405762 | AM82: 27.104076 | AN82: 0.89910425 | AO82: 0.84611554 | AP82: 88.105611 | AQ82: 17.791584 | AR82: 112.96244 | AS82: 28.346046 | AT82: 13.041461 | AU82: 4.7487633 | AV82: 474.93341 | AW82: 0.6146 | AX82: 0.9424 | AY82: 0.8553 | AZ82: 0.4845 | BA82: 0.0222 | BB82: 259.38036 | BC82: 250.20336 | BD82: 0.45386997 | BE82: 24.825697 | BF82: 67.902 | BG82: 187.829 | BH82: 8.521 | BI82: 138.05899 | BJ82: 10.948236 | BK82: 71.94049 | BL82: 23.370025 | BM82: 68.495607 | BN82: 0.20733054 | BO82: 0.080991764 | BP82: 0.1092625 | BQ82: 0.1315077 | BR82: 6.9167604 | BS82: 6.250702 | BT82: 0.068095839 | BU82: 58.094579 | BV82: 20.021248 | BW82: 13.325386 | BX82: 9.327838 | BY82: 61.236716 | BZ82: 42.380022 | CA82: 63.070196 | CB82: 0.024480273 | CC82: 0.67 | CD82: 29.298339 | CE82: 27.276015 | CF82: 14.084894 | CG82: 0.237 | CH82: 0.52851989 | CI82: 4.3352914 | CJ82: 433.52914 | CK82: 1.04 | CL82: 22.6 | CM82: 3.941174 | CN82: 0 | CO82: 0 | CP82: 252.23514
A83: Neiva | B83: 2021 | C83: 159.29566 | D83: 58.66125 | E83: 0.23253704 | F83: 0.021751564 | G83: 48.762922 | H83: 95.93 | I83: 0.2404943 | J83: 20.936372 | K83: 936.03873 | L83: 16.857858 | M83: 0.44865539 | N83: 566.25974 | O83: 0.64553314 | P83: 95.80959 | Q83: 0.89935364 | R83: 99.09073 | S83: 429.33419 | T83: 95.80959 | U83: 182.70198 | V83: 200.5453 | W83: 75641 | X83: 0.2282 | Y83: 9.5476806 | Z83: 709.8246 | AA83: 16.330974 | AB83: 8.1654872 | AC83: 23.7 | AD83: 26.142927 | AE83: 41.140235 | AF83: 75.008927 | AG83: 7442.698 | AH83: 1067.453 | AI83: 1.1739 | AJ83: 76816.269 | AK83: 57.56535 | AL83: 1.5606242 | AM83: 30.834356 | AN83: 0.8866562 | AO83: 0.8464704 | AP83: 95.217794 | AQ83: 7.7534406 | AR83: 77.489345 | AS83: 48.271149 | AT83: 22.631499 | AU83: 9.7457057 | AV83: 344.66861 | AW83: 0.7356 | AX83: 0.9471 | AY83: 0.8315 | AZ83: 0.4794 | BA83: 0.0284 | BB83: 269.83173 | BC83: 264.42212 | BD83: 0.6362379 | BE83: 27.009682 | BF83: 68.887 | BG83: 227.393 | BH83: 18.025 | BI83: 139.04496 | BJ83: 8.1120944 | BK83: 47.077758 | BL83: 20.697674 | BM83: 35.616062 | BN83: 0.36463224 | BO83: 0.12025859 | BP83: 0.0190888 | BQ83: 0.0262272 | BR83: 7.3413254 | BS83: 10.011393 | BT83: 0.038022814 | BU83: 59.998326 | BV83: 19.121289 | BW83: 20.73295 | BX83: 10.599125 | BY83: 63.746179 | BZ83: 81.017163 | CA83: 145.27483 | CB83: 0.033429572 | CC83: 0.65 | CD83: 29.466579 | CE83: 27.118639 | CF83: 10.001236 | CG83: 0.185 | CH83: 0.73794157 | CI83: 3.2628113 | CJ83: 304.52905 | CK83: 1.21 | CL83: 29.62 | CM83: 35.347122 | CN83: 2.7190094 | CO83: 5.4380188 | CP83: 570.99198
A84: Pasto | B84: 2021 | C84: 174.14842 | D84: 42.69375 | E84: 0.21935805 | F84: 0.023655302 | G84: 57.776275 | H84: 45.93 | I84: 0.17287671 | J84: 15.171374 | K84: 984.49014 | L84: 20.145595 | M84: 0.43702466 | N84: 485.50649 | O84: 0.54280156 | P84: 69.33467 | Q84: 0.31862653 | R84: 98.146924 | S84: 495.03607 | T84: 65.963461 | U84: 312.70343 | V84: 297.72435 | W84: 113696 | X84: 0.2264 | Y84: 11.420582 | Z84: 418.03354 | AA84: 33.115366 | AB84: 15.284015 | AC84: 20.73 | AD84: 30.68988 | AE84: 42.78149 | AF84: 72.128252 | AG84: 9085.221 | AH84: 916.656 | AI84: 1.4583 | AJ84: 46313.312 | AK84: 31.835653 | AL84: 2.8811525 | AM84: 28.330555 | AN84: 0.94512831 | AO84: 0.87048008 | AP84: 91.015895 | AQ84: 8.9285714 | AR84: 99.181751 | AS84: 50.905039 | AT84: 15.911577 | AU84: 5.5660499 | AV84: 446.77767 | AW84: 0.9331 | AX84: 0.9805 | AY84: 1 | AZ84: 0.6283 | BA84: 0.0071 | BB84: 275.41728 | BC84: 269.22276 | BD84: 0.76705491 | BE84: 23.09609 | BF84: 98.8 | BG84: 287.207 | BH84: 11.065 | BI84: 145.80368 | BJ84: 9.4386488 | BK84: 35.753201 | BL84: 25.814536 | BM84: 28.575598 | BN84: 0.34518748 | BO84: 0.17068499 | BP84: 0.0157584 | BQ84: 0.49764429 | BR84: 7.1628784 | BS84: 6.7848376 | BT84: 0.066348974 | BU84: 63.355047 | BV84: 13.445278 | BW84: 11.990428 | BX84: 9.5559332 | BY84: 72.828339 | BZ84: 52.294564 | CA84: 94.447574 | CB84: 0.029864765 | CC84: 0.54 | CD84: 29.417756 | CE84: 25.806863 | CF84: 6.878077 | CG84: 0.13 | CH84: 0.21072022 | CI84: 1.9896884 | CJ84: 579.49676 | CK84: 0.58 | CL84: 18.39 | CM84: 4.9742211 | CN84: 2.4871105 | CO84: 2.4871105 | CP84: 395.45058
A85: Pereira AM | B85: 2021 | C85: 209.03443 | D85: 68.687031 | E85: 0.32347435 | F85: 0.028001402 | G85: 54.442184 | H85: 96.378402 | I85: 0.25860324 | J85: 21.012962 | K85: 429.479 | L85: 11.673868 | M85: 0.52137757 | N85: 595.31111 | O85: 0.58302122 | P85: 75.388796 | Q85: 0.87534121 | R85: 99.23173 | S85: 478.60004 | T85: 70.138448 | U85: 409.86045 | V85: 347.31166 | W85: 597568 | X85: 0.0602 | Y85: 20.391508 | Z85: 1066.5383 | AA85: 8.1682218 | AB85: 21.781925 | AC85: 26.076329 | AD85: 28.435647 | AE85: 51.421193 | AF85: 84.527515 | AG85: 13594.539 | AH85: 1746.299 | AI85: 1.8 | AJ85: 51923.359 | AK85: 50.062935 | AL85: 3.8415366 | AM85: 31.038908 | AN85: 0.98178031 | AO85: 0.9775021 | AP85: 91.247702 | AQ85: 11.173184 | AR85: 55.834729 | AS85: 63.659469 | AT85: 26.174231 | AU85: 12.152322 | AV85: 198.68549 | AW85: 0.74390129 | AX85: 0.98932301 | AY85: 0.92987555 | AZ85: 0.54666923 | BA85: 0.027091141 | BB85: 265.85646 | BC85: 258.17862 | BD85: 0.51874181 | BE85: 26.931586 | BF85: 54.465 | BG85: 326.179 | BH85: 24.094 | BI85: 143.60751 | BJ85: 11.022682 | BK85: 48.131689 | BL85: 31.060202 | BM85: 39.502013 | BN85: 0.58413926 | BO85: 0.055475159 | BP85: 0.0262021 | BQ85: 0.0434395 | BR85: 4.5184736 | BS85: 9.5560909 | BT85: 0.068266743 | BU85: 57.976964 | BV85: 16.096527 | BW85: 30.667864 | BX85: 6.8155223 | BY85: 36.182253 | BZ85: 32.521278 | CA85: 95.750098 | CB85: 0.049902217 | CC85: 0.57 | CD85: 30.158287 | CE85: 27.769311 | CF85: 20.789789 | CG85: 0.138 | CH85: 0.2128891 | CI85: 7.1416603 | CJ85: 435.3666 | CK85: 0.93 | CL85: 30.23 | CM85: 32.961509 | CN85: 10.98717 | CO85: 21.974339 | CP85: 1424.2119
A86: Popayán | B86: 2021 | C86: 161.59614 | D86: 28.315 | E86: 0.24530662 | F86: 0.021729235 | G86: 59.894286 | H86: 51.285 | I86: 0.29664651 | J86: 21.327354 | K86: 1057.5248 | L86: 38.08456 | M86: 0.38309754 | N86: 392.2027 | O86: 0.36440678 | P86: 99.966208 | Q86: 0.8132745 | R86: 97.343409 | S86: 477.06087 | T86: 99.966208 | U86: 373.62754 | V86: 362.17027 | W86: 29415 | X86: 0.0028 | Y86: 11.545284 | Z86: 496.43986 | AA86: 21.332423 | AB86: 91.424671 | AC86: 19.45 | AD86: 28.121036 | AE86: 44.266117 | AF86: 73.673502 | AG86: 17803.79 | AH86: 1103.679 | AI86: 1.7143 | AJ86: 43416.558 | AK86: 46.725377 | AL86: 3.3613445 | AM86: 28.117544 | AN86: 0.93381818 | AO86: 0.84772561 | AP86: 89.548755 | AQ86: 9.0642495 | AR86: 53.290701 | AS86: 37.757093 | AT86: 12.618853 | AU86: 4.9268564 | AV86: 452.87378 | AW86: 0.7367 | AX86: 1 | AY86: 0.9251 | AZ86: 0.5951 | BA86: 0.0126 | BB86: 271.88213 | BC86: 262.43398 | BD86: 0.69649562 | BE86: 27.432416 | BF86: 107.987 | BG86: 447.528 | BH86: 46.965 | BI86: 141.26583 | BJ86: 12.285959 | BK86: 38.575729 | BL86: 21.932773 | BM86: 40.530374 | BN86: 0.3694668 | BO86: 0.1019889 | BP86: 0.0279216 | BQ86: 0.0421175 | BR86: 5.1185649 | BS86: 5.7370581 | BT86: 0.046733935 | BU86: 56.480205 | BV86: 19.54416 | BW86: 17.065731 | BX86: 9.0569361 | BY86: 70.686739 | BZ86: 64.104629 | CA86: 100.79092 | CB86: 0.034288768 | CC86: 0.44 | CD86: 29.21318 | CE86: 26.051072 | CF86: 11.321434 | CG86: 0.13 | CH86: 0.16891278 | CI86: 7.3122355 | CJ86: 685.52208 | CK86: 1.07 | CL86: 21.7 | CM86: 30.467648 | CN86: 3.0467648 | CO86: 9.1402944 | CP86: 414.36001
A87: Puerto Carreño | B87: 2021 | C87: 150.79975 | D87: 24.574286 | E87: 0.14500776 | F87: 0.026457305 | G87: 45.272291 | H87: 71.79 | I87: 0.0056959772 | J87: 32.803786 | K87: 399.13275 | L87: 37.490042 | M87: 0.5826087 | N87: 302.25 | O87: 0 | P87: 61.588032 | Q87: n/a | R87: 34.259801 | S87: 504.29771 | T87: 0 | U87: 241.15172 | V87: 246.94845 | W87: 16325 | X87: 0.0026 | Y87: N/A | Z87: 2057.7347 | AA87: 0 | AB87: 0 | AC87: 6.57 | AD87: 1.2013433 | AE87: 23.427662 | AF87: 52.970145 | AG87: 2001.862 | AH87: 325.885 | AI87: 1 | AJ87: 74433.655 | AK87: 32.694832 | AL87: 0 | AM87: 28.200001 | AN87: 1 | AO87: 1 | AP87: 61.803714 | AQ87: 20.009187 | AR87: 163.93443 | AS87: 88.371124 | AT87: 12.934477 | AU87: 5.2085142 | AV87: 172.46477 | AW87: 1 | AX87: 1 | AY87: 0.7374 | AZ87: 0.3138 | BA87: 0.0236 | BB87: 237 | BC87: 237 | BD87: 0.2385466 | BE87: 32.325434 | BF87: 6.897 | BG87: 9.768 | BH87: 19.704 | BI87: 132.47436 | BJ87: 0 | BK87: 0 | BL87: 3.8461538 | BM87: 0 | BN87: 0.53974895 | BO87: 0.014175249 | BP87: 0.2314768 | BQ87: 0.0349768 | BR87: 10.309761 | BS87: 6.2327194 | BT87: 0.022556391 | BU87: 58.616085 | BV87: 29.051959 | BW87: 18.817986 | BX87: 11.739065 | BY87: 47.721827 | BZ87: 57.606306 | CA87: 81.882973 | CB87: 0.018848366 | CC87: 0.4 | CD87: 25.644071 | CE87: 18.77245 | CF87: 0.50739516 | CG87: 1 | CH87: 1 | CI87: 0 | CJ87: 46.862552 | CK87: 0 | CL87: 0 | CM87: 0 | CN87: 0 | CO87: 0 | CP87: 0
A88: Quibdó | B88: 2021 | C88: 110.61129 | D88: 52.468571 | E88: 0.11978019 | F88: 0.016661326 | G88: 67.991937 | H88: 25 | I88: 0.44373866 | J88: 71.156795 | K88: 509.84139 | L88: 34.084426 | M88: 0.38764258 | N88: 357.21875 | O88: 0.49019608 | P88: 43.145533 | Q88: 0.12944822 | R88: 89.843999 | S88: 368.90119 | T88: 16.886713 | U88: 552.6122 | V88: 571.3327 | W88: 130275 | X88: 0.1176 | Y88: 21.306038 | Z88: 305.12971 | AA88: 7.5823059 | AB88: 37.91153 | AC88: 13.65 | AD88: 7.526561 | AE88: 25.807755 | AF88: 61.449661 | AG88: 5307.413 | AH88: 246.856 | AI88: 1.2727 | AJ88: 65195.853 | AK88: 12.799403 | AL88: 7.5630252 | AM88: 30.886301 | AN88: 0.97025797 | AO88: 0.88620903 | AP88: 74.982053 | AQ88: 16.943292 | AR88: 159.74441 | AS88: 30.619484 | AT88: 6.0812216 | AU88: 2.5960771 | AV88: 266.0042 | AW88: 0.7444 | AX88: 1 | AY88: 0.8441 | AZ88: 0.447 | BA88: 0.0072 | BB88: 223 | BC88: 222.33906 | BD88: 0.60348432 | BE88: 24.803484 | BF88: 102.626 | BG88: 247.612 | BH88: 7.773 | BI88: 114.44425 | BJ88: 2.5856885 | BK88: 1.105879 | BL88: 4.4247788 | BM88: 0 | BN88: 0.25747348 | BO88: 0 | BP88: 0.0569312 | BQ88: 0.0418191 | BR88: 9.4102653 | BS88: 7.3577901 | BT88: 0.017119839 | BU88: 47.272714 | BV88: 15.060516 | BW88: 11.772129 | BX88: 3.4747876 | BY88: 62.441643 | BZ88: 60.97635 | CA88: 89.77917 | CB88: 0.0078058886 | CC88: 0.34 | CD88: 28.054726 | CE88: 25.078036 | CF88: 6.006778 | CG88: 0.36 | CH88: 0.9512011 | CI88: 1.4819315 | CJ88: 266.74768 | CK88: 0 | CL88: 40 | CM88: 0 | CN88: 0 | CO88: 0 | CP88: 266.74768
A89: Riohacha | B89: 2021 | C89: 133.07515 | D89: 38.6925 | E89: 0.07493135 | F89: 0.013238877 | G89: 31.601158 | H89: 53.55 | I89: 0.21068702 | J89: 24.261598 | K89: 585.61527 | L89: 21.350206 | M89: 0.30102116 | N89: 294.37143 | O89: 0.46428571 | P89: 81.659328 | Q89: 0.8472611 | R89: 67.669987 | S89: 530.20196 | T89: 81.659328 | U89: 334.27602 | V89: 369.90283 | W89: 78523 | X89: 0.1142 | Y89: N/A | Z89: 978.27616 | AA89: 0 | AB89: 14.532419 | AC89: 12 | AD89: 23.99139 | AE89: 21.274722 | AF89: 63.880453 | AG89: 4023.277 | AH89: 351.159 | AI89: 1.3 | AJ89: 94939.138 | AK89: 28.931876 | AL89: 1.8007203 | AM89: 30.770971 | AN89: 0.9383475 | AO89: 0.85391621 | AP89: 67.462039 | AQ89: 19.506301 | AR89: 222.64631 | AS89: 30.775869 | AT89: 11.316641 | AU89: 3.744553 | AV89: 209.07753 | AW89: 0.9202 | AX89: 1 | AY89: 0.8225 | AZ89: 0.405 | BA89: 0.0053 | BB89: 241 | BC89: 232.19264 | BD89: 0.22285126 | BE89: 26.972723 | BF89: 52.988 | BG89: 125.162 | BH89: 13.018 | BI89: 131.60758 | BJ89: 12.147505 | BK89: 5.1683998 | BL89: 13.181818 | BM89: 32.748538 | BN89: 0.22133832 | BO89: 0.091473878 | BP89: 0.0586722 | BQ89: 0.0248476 | BR89: 8.1033738 | BS89: 4.7018977 | BT89: 0.027863777 | BU89: 59.284431 | BV89: 15.810645 | BW89: 9.0347767 | BX89: 18.007712 | BY89: 78.863363 | BZ89: 52.11039 | CA89: 73.438484 | CB89: 0.018099153 | CC89: 0.27 | CD89: 28.45236 | CE89: 27.691074 | CF89: 62.926918 | CG89: 0.19 | CH89: 0.98432969 | CI89: 5.8227836 | CJ89: 548.31212 | CK89: 0.56 | CL89: 19.05 | CM89: 4.8523197 | CN89: 9.7046393 | CO89: 9.7046393 | CP89: 164.97887
A90: San Andrés | B90: 2021 | C90: 149.3141 | D90: 71.24 | E90: 0.35424211 | F90: 0.037128662 | G90: 48.410482 | H90: 55.95 | I90: 0.44179793 | J90: 67.923854 | K90: 515.38314 | L90: 16.087229 | M90: 0.37786378 | N90: 230.86364 | O90: 0.71428571 | P90: 20.26997 | Q90: n/a | R90: 100 | S90: 456.29674 | T90: 6.7211474 | U90: - | V90: - | W90: 701340 | X90: 0.2606 | Y90: N/A | Z90: 0 | AA90: 0 | AB90: 17.147953 | AC90: 5.37 | AD90: 1.4686922 | AE90: 36.909532 | AF90: 77.338454 | AG90: 8080.059 | AH90: 444.774 | AI90: 0.6667 | AJ90: 1636.4775 | AK90: 10.446308 | AL90: 3.9615846 | AM90: 28.43903 | AN90: 0.88697789 | AO90: 0.8775 | AP90: 91.073919 | AQ90: 16.759777 | AR90: 0 | AS90: 124.1024 | AT90: 32.79589 | AU90: 12.762933 | AV90: 203.71563 | AW90: 0.7963 | AX90: 0.9339 | AY90: 0.8417 | AZ90: 0.5191 | BA90: 0.0152 | BB90: 239 | BC90: 228.19337 | BD90: 0.53005464 | BE90: 23.942623 | BF90: 0.767 | BG90: 14.195 | BH90: 29.516 | BI90: 127.60952 | BJ90: 14.102564 | BK90: 3.9490446 | BL90: 40 | BM90: 81.670534 | BN90: 0.66183575 | BO90: 0 | BP90: 0.2503977 | BQ90: 0.0228667 | BR90: 15.908482 | BS90: 16.391098 | BT90: 0.081788441 | BU90: 59.781069 | BV90: 18.336999 | BW90: 47.56683 | BX90: 1.2092195 | BY90: 31.264641 | BZ90: 56.420833 | CA90: 111.72664 | CB90: 0.0040782679 | CC90: 0.3 | CD90: 27.934397 | CE90: 17.200948 | CF90: 1.8282789 | CG90: 0.27 | CH90: 0.24604323 | CI90: 0 | CJ90: 107.24819 | CK90: 0 | CL90: 0 | CM90: 0 | CN90: 0 | CO90: 0 | CP90: 2055.5903
A91: San José del Guaviare | B91: 2021 | C91: 137.39871 | D91: 43.812857 | E91: 0.14242902 | F91: 0.016026959 | G91: 45.215049 | H91: 90.7 | I91: 0.00047483381 | J91: 26.645824 | K91: 204.22788 | L91: 49.738871 | M91: 0.4006192 | N91: 541.5 | O91: 1 | P91: 27.08797 | Q91: 0.4 | R91: 89.653671 | S91: 564.47492 | T91: 27.08797 | U91: 358.26015 | V91: 487.69107 | W91: 9868 | X91: 0.02 | Y91: N/A | Z91: 2133.4423 | AA91: 0 | AB91: 0 | AC91: 3.95 | AD91: 9.9745157 | AE91: 37.631111 | AF91: 69.987768 | AG91: 6776.948 | AH91: 88.936 | AI91: 1.6667 | AJ91: 71353.706 | AK91: 20.858134 | AL91: 3.7214886 | AM91: 32.362648 | AN91: 1 | AO91: 1 | AP91: 67.715736 | AQ91: 10.183299 | AR91: 0 | AS91: 51.544076 | AT91: 10.218978 | AU91: 2.0213363 | AV91: 163.02401 | AW91: 0.5034 | AX91: 0.8533 | AY91: 0.7879 | AZ91: 0.4213 | BA91: 0.0553 | BB91: 240 | BC91: 236.30248 | BD91: 0.42392718 | BE91: 26.338101 | BF91: 12.023 | BG91: 16.565 | BH91: 27.14 | BI91: 131.22057 | BJ91: 0 | BK91: 0 | BL91: 5.6818182 | BM91: 0 | BN91: 0.34937238 | BO91: 0.11513278 | BP91: 0.2060204 | BQ91: 0.0444669 | BR91: 14.921661 | BS91: 5.3291647 | BT91: 0.013333333 | BU91: 66.796605 | BV91: 22.233082 | BW91: 19.477413 | BX91: 14.175079 | BY91: 44.760113 | BZ91: 50.725459 | CA91: 86.146715 | CB91: 0.0023741561 | CC91: 0.34 | CD91: 26.998682 | CE91: 21.845741 | CF91: 0.57823713 | CG91: 1 | CH91: 0.50683572 | CI91: 1.7763882 | CJ91: 0 | CK91: 0 | CL91: 0 | CM91: 0 | CN91: 0 | CO91: 0 | CP91: 0
A92: Santa Marta | B92: 2021 | C92: 173.06894 | D92: 78.956667 | E92: 0.2464684 | F92: 0.037804119 | G92: 56.290681 | H92: 43.895 | I92: 0.18933333 | J92: 24.33471 | K92: 501.84548 | L92: 14.714011 | M92: 0.43605278 | N92: 421.92308 | O92: 0.59333333 | P92: 20.685848 | Q92: 0.87559683 | R92: 97.489049 | S92: 400.88022 | T92: 16.953673 | U92: 173.72288 | V92: 249.9359 | W92: 772983 | X92: 0.1636 | Y92: 35.484864 | Z92: 83.473714 | AA92: 18.282238 | AB92: 31.079804 | AC92: 16.76 | AD92: 31.986942 | AE92: 32.415684 | AF92: 65.502062 | AG92: 6877.591 | AH92: 539.46 | AI92: 1.6471 | AJ92: 164687.75 | AK92: 16.08488 | AL92: 2.6410564 | AM92: 28.382429 | AN92: 0.94452688 | AO92: 0.94928033 | AP92: 73.981944 | AQ92: 9.4003241 | AR92: 107.6774 | AS92: 30.834005 | AT92: 13.225593 | AU92: 4.4319061 | AV92: 340.87618 | AW92: 0.7036 | AX92: 0.9818 | AY92: 0.8652 | AZ92: 0.5219 | BA92: 0.0571 | BB92: 247.1581 | BC92: 237.46152 | BD92: 0.38051595 | BE92: 32.940597 | BF92: 55.716 | BG92: 186.479 | BH92: 17.325 | BI92: 140.07751 | BJ92: 12.926391 | BK92: 64.415275 | BL92: 27.024922 | BM92: 53.214786 | BN92: 0.30769231 | BO92: 0.052792281 | BP92: 0.0850895 | BQ92: 0.0412927 | BR92: 11.695752 | BS92: 9.7489752 | BT92: 0.064821981 | BU92: 52.773067 | BV92: 14.662315 | BW92: 20.031957 | BX92: 9.1914531 | BY92: 63.413682 | BZ92: 45.893164 | CA92: 75.321216 | CB92: 0.017040283 | CC92: 0.62 | CD92: 29.433783 | CE92: 27.684149 | CF92: 26.729916 | CG92: 0.11 | CH92: 0.31490576 | CI92: 5.4705937 | CJ92: 431.98826 | CK92: 0.85 | CL92: 32.48 | CM92: 3.7728232 | CN92: 7.5456464 | CO92: 3.7728232 | CP92: 488.58061
A93: Sincelejo | B93: 2021 | C93: 167.57333 | D93: 43.60375 | E93: 0.19102587 | F93: 0.026857542 | G93: 58.75495 | H93: 43.16 | I93: 0.42192531 | J93: 14.23502 | K93: 558.25631 | L93: 14.23502 | M93: 0.34372556 | N93: 424.45614 | O93: 0.73225806 | P93: 80.022949 | Q93: 0.99627208 | R93: 98.673128 | S93: 469.51656 | T93: 73.939732 | U93: 339.25893 | V93: 337.11329 | W93: 21306 | X93: 0.1006 | Y93: 0 | Z93: 403.90175 | AA93: 6.7100134 | AB93: 0 | AC93: 14.37 | AD93: 25.260318 | AE93: 28.712519 | AF93: 58.86425 | AG93: 4228.41 | AH93: 685.688 | AI93: 1.5385 | AJ93: 93166.556 | AK93: 29.737949 | AL93: 1.6806723 | AM93: 25.24472 | AN93: 0.93795903 | AO93: 1 | AP93: 90.366375 | AQ93: 8.6401975 | AR93: 41.059331 | AS93: 35.840069 | AT93: 13.92787 | AU93: 5.3123672 | AV93: 518.11356 | AW93: 0.7399 | AX93: 1 | AY93: 0.88 | AZ93: 0.5088 | BA93: 0.0134 | BB93: 257 | BC93: 249.12693 | BD93: 0.54521277 | BE93: 28.419681 | BF93: 79.528 | BG93: 98.383 | BH93: 13.837 | BI93: 136.22969 | BJ93: 7.4300699 | BK93: 3.19348 | BL93: 16.469038 | BM93: 46.150622 | BN93: 0.25863284 | BO93: 0.095652174 | BP93: 0.0234135 | BQ93: 0.065118 | BR93: 7.4564391 | BS93: 6.3210268 | BT93: 0.048793566 | BU93: 59.279719 | BV93: 15.859365 | BW93: 12.487965 | BX93: 11.895817 | BY93: 70.471009 | BZ93: 49.677608 | CA93: 73.123875 | CB93: 0.013842198 | CC93: 0.43 | CD93: 28.912873 | CE93: 28.245675 | CF93: 51.97679 | CG93: 0.29 | CH93: 0.98165123 | CI93: 4.0671486 | CJ93: 542.28648 | CK93: 0.59 | CL93: 30.84 | CM93: 3.3892905 | CN93: 0 | CO93: 0 | CP93: 183.02169
A94: Tunja | B94: 2021 | C94: 194.83091 | D94: 77.376667 | E94: 0.44719238 | F94: 0.029960766 | G94: 48.951379 | H94: 55.43 | I94: 0.28424089 | J94: 4.4641612 | K94: 482.53125 | L94: 21.762786 | M94: 0.42532424 | N94: 289.62162 | O94: 0.64808362 | P94: 92.840528 | Q94: 0.99919129 | R94: 99.490251 | S94: 444.30934 | T94: 90.95431 | U94: 403.24588 | V94: 309.89188 | W94: N/A | X94: NA | Y94: 5.8492769 | Z94: 487.4306 | AA94: 38.766559 | AB94: 60.918878 | AC94: 25.8 | AD94: 35.430926 | AE94: 47.805259 | AF94: 76.247644 | AG94: 19986.732 | AH94: 2110.85 | AI94: 2.6667 | AJ94: 34842.57 | AK94: 42.048325 | AL94: 0.6002401 | AM94: 29.995695 | AN94: 0.88893234 | AO94: 0.91893039 | AP94: 90.307763 | AQ94: 5.842259 | AR94: 48.685492 | AS94: 55.906001 | AT94: 15.342535 | AU94: 5.726607 | AV94: 325.22049 | AW94: 0.8466 | AX94: 1 | AY94: 0.9815 | AZ94: 0.5519 | BA94: 0.0207 | BB94: 284 | BC94: 274.88251 | BD94: 0.82129743 | BE94: 30.777234 | BF94: 147.86849 | BG94: 792.84739 | BH94: 49.365 | BI94: 147.86849 | BJ94: 13.865546 | BK94: 65.050486 | BL94: 30.989273 | BM94: 2.5477707 | BN94: 0.51751775 | BO94: 0.083204932 | BP94: 0.0148993 | BQ94: 0.0354844 | BR94: 17.298624 | BS94: 11.444993 | BT94: 0.030229157 | BU94: 52.526404 | BV94: 14.720188 | BW94: 25.875142 | BX94: 8.6744819 | BY94: 56.745322 | BZ94: 95.338341 | CA94: 140.65472 | CB94: 0.054322512 | CC94: 0.54 | CD94: 28.96901 | CE94: 25.88354 | CF94: 6.3844375 | CG94: 0.32 | CH94: 0.71017768 | CI94: 16.182584 | CJ94: 1044.2393 | CK94: 0.86 | CL94: 26.14 | CM94: 33.481209 | CN94: 11.160403 | CO94: 16.740604 | CP94: 1004.4363
A95: Valledupar | B95: 2021 | C95: 176.99943 | D95: 19.667143 | E95: 0.22267197 | F95: 0.028010648 | G95: 63.731611 | H95: 52.565 | I95: 0.38360942 | J95: 12.541854 | K95: 440.74933 | L95: 14.062078 | M95: 0.39985636 | N95: 589.60294 | O95: 0.88043478 | P95: 87.950221 | Q95: 0.89357868 | R95: 97.538753 | S95: 410.40609 | T95: 87.950221 | U95: 254.74167 | V95: 259.64908 | W95: 131132 | X95: 0.1282 | Y95: 3.6485196 | Z95: 467.37408 | AA95: 3.6755652 | AB95: 9.188913 | AC95: 15.35 | AD95: 32.280677 | AE95: 32.025988 | AF95: 72.015974 | AG95: 6705.992 | AH95: 387.043 | AI95: 1.4118 | AJ95: 110506.14 | AK95: 41.095987 | AL95: 3.4813926 | AM95: 27.576504 | AN95: 0.92883855 | AO95: 0.92896649 | AP95: 85.953899 | AQ95: 12.942638 | AR95: 123.38063 | AS95: 46.14542 | AT95: 17.018883 | AU95: 6.4682602 | AV95: 452.75783 | AW95: 0.592 | AX95: 0.8609 | AY95: 0.7589 | AZ95: 0.4742 | BA95: 0.0125 | BB95: 256.69416 | BC95: 246.43302 | BD95: 0.38391801 | BE95: 33.532125 | BF95: 49.618 | BG95: 321.403 | BH95: 17.173 | BI95: 139.10741 | BJ95: 11.292346 | BK95: 1.3789006 | BL95: 21.7958 | BM95: 67.039861 | BN95: 0.33266444 | BO95: 0.038616248 | BP95: 0.0900724 | BQ95: 0.0117954 | BR95: 8.5892695 | BS95: 6.4324507 | BT95: 0.049630724 | BU95: 52.887848 | BV95: 18.470736 | BW95: 17.504209 | BX95: 8.4919595 | BY95: 61.90908 | BZ95: 36.209542 | CA95: 62.734143 | CB95: 0.01834958 | CC95: 0.55 | CD95: 29.340131 | CE95: 28.631408 | CF95: 55.417771 | CG95: 0.09 | CH95: 0.95753982 | CI95: 1.5202247 | CJ95: 150.12219 | CK95: 0.57 | CL95: 10 | CM95: 0 | CN95: 0 | CO95: 1.9002809 | CP95: 150.12219
A96: Villavicencio | B96: 2021 | C96: 166.40696 | D96: 45.861429 | E96: 0.26688908 | F96: 0.018881239 | G96: 42.539696 | H96: 42.95 | I96: 0.14250914 | J96: 17.88912 | K96: 809.27633 | L96: 26.743331 | M96: 0.4091915 | N96: 550.5 | O96: 0.63141524 | P96: 48.522099 | Q96: 0.9260838 | R96: 98.196289 | S96: 424.85113 | T96: 50.551101 | U96: 313.08912 | V96: 223.13975 | W96: 48471 | X96: 0.1714 | Y96: 10.991006 | Z96: 970.43958 | AA96: 1.8184397 | AB96: 0 | AC96: 19.8 | AD96: 39.698131 | AE96: 42.738748 | AF96: 80.937944 | AG96: 3359.761 | AH96: 376.949 | AI96: 1.2273 | AJ96: 113420.21 | AK96: 29.283608 | AL96: 2.8811525 | AM96: 33.017136 | AN96: 0.93824104 | AO96: 0.86794171 | AP96: 84.608209 | AQ96: 10.372899 | AR96: 65.59958 | AS96: 46.33874 | AT96: 13.982951 | AU96: 5.3233176 | AV96: 295.61601 | AW96: 0.6604 | AX96: 0.9162 | AY96: 0.8467 | AZ96: 0.511 | BA96: 0.0151 | BB96: 262.61268 | BC96: 263.26564 | BD96: 0.70847458 | BE96: 30.482486 | BF96: 44.984 | BG96: 148.843 | BH96: 11.305 | BI96: 140.28106 | BJ96: 10.671937 | BK96: 18.998032 | BL96: 20.360825 | BM96: 71.173013 | BN96: 0.46508779 | BO96: 0.078014184 | BP96: 0.0148065 | BQ96: 0.0778745 | BR96: 13.859551 | BS96: 10.390145 | BT96: 0.043478261 | BU96: 59.621958 | BV96: 21.697782 | BW96: 26.250186 | BX96: 8.5942995 | BY96: 42.872763 | BZ96: 64.805065 | CA96: 86.760701 | CB96: 0.023162349 | CC96: 0.52 | CD96: 29.764915 | CE96: 27.241681 | CF96: 8.6039824 | CG96: 0.77 | CH96: 0.94605004 | CI96: 0.72279273 | CJ96: 222.25876 | CK96: 0.54 | CL96: 16.21 | CM96: 7.2279273 | CN96: 5.4209454 | CO96: 5.4209454 | CP96: 390.30807
A97: Yopal | B97: 2021 | C97: 176.81857 | D97: 44.8925 | E97: 0.29309341 | F97: 0.015056394 | G97: 33.106682 | H97: 70.93 | I97: 0.16153295 | J97: 20.538326 | K97: 857.12035 | L97: 25.534135 | M97: 0.3738588 | N97: 367.56667 | O97: 0.44578313 | P97: 51.851058 | Q97: 0.97737802 | R97: 96.46519 | S97: 448.97555 | T97: 52.282722 | U97: 186.1651 | V97: 221.00684 | W97: 85770 | X97: 0.0312 | Y97: N/A | Z97: 1206.5434 | AA97: 5.5755346 | AB97: 0 | AC97: 19.88 | AD97: 24.259124 | AE97: 43.496832 | AF97: 75.662099 | AG97: 6276.228 | AH97: 506.048 | AI97: 1.0667 | AJ97: 43625.779 | AK97: 39.357024 | AL97: 1.0804322 | AM97: 34.13717 | AN97: 0.94151834 | AO97: 0.93735934 | AP97: 85.344484 | AQ97: 10.15625 | AR97: 192.67823 | AS97: 50.638962 | AT97: 12.851384 | AU97: 4.937637 | AV97: 237.49493 | AW97: 0.8222 | AX97: 0.9946 | AY97: 0.9032 | AZ97: 0.5351 | BA97: 0.0249 | BB97: 264.93173 | BC97: 261.12594 | BD97: 0.67439934 | BE97: 28.777133 | BF97: 42.742 | BG97: 114.625 | BH97: 16.209 | BI97: 140.78462 | BJ97: 3.5 | BK97: 14.916302 | BL97: 17.802198 | BM97: 15.471551 | BN97: 0.50711864 | BO97: 0.10421598 | BP97: 0.0651126 | BQ97: 0.019376 | BR97: 10.158145 | BS97: 12.916942 | BT97: 0.040825097 | BU97: 65.92909 | BV97: 11.628294 | BW97: 25.741419 | BX97: 7.0444084 | BY97: 44.071159 | BZ97: 81.785048 | CA97: 95.540972 | CB97: 0.011069239 | CC97: 0.22 | CD97: 29.280821 | CE97: 28.117887 | CF97: 32.612751 | CG97: 0.59 | CH97: 0.99097705 | CI97: 0 | CJ97: 72.161687 | CK97: 0 | CL97: 0 | CM97: 0 | CN97: 0 | CO97: 11.101798 | CP97: 383.01203
A98: Arauca | B98: 2022 | C98: 127.41789 | D98: 21.032857 | E98: 0.19521374 | F98: 0.01799866 | G98: 40.331096 | H98: 37.82 | I98: 0.15455861 | J98: 61.695475 | K98: 439.76882 | L98: 55.421359 | M98: 0.4128041 | N98: 328.38889 | O98: 0.64044944 | P98: 48.089586 | Q98: n/a | R98: 95.038491 | S98: 486.91863 | T98: 47.935733 | U98: 419.02455 | V98: 451.54299 | W98: 134517 | X98: 0.0058 | Y98: N/A | Z98: 1921.6572 | AA98: 0 | AB98: 0 | AC98: 11.3 | AD98: 11.964087 | AE98: 23.649124 | AF98: 74.874481 | AG98: 600.99 | AH98: 259.251 | AI98: 0.2857 | AJ98: 43202.422 | AK98: 41.417615 | AL98: 0 | AM98: 28.831922 | AN98: 0.9434 | AO98: 0.8947 | AP98: 75.32 | AQ98: 13.552068 | AR98: 0 | AS98: 64.529649 | AT98: 12.506777 | AU98: 4.2243636 | AV98: 263.2561 | AW98: 0.5966 | AX98: 0.9732 | AY98: 0.7839 | AZ98: 0.4215 | BA98: 0.038 | BB98: 246 | BC98: 241.2984 | BD98: 0.52326498 | BE98: 26.196372 | BF98: 12.166 | BG98: 57.493 | BH98: 4.014 | BI98: 132.65483 | BJ98: 50 | BK98: 4.1355932 | BL98: 16.393443 | BM98: 79.150579 | BN98: 0.34760705 | BO98: 0.080581801 | BP98: 0.0779343 | BQ98: 0.0484244 | BR98: 11.18884 | BS98: 7.8008177 | BT98: 0.033512064 | BU98: 47.614601 | BV98: 27.756263 | BW98: 27.780384 | BX98: 4.4858161 | BY98: 61.725262 | BZ98: 57.577052 | CA98: 92.115411 | CB98: 0.00077601805 | CC98: 0.18277484 | CD98: 28.083734 | CE98: 25.805943 | CF98: 9.3274724 | CG98: 0.355 | CH98: 0.36975062 | CI98: 0 | CJ98: 83.654882 | CK98: 0 | CL98: 0 | CM98: 0 | CN98: 0 | CO98: 0 | CP98: 135.93918
A99: Armenia | B99: 2022 | C99: 185.30739 | D99: 53.9325 | E99: 0.27006818 | F99: 0.029043607 | G99: 49.79889 | H99: 42.44 | I99: 0.3071338 | J99: 33.147358 | K99: 728.45041 | L99: 12.471283 | M99: 0.57800718 | N99: 366.36957 | O99: 0.23629243 | P99: 83.313186 | Q99: 0.93691304 | R99: 99.466699 | S99: 464.58541 | T99: 75.33599 | U99: 571.70068 | V99: 477.90117 | W99: 330513 | X99: 0.2506 | Y99: 15.883562 | Z99: 222.87496 | AA99: 9.5984335 | AB99: 12.797911 | AC99: 29.26 | AD99: 67.963786 | AE99: 45.830568 | AF99: 76.753015 | AG99: 12562.318 | AH99: 1383.337 | AI99: 0.95 | AJ99: 60975.476 | AK99: 58.193487 | AL99: 0.97751711 | AM99: 31.269909 | AN99: 0.8397 | AO99: 0.858 | AP99: 87 | AQ99: 11.063526 | AR99: 35.688794 | AS99: 60.653492 | AT99: 22.329963 | AU99: 10.393126 | AV99: 295.01107 | AW99: 0.7412 | AX99: 0.9164 | AY99: 0.8849 | AZ99: 0.609 | BA99: 0.0671 | BB99: 266.91185 | BC99: 257.57433 | BD99: 0.64133166 | BE99: 24.101131 | BF99: 81.49 | BG99: 182.518 | BH99: 40.102 | BI99: 145.23976 | BJ99: 10.205279 | BK99: 53.856383 | BL99: 42.053523 | BM99: 77.123696 | BN99: 0.54808227 | BO99: 0.023798861 | BP99: 0.199021 | BQ99: 0.0361781 | BR99: 18.017722 | BS99: 9.6488349 | BT99: 0.058163265 | BU99: 51.261827 | BV99: 13.728304 | BW99: 52.750001 | BX99: 5.233306 | BY99: 39.136409 | BZ99: 49.784936 | CA99: 118.10892 | CB99: 0.042785121 | CC99: 0.64904268 | CD99: 28.973752 | CE99: 27.024397 | CF99: 16.065209 | CG99: 0.156 | CH99: 0.7970167 | CI99: 3.2819166 | CJ99: 617.00033 | CK99: 0.99 | CL99: 17.11 | CM99: 62.356416 | CN99: 17.156735 | CO99: 16.409583 | CP99: 1132.2612
A100: Barranquilla AM | B100: 2022 | C100: 198.49077 | D100: 71.188127 | E100: 0.30629335 | F100: 0.055212497 | G100: 54.692174 | H100: 49.067451 | I100: 0.53507366 | J100: 30.484936 | K100: 823.59413 | L100: 10.025247 | M100: 0.39276853 | N100: 302.50588 | O100: 0.49336243 | P100: 94.870473 | Q100: 0.88787936 | R100: 99.908668 | S100: 453.52985 | T100: 86.269199 | U100: 293.53328 | V100: 325.2761 | W100: 2138336 | X100: 0.3256 | Y100: 19.097487 | Z100: 611.80606 | AA100: 6.0072718 | AB100: 10.01212 | AC100: 18.838553 | AD100: 75.314948 | AE100: 40.781955 | AF100: 76.981613 | AG100: 6839.808 | AH100: 1297.654 | AI100: 1.8182 | AJ100: 123271.85 | AK100: 54.980728 | AL100: 6.5493646 | AM100: 28.368488 | AN100: 0.96983892 | AO100: 0.9477717 | AP100: 80.489826 | AQ100: 15.15949 | AR100: 133.37077 | AS100: 66.756609 | AT100: 29.839453 | AU100: 11.798605 | AV100: 291.77085 | AW100: 0.64428019 | AX100: 0.9184964 | AY100: 0.84290317 | AZ100: 0.54446127 | BA100: 0.013316356 | BB100: 252.54077 | BC100: 245.07254 | BD100: 0.49964945 | BE100: 29.725987 | BF100: 53.725 | BG100: 398.895 | BH100: 20.181 | BI100: 141.39858 | BJ100: 14.203779 | BK100: 54.004543 | BL100: 41.41252 | BM100: 64.022956 | BN100: 0.43941859 | BO100: 0.15253896 | BP100: 0.0216996 | BQ100: 0.0515975 | BR100: 22.070889 | BS100: 14.566787 | BT100: 0.061835036 | BU100: 61.456883 | BV100: 14.531743 | BW100: 40.346409 | BX100: 12.533665 | BY100: 51.44792 | BZ100: 40.946118 | CA100: 91.802708 | CB100: 0.041953112 | CC100: 0.86826953 | CD100: 31.200775 | CE100: 28.932334 | CF100: 29.93535 | CG100: 0.127 | CH100: 0.055347715 | CI100: 7.0585925 | CJ100: 690.51448 | CK100: 1.52 | CL100: 20.47 | CM100: 16.879243 | CN100: 6.6493987 | CO100: 8.6953675 | CP100: 1284.8684
...

Sheet Valor_normalizado
A1: Ciudad o AM | B1: Año edición | C1: INS-1-1 | D1: INS-1-2 | E1: INS-1 | F1: INS-2-1 | G1: INS-2-2 | H1: INS-2-3 | I1: INS-2 | J1: INS-3-1 | K1: INS-3-2 | L1: INS-3 | M1: INS-4-1 | N1: INS-4-2 | O1: INS-4-3 | P1: INS-4-4 | Q1: INS-4-5 | R1: INS-4-6 | S1: INS-4 | T1: INS | U1: INF-1-1 | V1: INF-1-2 | W1: INF-1-3 | X1: INF-1-4 | Y1: INF-1-5 | Z1: INF-1 | AA1: INF-2-1 | AB1: INF-2-2 | AC1: INF-2-3 | AD1: INF-2-4 | AE1: INF-2-5 | AF1: INF-2 | AG1: INF-3-1 | AH1: INF-3-2 | AI1: INF-3-3 | AJ1: INF-3 | AK1: INF | AL1: TIC-1-1 | AM1: TIC-1-2 | AN1: TIC-1-3 | AO1: TIC-1-4 | AP1: TIC-1 | AQ1: TIC-2-1 | AR1: TIC-2-2 | AS1: TIC-2-3 | AT1: TIC-2 | AU1: TIC | AV1: AMB-1-1 | AW1: AMB-1-2 | AX1: AMB-1 | AY1: AMB-2-1 | AZ1: AMB-2-2 | BA1: AMB-2 | BB1: AMB | BC1: SAL-1-1 | BD1: SAL-1-2 | BE1: SAL-1-3 | BF1: SAL-1 | BG1: SAL-2-1 | BH1: SAL-2-2 | BI1: SAL-2 | BJ1: SAL-3-1 | BK1: SAL-3-2 | BL1: SAL-3-3 | BM1: SAL-3-4 | BN1: SAL-3 | BO1: SAL | BP1: EDU-1-1 | BQ1: EDU-1-2 | BR1: EDU-1-3 | BS1: EDU-1-4 | BT1: EDU-1-5 | BU1: EDU-1 | BV1: EDU-2-1 | BW1: EDU-2-2 | BX1: EDU-2-3 | BY1: EDU-2-4 | BZ1: EDU-2 | CA1: EDU | CB1: EDS-1-1 | CC1: EDS-1-2 | CD1: EDS-1-3 | CE1: EDS-1 | CF1: EDS-2-1 | CG1: EDS-2-2 | CH1: EDS-2-3 | CI1: EDS-2-4 | CJ1: EDS-2 | CK1: EDS-3-1 | CL1: EDS-3-2 | CM1: EDS-3 | CN1: EDS | CO1: NEG-1-1 | CP1: NEG-1-2 | CQ1: NEG-1-3 | CR1: NEG-1 | CS1: NEG-2-1 | CT1: NEG-2-2 | CU1: NEG-2-3 | CV1: NEG-2 | CW1: NEG | CX1: LAB-1-1 | CY1: LAB-1-2 | CZ1: LAB-1-3 | DA1: LAB-1-4 | DB1: LAB-1-5 | DC1: LAB | DD1: FIN-1-1 | DE1: FIN-1-2 | DF1: FIN-1-3 | DG1: FIN-1-4 | DH1: FIN | DI1: TAM-1-1 | DJ1: TAM-1 | DK1: TAM-2-1 | DL1: TAM-2-2 | DM1: TAM-2 | DN1: TAM | DO1: SOF-1-1 | DP1: SOF-1-2 | DQ1: SOF | DR1: INN-1-1 | DS1: INN-1-2 | DT1: INN-1-3 | DU1: INN-1-4 | DV1: INN-1 | DW1: INN-2-1 | DX1: INN-2-2 | DY1: INN-2-3 | DZ1: INN-2-4 | EA1: INN-2 | EB1: INN | EC1: Puntaje general
A2: Arauca | B2: 2019 | C2: 3.2753099 | D2: 1.3128225 | E2: 2.2940662 | F2: 2.0588323 | G2: 1.2233113 | H2: 7.1377288 | I2: 3.4732908 | J2: 2.0586695 | K2: 0.72591526 | L2: 1.3922924 | M2: 5.549348 | N2: 6.3885379 | O2: 2.8507765 | P2: 5.7736192 | Q2: 2.4028182 | R2: 5.8181818 | S2: 4.7972136 | T2: 2.9892157 | U2: 3.7672557 | V2: NA | W2: 9.3511682 | X2: 7.462969 | Y2: 4.737097 | Z2: 6.3296225 | AA2: 9.4824316 | AB2: 9.4569323 | AC2: 0.064316643 | AD2: 1.7316569 | AE2: NA | AF2: 5.1838343 | AG2: 5.1145487 | AH2: 0 | AI2: 0 | AJ2: 1.7048496 | AK2: 4.4061021 | AL2: 2.5795865 | AM2: 0.26550274 | AN2: 2.081354 | AO2: 5.3884558 | AP2: 2.5787248 | AQ2: 0.45428784 | AR2: 1.0945118 | AS2: 1.4772794 | AT2: 1.008693 | AU2: 1.7937089 | AV2: 7.9833928 | AW2: 4.0907159 | AX2: 6.0370544 | AY2: 0 | AZ2: 3.1122028 | BA2: 1.5561014 | BB2: 3.7965779 | BC2: 10 | BD2: 8.695968 | BE2: 7.9367953 | BF2: 8.8775878 | BG2: 7.2902414 | BH2: 8.8050217 | BI2: 8.0476315 | BJ2: 2.4544015 | BK2: 1.9137029 | BL2: 1.860571 | BM2: 3.4312488 | BN2: 2.414981 | BO2: 6.4467334 | BP2: 4.4358578 | BQ2: 9.081448 | BR2: 6.3230606 | BS2: 5.3802315 | BT2: 7.5872093 | BU2: 6.5615614 | BV2: 5.1898734 | BW2: 5.1877562 | BX2: 5.3052677 | BY2: 6.3361438 | BZ2: 5.5047603 | CA2: 6.0331609 | CB2: 1.025645 | CC2: 0.12178048 | CD2: 2.0562452 | CE2: 1.0678902 | CF2: 6.0383371 | CG2: 6.0606061 | CH2: 0.14624953 | CI2: 1.1397479 | CJ2: 3.3462352 | CK2: 0 | CL2: 3.4724159 | CM2: 1.7362079 | CN2: 2.0501111 | CO2: 2.0467338 | CP2: 8.2919215 | CQ2: 9.0201771 | CR2: 6.4529441 | CS2: 1.2631524 | CT2: 2.118976 | CU2: 4.5990678 | CV2: 2.6603987 | CW2: 4.5566714 | CX2: 3.8404685 | CY2: 2.6294319 | CZ2: 4.7199402 | DA2: 4.0937297 | DB2: 4.9641182 | DC2: 4.0495377 | DD2: 1.7417123 | DE2: 2.656682 | DF2: 0.39466357 | DG2: 1.3794758 | DH2: 1.5431334 | DI2: 3.2580075 | DJ2: 3.2580075 | DK2: 8.1837155 | DL2: 2.9498228 | DM2: 5.5667691 | DN2: 4.4123883 | DO2: 7.2944015 | DP2: 0.02482733 | DQ2: 3.6596144 | DR2: 0 | DS2: 0.093869546 | DT2: 0 | DU2: 0 | DV2: 0.023467387 | DW2: 0 | DX2: 0 | DY2: 0 | DZ2: 0.22262824 | EA2: 0.055657061 | EB2: 0.039562224 | EC2: 3.5212706
A3: Armenia | B3: 2019 | C3: 7.9765414 | D3: 5.3306263 | E3: 6.6535838 | F3: 4.8396846 | G3: 4.015429 | H3: 7.7230459 | I3: 5.5260532 | J3: 2.6636983 | K3: 3.9631976 | L3: 3.313448 | M3: 5.9447483 | N3: 6.6774197 | O3: 8.579843 | P3: 8.1814414 | Q3: 5.5589451 | R3: 2.0596511 | S3: 6.1670081 | T3: 5.4150233 | U3: 10 | V3: 7.9118198 | W3: 9.8777582 | X3: 8.0219171 | Y3: 9.9998082 | Z3: 9.1622607 | AA3: 8.5334738 | AB3: 8.8411664 | AC3: 0.2332874 | AD3: 3.8421136 | AE3: 4.6605475 | AF3: 5.2221177 | AG3: 0.61104133 | AH3: 2.2699071 | AI3: 1.4264237 | AJ3: 1.4357907 | AK3: 5.2733897 | AL3: 8.03085 | AM3: 0.45331118 | AN3: 5.5787721 | AO3: 6.7736506 | AP3: 5.209146 | AQ3: 3.6540714 | AR3: 3.4409141 | AS3: 3.5764935 | AT3: 3.5571597 | AU3: 4.3831528 | AV3: 6.5310107 | AW3: 2.3918078 | AX3: 4.4614093 | AY3: 1.5686275 | AZ3: 4.36897 | BA3: 2.9687987 | BB3: 3.715104 | BC3: 9.4779256 | BD3: 8.40043 | BE3: 9.8444537 | BF3: 9.2409364 | BG3: 7.6911382 | BH3: 8.76561 | BI3: 8.2283741 | BJ3: 7.0346176 | BK3: 3.6431369 | BL3: 3.3386318 | BM3: 5.9780353 | BN3: 4.9986054 | BO3: 7.4893053 | BP3: 6.2892839 | BQ3: 8.7737557 | BR3: 8.5152573 | BS3: 8.5164737 | BT3: 6.3081395 | BU3: 7.680582 | BV3: 6.9620253 | BW3: 6.8332172 | BX3: 6.1925362 | BY3: 7.7360039 | BZ3: 6.9309457 | CA3: 7.3057638 | CB3: 3.2700091 | CC3: 0.60635518 | CD3: 7.6660355 | CE3: 3.8474666 | CF3: 8.4282837 | CG3: 0.84020416 | CH3: 5.0380381 | CI3: 5.5426112 | CJ3: 4.9622843 | CK3: 5.9871383 | CL3: 5.567063 | CM3: 5.7771006 | CN3: 4.8622838 | CO3: 0.47513462 | CP3: 9.3656006 | CQ3: 8.7995533 | CR3: 6.2134295 | CS3: 3.1104711 | CT3: 2.5692497 | CU3: 7.5161349 | CV3: 4.3986186 | CW3: 5.306024 | CX3: 3.5304966 | CY3: 5.3576163 | CZ3: 5.8313073 | DA3: 4.0244035 | DB3: 5.6072049 | DC3: 4.8702057 | DD3: 0.8058775 | DE3: 4.9828172 | DF3: 3.7584586 | DG3: 4.3204951 | DH3: 3.4669121 | DI3: 4.170829 | DJ3: 4.170829 | DK3: 8.1244028 | DL3: 1.5337213 | DM3: 4.8290621 | DN3: 4.4999455 | DO3: 8.2075137 | DP3: 0.99075528 | DQ3: 4.5991345 | DR3: 1.3058107 | DS3: 3.4561929 | DT3: 7.2197309 | DU3: 3.5420799 | DV3: 3.8809536 | DW3: 3.2594324 | DX3: 4.7066517 | DY3: 2.054473 | DZ3: 1.7910709 | EA3: 2.952907 | EB3: 3.4169303 | EC3: 4.969475
A4: Barranquilla AM | B4: 2019 | C4: 6.8042734 | D4: 7.4379356 | E4: 7.1211045 | F4: 5.7601495 | G4: 5.1110668 | H4: 9.3071495 | I4: 6.7261219 | J4: 3.5316201 | K4: 2.8163933 | L4: 3.1740067 | M4: 6.4305442 | N4: 6.671547 | O4: 9.1738064 | P4: 6.1600951 | Q4: 3.1600071 | R4: 4.5842789 | S4: 6.0300465 | T4: 5.7628199 | U4: 9.3145165 | V4: 8.7693374 | W4: 9.9519707 | X4: 8.8061072 | Y4: 8.6178068 | Z4: 9.0919477 | AA4: 9.5976453 | AB4: 9.6600631 | AC4: 1.5269546 | AD4: 5.0262613 | AE4: 5.5249622 | AF4: 6.2671773 | AG4: 1.4146227 | AH4: 1.328204 | AI4: 1.1381613 | AJ4: 1.2936627 | AK4: 5.5509292 | AL4: 4.4989081 | AM4: 0.61528464 | AN4: 6.1538251 | AO4: 7.4311811 | AP4: 4.6747997 | AQ4: 2.625231 | AR4: 2.700072 | AS4: 6.7644626 | AT4: 4.0299219 | AU4: 4.3523608 | AV4: 4.4232379 | AW4: 1.7410537 | AX4: 3.0821458 | AY4: 3.7254902 | AZ4: 2.8733054 | BA4: 3.2993978 | BB4: 3.1907718 | BC4: 9.6548722 | BD4: 9.5829423 | BE4: 9.354904 | BF4: 9.5309062 | BG4: 6.371533 | BH4: 8.5711638 | BI4: 7.4713484 | BJ4: 2.9934348 | BK4: 5.2614554 | BL4: 4.0563363 | BM4: 5.4753044 | BN4: 4.4466327 | BO4: 7.1496291 | BP4: 5.3613082 | BQ4: 7.9909277 | BR4: 6.8724789 | BS4: 7.5779202 | BT4: 9.497338 | BU4: 7.4599946 | BV4: 5.2212339 | BW4: 5.2393093 | BX4: 4.1669972 | BY4: 4.657801 | BZ4: 4.8213354 | CA4: 6.140665 | CB4: 2.8070964 | CC4: 2.6718278 | CD4: 4.5171471 | CE4: 3.3320238 | CF4: 7.9011249 | CG4: 1.7860105 | CH4: 5.5505394 | CI4: 6.3514892 | CJ4: 5.397291 | CK4: 4.2440221 | CL4: 4.6741014 | CM4: 4.4590617 | CN4: 4.3961255 | CO4: 2.7642276 | CP4: 9.6940806 | CQ4: 8.8739454 | CR4: 7.1107512 | CS4: 6.2822714 | CT4: 5.1584695 | CU4: 7.3493694 | CV4: 6.2633701 | CW4: 6.6870607 | CX4: 4.4371447 | CY4: 8.2789861 | CZ4: 4.6073329 | DA4: 3.1358821 | DB4: 5.8506076 | DC4: 5.2619907 | DD4: 1.7860194 | DE4: 3.0530333 | DF4: 4.1613159 | DG4: 6.857821 | DH4: 3.9645474 | DI4: 6.6448755 | DJ4: 6.6448755 | DK4: 8.7616951 | DL4: 3.4423645 | DM4: 6.1020298 | DN4: 6.3734526 | DO4: 9.4564831 | DP4: 9.8442722 | DQ4: 9.6503777 | DR4: 3.0419735 | DS4: 3.8209438 | DT4: 7.309417 | DU4: 3.060357 | DV4: 4.3081729 | DW4: 1.7717155 | DX4: 1.3431464 | DY4: 0.40202674 | DZ4: 2.5812618 | EA4: 1.5245376 | EB4: 2.9163552 | EC4: 5.4920835
A5: Bogotá D.C. | B5: 2019 | C5: 7.4915229 | D5: 9.9676374 | E5: 8.7295802 | F5: 10 | G5: 5.5590518 | H5: 9.013658 | I5: 8.1909033 | J5: 3.4199843 | K5: 6.5729288 | L5: 4.9964566 | M5: 8.021603 | N5: 2.6141655 | O5: 8.8382631 | P5: 7.226283 | Q5: 7.1424819 | R5: 3.6015982 | S5: 6.2407324 | T5: 7.0394181 | U5: 9.7754252 | V5: 9.5803188 | W5: 9.9859574 | X5: 8.7340384 | Y5: 9.8056066 | Z5: 9.5762693 | AA5: 8.8305906 | AB5: 9.3459166 | AC5: 7.9256402 | AD5: 9.6304313 | AE5: 8.0664198 | AF5: 8.7597997 | AG5: 1.6823523 | AH5: 2.034191 | AI5: 2.1994249 | AJ5: 1.9719894 | AK5: 6.7693528 | AL5: 8.2638661 | AM5: 0.64984122 | AN5: 9.5688935 | AO5: 9.513601 | AP5: 6.9990505 | AQ5: 3.5182033 | AR5: 4.7623884 | AS5: 8.1711281 | AT5: 5.4839066 | AU5: 6.2414785 | AV5: 7.7633283 | AW5: 4.5072545 | AX5: 6.1352914 | AY5: 3.3333333 | AZ5: 5.4961881 | BA5: 4.4147607 | BB5: 5.2750261 | BC5: 8.2181207 | BD5: 7.9423075 | BE5: 8.9572076 | BF5: 8.3725453 | BG5: 8.1760536 | BH5: 8.9167747 | BI5: 8.5464141 | BJ5: 5.9809371 | BK5: 8.7564313 | BL5: 9.6254184 | BM5: 2.9767807 | BN5: 6.8348919 | BO5: 7.9179504 | BP5: 6.2197321 | BQ5: 9.5045249 | BR5: 7.8700471 | BS5: 8.3383793 | BT5: 8.8565891 | BU5: 8.1578545 | BV5: 7.6674465 | BW5: 6.2154223 | BX5: 2.8359975 | BY5: 7.7707571 | BZ5: 6.1224059 | CA5: 7.1401302 | CB5: 4.0705819 | CC5: 3.5619202 | CD5: 5.2407252 | CE5: 4.2910758 | CF5: 10 | CG5: 1.0972232 | CH5: 3.6684855 | CI5: 7.7946952 | CJ5: 5.640101 | CK5: 3.9621085 | CL5: 8.1326935 | CM5: 6.047401 | CN5: 5.3261926 | CO5: 8.7255968 | CP5: 9.9932181 | CQ5: 9.9464027 | CR5: 9.5550725 | CS5: 10 | CT5: 9.576852 | CU5: 8.6821633 | CV5: 9.4196718 | CW5: 9.4873721 | CX5: 6.2763627 | CY5: 7.6253604 | CZ5: 7.2004701 | DA5: 5.5245826 | DB5: 9.152047 | DC5: 7.1557646 | DD5: 3.2599356 | DE5: 5.571848 | DF5: 7.2058629 | DG5: 7.4966282 | DH5: 5.8835687 | DI5: 8.9990162 | DJ5: 8.9990162 | DK5: 9.0079877 | DL5: 3.8267281 | DM5: 6.4173579 | DN5: 7.7081871 | DO5: 8.8267506 | DP5: 9.9629571 | DQ5: 9.3948538 | DR5: 3.3282791 | DS5: 4.7275863 | DT5: 9.5964126 | DU5: 2.6636441 | DV5: 5.0789805 | DW5: 4.7379928 | DX5: 6.373097 | DY5: 4.6637456 | DZ5: 7.9192384 | EA5: 5.9235185 | EB5: 5.5012495 | EC5: 6.9877342
A6: Bucaramanga AM | B6: 2019 | C6: 7.9421361 | D6: 8.1554875 | E6: 8.0488118 | F6: 5.9233181 | G6: 3.2843892 | H6: 8.7690497 | I6: 5.9922523 | J6: 5.5866736 | K6: 1.9091127 | L6: 3.7478931 | M6: 8.2939955 | N6: 6.4466984 | O6: 8.8613556 | P6: 6.7461567 | Q6: 5.3719939 | R6: 4.5364536 | S6: 6.7094423 | T6: 6.1245999 | U6: 6.431903 | V6: 9.5141332 | W6: 9.9363764 | X6: 8.5121262 | Y6: 6.4615611 | Z6: 8.17122 | AA6: 9.1928271 | AB6: 9.5676918 | AC6: 0.9794967 | AD6: 4.3864396 | AE6: 4.1385451 | AF6: 5.6530001 | AG6: 2.2626532 | AH6: 1.6475237 | AI6: 0.60393322 | AJ6: 1.5047034 | AK6: 5.1096411 | AL6: 6.9423397 | AM6: 0.49169784 | AN6: 7.0919271 | AO6: 7.9844421 | AP6: 5.6276017 | AQ6: 3.3371473 | AR6: 4.2493444 | AS6: 7.8789222 | AT6: 5.155138 | AU6: 5.3913698 | AV6: 6.8285054 | AW6: 2.2791932 | AX6: 4.5538493 | AY6: 4.1176471 | AZ6: 2.9816157 | BA6: 3.5496314 | BB6: 4.0517403 | BC6: 7.7264332 | BD6: 8.0854111 | BE6: 9.7815826 | BF6: 8.5311423 | BG6: 9.0465161 | BH6: 9.0639796 | BI6: 9.0552478 | BJ6: 2.9826636 | BK6: 4.1668438 | BL6: 4.2812616 | BM6: 4.1945801 | BN6: 3.9063373 | BO6: 7.1642425 | BP6: 6.321552 | BQ6: 9.2027804 | BR6: 7.6562472 | BS6: 7.3993717 | BT6: 6.8044499 | BU6: 7.4768802 | BV6: 9.2888278 | BW6: 8.9542977 | BX6: 7.7887725 | BY6: 5.4203698 | BZ6: 7.8630669 | CA6: 7.6699736 | CB6: 2.8760035 | CC6: 7.2724943 | CD6: 5.1842696 | CE6: 5.1109225 | CF6: 9.1970195 | CG6: 1.097294 | CH6: 4.6237697 | CI6: 6.4808738 | CJ6: 5.3497392 | CK6: 4.8673594 | CL6: 5.9663475 | CM6: 5.4168535 | CN6: 5.2925051 | CO6: 1.8026384 | CP6: 9.8522977 | CQ6: 9.9692468 | CR6: 7.208061 | CS6: 2.8974129 | CT6: 4.1514969 | CU6: 7.4219239 | CV6: 4.8236112 | CW6: 6.0158361 | CX6: 4.302519 | CY6: 7.9375817 | CZ6: 5.7397438 | DA6: 6.2207209 | DB6: 6.2204491 | DC6: 6.0842029 | DD6: 1.9677681 | DE6: 3.9084664 | DF6: 5.7897452 | DG6: 6.3116887 | DH6: 4.4944171 | DI6: 6.3540258 | DJ6: 6.3540258 | DK6: 8.4274612 | DL6: 0.93332684 | DM6: 4.680394 | DN6: 5.5172099 | DO6: 9.4249965 | DP6: 6.0827242 | DQ6: 7.7538603 | DR6: 2.7898452 | DS6: 4.1967489 | DT6: 6.0986547 | DU6: 3.2020402 | DV6: 4.0718223 | DW6: 2.2641633 | DX6: 2.3078637 | DY6: 1.8133057 | DZ6: 2.5555855 | EA6: 2.2352295 | EB6: 3.1535259 | EC6: 5.6787019
A7: Cali AM | B7: 2019 | C7: 5.8180812 | D7: 8.1420787 | E7: 6.9800799 | F7: 7.3360328 | G7: 4.0063485 | H7: 9.2040943 | I7: 6.8488252 | J7: 5.6487117 | K7: 4.2674671 | L7: 4.9580894 | M7: 2.6707171 | N7: 5.727678 | O7: 8.4714104 | P7: 6.816378 | Q7: 4.8846339 | R7: 4.5357238 | S7: 5.5177569 | T7: 6.0761879 | U7: 7.8399636 | V7: 9.9704557 | W7: 9.9033707 | X7: 8.9521956 | Y7: 8.1363658 | Z7: 8.9604703 | AA7: 8.8502606 | AB7: 9.2676578 | AC7: 2.8641799 | AD7: 5.9366545 | AE7: 8.5020173 | AF7: 7.084154 | AG7: 4.2613101 | AH7: 2.0294112 | AI7: 0.9109247 | AJ7: 2.4005487 | AK7: 6.148391 | AL7: 6.880387 | AM7: 0.53030973 | AN7: 7.23106 | AO7: 8.592928 | AP7: 5.8086712 | AQ7: 2.1746561 | AR7: 2.8367979 | AS7: 5.3908881 | AT7: 3.4674474 | AU7: 4.6380593 | AV7: 5.7009699 | AW7: 2.4277022 | AX7: 4.0643361 | AY7: 2.1568627 | AZ7: 3.7340239 | BA7: 2.9454433 | BB7: 3.5048897 | BC7: 9.5789996 | BD7: 9.6110596 | BE7: 9.6252173 | BF7: 9.6050922 | BG7: 8.0787033 | BH7: 9.4063751 | BI7: 8.7425392 | BJ7: 2.9357607 | BK7: 4.6577582 | BL7: 4.2916355 | BM7: 4.1419013 | BN7: 4.0067639 | BO7: 7.4514651 | BP7: 4.071475 | BQ7: 5.2479358 | BR7: 6.2306428 | BS7: 5.9430774 | BT7: 7.7456052 | BU7: 5.8477472 | BV7: 6.429646 | BW7: 5.1901141 | BX7: 3.3833611 | BY7: 4.2372897 | BZ7: 4.8101027 | CA7: 5.328925 | CB7: 2.2417795 | CC7: 1.3189335 | CD7: 3.2179676 | CE7: 2.2595602 | CF7: 8.3962515 | CG7: 1.5934895 | CH7: 5.2415261 | CI7: 6.520706 | CJ7: 5.4379933 | CK7: 5.9703441 | CL7: 6.6244855 | CM7: 6.2974148 | CN7: 4.6649894 | CO7: 3.7011396 | CP7: 9.845517 | CQ7: 9.8947794 | CR7: 7.813812 | CS7: 4.0901111 | CT7: 4.7883885 | CU7: 8.0635868 | CV7: 5.6473621 | CW7: 6.7305871 | CX7: 4.6880231 | CY7: 6.9822217 | CZ7: 5.7913441 | DA7: 3.5600013 | DB7: 8.0239913 | DC7: 5.8091163 | DD7: 2.0295518 | DE7: 4.0798273 | DF7: 5.1643345 | DG7: 7.0287549 | DH7: 4.5756171 | DI7: 7.1542177 | DJ7: 7.1542177 | DK7: 8.7377168 | DL7: 2.3130915 | DM7: 5.5254041 | DN7: 6.3398109 | DO7: 9.4879697 | DP7: 9.943693 | DQ7: 9.7158314 | DR7: 3.0895781 | DS7: 3.4681709 | DT7: 6.7713004 | DU7: 3.2558799 | DV7: 4.1462323 | DW7: 2.6785579 | DX7: 3.5703354 | DY7: 1.6104151 | DZ7: 4.7573384 | EA7: 3.1541617 | EB7: 3.650197 | EC7: 5.7410821
A8: Cartagena | B8: 2019 | C8: 7.3745126 | D8: 7.9779481 | E8: 7.6762304 | F8: 6.1879828 | G8: 4.1068176 | H8: 8.5078493 | I8: 6.2675499 | J8: 8.9837611 | K8: 2.8422725 | L8: 5.9130168 | M8: 6.81239 | N8: 7.1496078 | O8: 8.7656574 | P8: 7.1422087 | Q8: 4.4389181 | R8: 2.58553 | S8: 6.149052 | T8: 6.5014623 | U8: 3.5222681 | V8: 9.2410393 | W8: 9.4425882 | X8: 9.4012491 | Y8: 4.394764 | Z8: 7.2003817 | AA8: 9.5459286 | AB8: 9.5511891 | AC8: 3.2422298 | AD8: 7.267229 | AE8: 6.4502533 | AF8: 7.211366 | AG8: 1.6488332 | AH8: 2.2630357 | AI8: 10 | AJ8: 4.6372896 | AK8: 6.3496791 | AL8: 5.037742 | AM8: 0.52527963 | AN8: 3.6269514 | AO8: 5.0833524 | AP8: 3.5683314 | AQ8: 1.7103458 | AR8: 2.7994739 | AS8: 4.6968623 | AT8: 3.068894 | AU8: 3.3186127 | AV8: 3.3691116 | AW8: 2.3607467 | AX8: 2.8649291 | AY8: 0 | AZ8: 2.3933355 | BA8: 1.1966677 | BB8: 2.0307984 | BC8: 8.4293106 | BD8: 7.9309715 | BE8: 9.1740372 | BF8: 8.5114397 | BG8: 6.3637569 | BH8: 8.4679684 | BI8: 7.4158626 | BJ8: 1.8080509 | BK8: 3.29311 | BL8: 2.9785235 | BM8: 5.1096414 | BN8: 3.2973315 | BO8: 6.4082113 | BP8: 6.7375064 | BQ8: 10 | BR8: 8.6685896 | BS8: 8.0605521 | BT8: 7.5872093 | BU8: 8.2107715 | BV8: 3.9078281 | BW8: 2.1732153 | BX8: 3.4897763 | BY8: 2.1969428 | BZ8: 2.9419406 | CA8: 5.5763561 | CB8: 2.332346 | CC8: 1.3686945 | CD8: 6.4147205 | CE8: 3.3719203 | CF8: 7.7346031 | CG8: 0.79254079 | CH8: 4.6887524 | CI8: 5.2482411 | CJ8: 4.6160343 | CK8: 7.8610537 | CL8: 3.2125175 | CM8: 5.5367856 | CN8: 4.5082467 | CO8: 4.9721158 | CP8: 5.6231466 | CQ8: 9.8228629 | CR8: 6.8060418 | CS8: 5.4460069 | CT8: 4.4344071 | CU8: 7.6002639 | CV8: 5.8268926 | CW8: 6.3164672 | CX8: 4.9447094 | CY8: 8.6370895 | CZ8: 5.0773354 | DA8: 5.9706303 | DB8: 5.2138169 | DC8: 5.9687163 | DD8: 1.5297403 | DE8: 3.2687115 | DF8: 1.7964404 | DG8: 3.266241 | DH8: 2.4652833 | DI8: 6.1286716 | DJ8: 6.1286716 | DK8: 8.7705875 | DL8: 5.1165015 | DM8: 6.9435445 | DN8: 6.5361081 | DO8: 9.3725188 | DP8: 9.3598784 | DQ8: 9.3661986 | DR8: 2.1506066 | DS8: 2.8154241 | DT8: 0 | DU8: 3.3833947 | DV8: 2.0873564 | DW8: 0.3296218 | DX8: 0.35698278 | DY8: 0.99727659 | DZ8: 1.4588185 | EA8: 0.78567492 | EB8: 1.4365156 | EC8: 5.1371274
A9: Cúcuta AM | B9: 2019 | C9: 4.7260647 | D9: 7.0864073 | E9: 5.906236 | F9: 2.9648806 | G9: 3.9079756 | H9: 8.637621 | I9: 5.1701591 | J9: 3.6537454 | K9: 1.3689623 | L9: 2.5113538 | M9: 6.3555429 | N9: 8.2129992 | O9: 7.4399273 | P9: 7.4035932 | Q9: 6.0665114 | R9: 5.8007449 | S9: 6.8798865 | T9: 5.1169088 | U9: 6.3421072 | V9: 6.9040666 | W9: 9.7531196 | X9: 7.999232 | Y9: 6.8720825 | Z9: 7.5741216 | AA9: 9.6197677 | AB9: 9.9796257 | AC9: 0.55541285 | AD9: 4.0012733 | AE9: 3.3443737 | AF9: 5.5000906 | AG9: 1.8342101 | AH9: 0.92853296 | AI9: 2.5163259 | AJ9: 1.7596897 | AK9: 4.944634 | AL9: 4.2461571 | AM9: 0.45705504 | AN9: 5.1583129 | AO9: 6.761601 | AP9: 4.1557815 | AQ9: 1.9819903 | AR9: 2.8328874 | AS9: 5.1382734 | AT9: 3.317717 | AU9: 3.7367493 | AV9: 4.7681561 | AW9: 3.446071 | AX9: 4.1071135 | AY9: 1.5686275 | AZ9: 2.203033 | BA9: 1.8858302 | BB9: 2.9964719 | BC9: 10 | BD9: 9.7212604 | BE9: 9.0535252 | BF9: 9.5915952 | BG9: 7.6474784 | BH9: 8.912246 | BI9: 8.2798622 | BJ9: 2.2049774 | BK9: 1.9866692 | BL9: 2.1283767 | BM9: 2.9043359 | BN9: 2.3060898 | BO9: 6.7258491 | BP9: 5.9485392 | BQ9: 8.2577491 | BR9: 7.0222173 | BS9: 6.2918755 | BT9: 6.8733106 | BU9: 6.8787383 | BV9: 6.6365727 | BW9: 6.8396925 | BX9: 6.8293965 | BY9: 3.4421486 | BZ9: 5.9369526 | CA9: 6.4078455 | CB9: 2.4471049 | CC9: 1.0068843 | CD9: 2.7743881 | CE9: 2.0761258 | CF9: 6.9416709 | CG9: 0.82032446 | CH9: 1.8187721 | CI9: 2.3742716 | CJ9: 2.9887598 | CK9: 7.4948415 | CL9: 2.8457383 | CM9: 5.1702899 | CN9: 3.4117251 | CO9: 2.20348 | CP9: 9.9007281 | CQ9: 9.9433343 | CR9: 7.3491808 | CS9: 2.1244363 | CT9: 1.8670347 | CU9: 5.8471315 | CV9: 3.2795341 | CW9: 5.3143575 | CX9: 4.8184339 | CY9: 5.7403321 | CZ9: 3.133142 | DA9: 3.0361802 | DB9: 2.703323 | DC9: 3.8862822 | DD9: 0.82901251 | DE9: 1.679662 | DF9: 2.1729182 | DG9: 3.3756 | DH9: 2.0142982 | DI9: 5.2158903 | DJ9: 5.2158903 | DK9: 8.1448299 | DL9: 0.74535129 | DM9: 4.4450906 | DN9: 4.8304904 | DO9: 9.687385 | DP9: 6.8750628 | DQ9: 8.2812239 | DR9: 0.47399146 | DS9: 1.1668805 | DT9: 5.0224215 | DU9: 4.2207424 | DV9: 2.721009 | DW9: 0.34507944 | DX9: 1.8686176 | DY9: 0.52202197 | DZ9: 1.3529822 | EA9: 1.0221753 | EB9: 1.8715921 | EC9: 4.5798791
A10: Florencia | B10: 2019 | C10: 5.3079253 | D10: 5.614257 | E10: 5.4610911 | F10: 2.1500443 | G10: 2.5174369 | H10: 6.184806 | I10: 3.617429 | J10: 5.2200105 | K10: 0.99370739 | L10: 3.1068589 | M10: 6.9292528 | N10: 6.1205847 | O10: 6.2308103 | P10: 7.009336 | Q10: 8.1089783 | R10: 5.6238004 | S10: 6.6704604 | T10: 4.7139599 | U10: 7.0049682 | V10: 8.7890267 | W10: 8.7461015 | X10: 7.6021867 | Y10: 7.4686722 | Z10: 7.9221911 | AA10: 6.4690899 | AB10: 6.8095719 | AC10: 0.062171808 | AD10: 1.8971829 | AE10: 3.6839859 | AF10: 3.7844005 | AG10: 1.5539484 | AH10: 1.3301252 | AI10: 0.62689419 | AJ10: 1.1703226 | AK10: 4.2923047 | AL10: 3.6855924 | AM10: 0.30065948 | AN10: 3.9192814 | AO10: 5.2442254 | AP10: 3.2874397 | AQ10: 1.5729301 | AR10: 1.5257557 | AS10: 7.1754417 | AT10: 3.4247092 | AU10: 3.3560744 | AV10: 6.2795346 | AW10: 1.0172463 | AX10: 3.6483904 | AY10: 8.627451 | AZ10: 2.8963463 | BA10: 5.7618987 | BB10: 4.7051445 | BC10: 5.0228109 | BD10: 6.3133685 | BE10: 8.3797499 | BF10: 6.5719764 | BG10: 8.5174198 | BH10: 8.8378052 | BI10: 8.6776125 | BJ10: 1.4817711 | BK10: 1.2344812 | BL10: 1.0710357 | BM10: 4.979719 | BN10: 2.1917517 | BO10: 5.8137802 | BP10: 6.0922205 | BQ10: 9.5701357 | BR10: 6.8392288 | BS10: 5.4336598 | BT10: 5.629845 | BU10: 6.713018 | BV10: 5.8227848 | BW10: 5.9084541 | BX10: 8.1957535 | BY10: 5.0973902 | BZ10: 6.2560957 | CA10: 6.4845568 | CB10: 2.9671903 | CC10: 1.3509699 | CD10: 1.4697735 | CE10: 1.9293112 | CF10: 6.0281502 | CG10: 0.52770449 | CH10: 0.1216277 | CI10: 2.3128596 | CJ10: 2.2475855 | CK10: 0 | CL10: 2.6515543 | CM10: 1.3257772 | CN10: 1.8342246 | CO10: 2.9036005 | CP10: 9.5511611 | CQ10: 9.4782202 | CR10: 7.3109939 | CS10: 2.2712469 | CT10: 1.2585642 | CU10: 4.7117581 | CV10: 2.7471897 | CW10: 5.0290918 | CX10: 3.6996459 | CY10: 6.6163102 | CZ10: 4.6567228 | DA10: 6.2982692 | DB10: 6.1434187 | DC10: 5.4828734 | DD10: 2.212391 | DE10: 3.168438 | DF10: 1.2056576 | DG10: 4.1001417 | DH10: 2.6716571 | DI10: 3.2342979 | DJ10: 3.2342979 | DK10: 6.0587097 | DL10: 0.0070581349 | DM10: 3.0328839 | DN10: 3.1335909 | DO10: 5.8460168 | DP10: 6.2526865 | DQ10: 6.0493516 | DR10: 0 | DS10: 2.2429388 | DT10: 6.2780269 | DU10: 2.1479173 | DV10: 2.6672207 | DW10: 0.95261201 | DX10: 0 | DY10: 0 | DZ10: 0.38198727 | EA10: 0.33364982 | EB10: 1.5004353 | EC10: 4.2359266
A11: Ibagué | B11: 2019 | C11: 5.9083682 | D11: 7.2758934 | E11: 6.5921308 | F11: 3.5953638 | G11: 2.1504696 | H11: 8.1424876 | I11: 4.6294403 | J11: 3.0447878 | K11: 5.6433555 | L11: 4.3440717 | M11: 7.8681106 | N11: 5.9518751 | O11: 8.0745662 | P11: 6.1109756 | Q11: 4.0711577 | R11: 6.3340892 | S11: 6.4017957 | T11: 5.4918596 | U11: 4.294041 | V11: 9.6423383 | W11: 9.7750737 | X11: 9.1871513 | Y11: 5.1452263 | Z11: 7.6087661 | AA11: 9.9534542 | AB11: 10 | AC11: 0.071309436 | AD11: 3.5938246 | AE11: 5.4590122 | AF11: 5.8155201 | AG11: 1.7876895 | AH11: 2.1184761 | AI11: 1.9968953 | AJ11: 1.967687 | AK11: 5.1306577 | AL11: 6.7673121 | AM11: 0.44074085 | AN11: 5.9627141 | AO11: 7.6113844 | AP11: 5.1955379 | AQ11: 3.3439399 | AR11: 6.6170926 | AS11: 5.4869113 | AT11: 5.1493146 | AU11: 5.1724262 | AV11: 6.6975242 | AW11: 2.1725399 | AX11: 4.435032 | AY11: 4.1176471 | AZ11: 3.2575228 | BA11: 3.6875849 | BB11: 4.0613085 | BC11: 8.0336607 | BD11: 7.0292098 | BE11: 9.5710438 | BF11: 8.2113047 | BG11: 8.7072723 | BH11: 9.7245642 | BI11: 9.2159182 | BJ11: 2.0355532 | BK11: 2.2670544 | BL11: 2.0819069 | BM11: 4.0797042 | BN11: 2.6160547 | BO11: 6.6810925 | BP11: 7.5953117 | BQ11: 10 | BR11: 8.1448307 | BS11: 7.3731077 | BT11: 8.0813953 | BU11: 8.2389291 | BV11: 6.4556962 | BW11: 6.3226836 | BX11: 5.2348144 | BY11: 6.2522467 | BZ11: 6.0663602 | CA11: 7.1526447 | CB11: 2.7518364 | CC11: 1.0319018 | CD11: 5.502139 | CE11: 3.0952924 | CF11: 7.7739171 | CG11: 1.2399541 | CH11: 5.3510386 | CI11: 3.3383159 | CJ11: 4.4258064 | CK11: 4.7068677 | CL11: 3.8516723 | CM11: 4.27927 | CN11: 3.9334563 | CO11: 6.8371573 | CP11: 9.8510296 | CQ11: 2.178383 | CR11: 6.2888566 | CS11: 2.9318916 | CT11: 2.8994861 | CU11: 4.701555 | CV11: 3.5109776 | CW11: 4.8999171 | CX11: 3.5886101 | CY11: 5.7912296 | CZ11: 5.7447328 | DA11: 4.8097053 | DB11: 7.6220531 | DC11: 5.5112662 | DD11: 2.0473621 | DE11: 4.1239372 | DF11: 2.3283764 | DG11: 4.8323205 | DH11: 3.332999 | DI11: 5.0135572 | DJ11: 5.0135572 | DK11: 7.9192552 | DL11: 0.3997024 | DM11: 4.1594788 | DN11: 4.586518 | DO11: 8.3334602 | DP11: 6.3900454 | DQ11: 7.3617528 | DR11: 1.1437374 | DS11: 2.4421457 | DT11: 7.3542601 | DU11: 3.5279116 | DV11: 3.6170137 | DW11: 0.90837136 | DX11: 1.311697 | DY11: 1.8321958 | DZ11: 1.7762674 | EA11: 1.4571329 | EB11: 2.5370733 | EC11: 5.0656132
A12: Inírida | B12: 2019 | C12: 2.5360888 | D12: 3.598791 | E12: 3.0674399 | F12: 1.6514007 | G12: 1.2280172 | H12: 6.9909416 | I12: 3.2901199 | J12: 2.0547407 | K12: 0.011648224 | L12: 1.0331945 | M12: 8.7049665 | N12: 8.7313414 | O12: 3.1685509 | P12: 0 | Q12: 2.4483685 | R12: 9.5238095 | S12: 5.4295061 | T12: 3.2050651 | U12: 0.051949763 | V12: NA | W12: 5.430032 | X12: 6.5276236 | Y12: 1.1468447 | Z12: 3.2891125 | AA12: NA | AB12: NA | AC12: 0.025363771 | AD12: 0.10186217 | AE12: NA | AF12: 0.063612969 | AG12: 6.0650933 | AH12: 6.951841 | AI12: 0 | AJ12: 4.3389781 | AK12: 2.5639012 | AL12: 0.85001641 | AM12: 0.0014639451 | AN12: 2.0912455 | AO12: 1.2546185 | AP12: 1.0493361 | AQ12: 1.1117341 | AR12: 0.78880333 | AS12: 7.8789222 | AT12: 3.2598199 | AU12: 2.154578 | AV12: 6.0406476 | AW12: 4.9776947 | AX12: 5.5091711 | AY12: 3.7254902 | AZ12: 4.4124956 | BA12: 4.0689929 | BB12: 4.789082 | BC12: 10 | BD12: 10 | BE12: 1.5741758 | BF12: 7.1913919 | BG12: 5.9980519 | BH12: 7.1737537 | BI12: 6.5859028 | BJ12: 2.1534952 | BK12: 1.0602575 | BL12: 0.85862225 | BM12: 1.4777441 | BN12: 1.3875298 | BO12: 5.0549415 | BP12: 3.7068521 | BQ12: 3.3914027 | BR12: 0.53286777 | BS12: 0 | BT12: 3.7015504 | BU12: 2.2665346 | BV12: 4.1772152 | BW12: 4.6967917 | BX12: 0.20711466 | BY12: 3.7400827 | BZ12: 3.2053011 | CA12: 2.7359178 | CB12: 0.27557651 | CC12: 0.16449146 | CD12: 2.0155691 | CE12: 0.81854569 | CF12: 4.7200497 | CG12: 0 | CH12: 0.45541159 | CI12: 0.9355685 | CJ12: 1.5277575 | CK12: 0 | CL12: 3.085106 | CM12: 1.542553 | CN12: 1.2962854 | CO12: 0 | CP12: 7.3401183 | CQ12: 9.5974946 | CR12: 5.645871 | CS12: 1.1304665 | CT12: 0.44733147 | CU12: 1.5268482 | CV12: 1.034882 | CW12: 3.3403765 | CX12: 2.4577623 | CY12: 7.6416244 | CZ12: 4.6464081 | DA12: 3.9458001 | DB12: 4.2136536 | DC12: 4.5810497 | DD12: 0 | DE12: 3.5828049 | DF12: 0 | DG12: 0.054985602 | DH12: 0.90944763 | DI12: 0.868302 | DJ12: 0.868302 | DK12: 5.8409965 | DL12: 0.02873632 | DM12: 2.9348664 | DN12: 1.9015842 | DO12: 1.7527555 | DP12: 1.6991148 | DQ12: 1.7259351 | DR12: 0 | DS12: 0 | DT12: 0 | DU12: 0 | DV12: 0 | DW12: 0 | DX12: 0 | DY12: 0 | DZ12: 0 | EA12: 0 | EB12: 0 | EC12: 2.6352434
